Workbook
Name FN_5: '4'!#REF!
Name FN_5: #REF!
Name FN_5: #REF!
Name FN_5.10: '4'!#REF!
Name FN_5.10: #REF!
Name FN_5.10: #REF!
Name FN_5.11: '4'!#REF!
Name FN_5.11: #REF!
Name FN_5.11: #REF!
Name FN_5.12: '4'!#REF!
Name FN_5.12: #REF!
Name FN_5.12: #REF!
Name FN_5.13: '4'!#REF!
Name FN_5.13: #REF!
Name FN_5.13: #REF!
Name FN_5.2: '4'!#REF!
Name FN_5.2: #REF!
Name FN_5.2: #REF!
Name FN_5.3: '4'!#REF!
Name FN_5.3: #REF!
Name FN_5.3: #REF!
Name FN_5.4: '4'!#REF!
Name FN_5.4: #REF!
Name FN_5.4: #REF!
Name FN_5.5: '4'!#REF!
Name FN_5.5: #REF!
Name FN_5.5: #REF!
Name FN_5.6: '4'!#REF!
Name FN_5.6: #REF!
Name FN_5.6: #REF!
Name FN_5.7: '4'!#REF!
Name FN_5.7: #REF!
Name FN_5.7: #REF!
Name FN_5.8: '4'!#REF!
Name FN_5.8: #REF!
Name FN_5.8: #REF!
Name FN_5.9: '4'!#REF!
Name FN_5.9: #REF!
Name FN_5.9: #REF!
Name RF: #REF!
Name 기초가격: #REF!
Name 만기: #REF!
Name 주가상승계수: #REF!
Name 주가하락계수: #REF!
Name 행사가격: #REF!
Name 행사시작일: #REF!
Name 행사종료일: #REF!
Name 헷지확률: #REF!

Sheet A0
D5: 회사명 | E5: 주식회사 울트라브이와 그 종속기업
D6: 당기개시사업년도 | E6: 46023
D7: 당기종료사업년도 | E7: 46203
D8: 전기개시사업년도 | E8: 45658
D9: 전기종료사업년도 | E9: 46022
D10: 전분기종료사업년도 | E10: 45838
D11: 당기기수 | E11: 15
D12: 전기기수 | E12: 14

Sheet 계정코드
B2: 유동자산 | C2: 10100 | D2: 현금
C3: 10300 | D3: 보통예금
C4: 10400 | D4: 외화보통예금
C5: 10600 | D5: 기타단기금융상품
C6: 10800 | D6: 외상매출금
C7: 10900 | D7: 외상매출금_대손충당금
C8: 11600 | D8: 미수수익
C9: 11700 | D9: 미수수익_대손충당금
C10: 12000 | D10: 미수금
C11: 12100 | D11: 미수금_대손충당금
C12: 12400 | D12: 임차보증금(유동)
C13: 12500 | D13: 임차보증금(유동)_현재가치할인차금
C14: 13100 | D14: 선급금
... C30: 15800 | D30: 재공품재고자산평가충당금
B31: 비유동자산 | C31: 19500 | D31: 당기손익-공정가치금융자산
C32: 17600 | D32: 종속기업투자
C33: 17700 | D33: 관계기업투자
C34: 20100 | D34: 토지
C35: 20200 | D35: 건물
C36: 20300 | D36: 감가상각누계액건물
C37: 20600 | D37: 기계장치
C38: 20700 | D38: 감가상각누계액기계장치
C39: 20800 | D39: 차량운반구
C40: 20900 | D40: 감가상각누계액차량운반구
C41: 21000 | D41: 공구와기구
C42: 21100 | D42: 감가상각누계액공구와기구
C43: 21200 | D43: 비품
... C65: 19600 | D65: 이연법인세자산
B66: 유동부채 | C66: 25100 | D66: 외상매입금
C67: 25300 | D67: 미지급금
C68: 25400 | D68: 예수금
C69: 25500 | D69: 부가세예수금
C70: 25900 | D70: 선수금
C71: 26000 | D71: 단기차입금
C72: 26200 | D72: 미지급비용
C73: 27500 | D73: 미지급법인세
C74: 28100 | D74: 반품충당부채
C75: 28200 | D75: 유동성장기차입금
C76: 28300 | D76: 유동성리스부채
B77: 비유동부채 | C77: 29300 | D77: 장기차입금
C78: 29500 | D78: 퇴직급여충당금
C79: 31100 | D79: 신주인수권부사채
C80: 31200 | D80: 사채상환할증금
C81: 31300 | D81: 신주인수권조정
C82: 31500 | D82: 리스부채
C83: 31600 | D83: 기타장기종업원급여채무
C84: 31700 | D84: 이연법인세부채
C85: 31800 | D85: 장기미지급금
C86: 31900 | D86: 장기미지급금_현재가치할인차금
C87: 32000 | D87: 복구충당부채
B88: 자본 | C88: 33100 | D88: 자본금
C89: 33200 | D89: 우선주자본금
C90: 34100 | D90: 주식발행초과금
C91: 34300 | D91: 신주인수권대가
C92: 34400 | D92: 주식선택권
C93: 34500 | D93: 기타자본잉여금
C94: 35100 | D94: 주식할인발행차금
C95: 39700 | D95: 보험수리적손익누계액
C96: 39800 | D96: 해외사업환산차이
C97: 37600 | D97: 이월결손금
C98: 37700 | D98: 처분전이익잉여금
C101: 40100 | D101: 상품매출
C102: 40400 | D102: 제품매출
... C123: 48400 | D123: 기말상품재고액(식음료)
B124: 제조원가 | C124: 50100 | D124: 원재료비
C125: 50300 | D125: 급여
C126: 50500 | D126: 상여금
C127: 51000 | D127: 퇴직급여
C128: 51100 | D128: 복리후생비
C129: 51200 | D129: 여비교통비
C130: 51400 | D130: 통신비
C131: 51500 | D131: 가스수도료
C132: 51600 | D132: 전력비
C133: 51700 | D133: 세금과공과금
C134: 51800 | D134: 감가상각비
C135: 51900 | D135: 지급임차료
C136: 52000 | D136: 수선비
... C146: 54000 | D146: 무형고정자산상각
B147: 판매관리비 | C147: 80200 | D147: 직원급여
C148: 80300 | D148: 상여금
C149: 80800 | D149: 퇴직급여
C150: 85200
C151: 81000 | D151: 주식보상비
C152: 81100 | D152: 복리후생비
C153: 81200 | D153: 여비교통비
C154: 81300 | D154: 접대비
C155: 81400 | D155: 통신비
C156: 81500 | D156: 수도광열비
C157: 81600 | D157: 전력비
C158: 81700 | D158: 세금과공과금
C159: 81800 | D159: 감가상각비
C160: 81900 | D160: 지급임차료
C161: 82000 | D161: 수선비
C162: 82100 | D162: 보험료
... C180: 85300 | D180: 보관료
B181: 영업외수익 | C181: 91100 | D181: 상품평가손실환입
C182: 91200 | D182: 제품평가손실환입
C183: 90100 | D183: 이자수익
C184: 90700 | D184: 외환차익
C185: 91000 | D185: 외화환산이익
...

Sheet 환율
B3: 기준일 | C3: 46203
B5: 통화 | C5: HKD
B6: 평균환율 | C6: 189.66
B7: 기말환율 | C7: 196.6
B16: 통화 | C16: RMB(CNH)
B17: 평균환율 | C17: 216.23
B18: 기말환율 | C18: 226.97
Q20: =ROUND(SUM(E116:E118,E130:E132)*환율!C7,) -> 0
B23: 통화 | C23: SGD
B24: 평균환율 | C24: 1160.66
B25: 기말환율 | C25: 1192.74

Sheet >>BSPL

Sheet 연결PL
B1: 계정과목 | C1: 주석 | D1: =연결BS!D1 -> 46203 | E1: =A0!E10 -> 45838
B2: 매출액 | D2: =SUM(D3:D6) -> 8812244469 | E2: 9441165967
B3: 상품매출 | D3: =SUMIF(PL!$AC:$AC,연결PL!B3,PL!$Y:$Y) -> 1181126900 | E3: 1049196780
B4: 제품매출 | D4: =SUMIF(PL!$AC:$AC,연결PL!B4,PL!$Y:$Y) -> 7595910549 | E4: 8347940342
B5: 서비스매출 | D5: =SUMIF(PL!$AC:$AC,연결PL!B5,PL!$Y:$Y) -> 0 | E5: 0
B6: 식음료매출 | D6: =SUMIF(PL!$AC:$AC,연결PL!B6,PL!$Y:$Y) -> 35207020 | E6: 44028845
B7: 매출원가 | D7: =SUM(D8,D15,D22,D28) -> 3634217621 | E7: 3581100990
B8: (1)제품매출원가 | D8: =SUM(D11:D13)-D14 -> 3389356072 | E8: 3467738461
B9: 기초제품재고액 | D9: =SUMIF(PL!$AC:$AC,연결PL!B9,PL!$Y:$Y) -> 2349819825 | E9: 2459042471
B10: 당기제품제조원가 | D10: =SUMIF(PL!$AC:$AC,연결PL!B10,PL!$Y:$Y) -> 3476800819 | E10: 3344382182
B11: 계(제품) | D11: =SUM(D9:D10) -> 5826620644 | E11: 5803424653
B12: 타계정대체(제품) | D12: =SUMIF(PL!$AC:$AC,연결PL!B12,PL!$Y:$Y) -> -5296679 | E12: -6471662
B13: 재고자산평가(제품) | D13: =SUMIF(PL!$AC:$AC,연결PL!B13,PL!$Y:$Y) -> 102749779 | E13: 8624839
B14: 기말제품재고액 | D14: =SUMIF(PL!$AC:$AC,연결PL!B14,PL!$Y:$Y) -> 2534717672 | E14: 2337839369
B15: (2)상품매출원가 | D15: =SUM(D18:D20)-D21 -> 234624705 | E15: 99559984
B16: 기초상품재고액(상품) | D16: =SUMIF(PL!$AC:$AC,연결PL!B16,PL!$Y:$Y) -> 137397633 | E16: 132365368
B17: 당기상품제조원가(상품) | D17: =SUMIF(PL!$AC:$AC,연결PL!B17,PL!$Y:$Y) -> 287806604 | E17: 182932057
B18: 계(상품) | D18: =SUM(D16:D17) -> 425204237 | E18: 315297425
B19: 타계정대체(상품) | D19: =SUMIF(PL!$AC:$AC,연결PL!B19,PL!$Y:$Y) -> -894006 | E19: 0
B20: 재고자산평가(상품) | D20: =SUMIF(PL!$AC:$AC,연결PL!B20,PL!$Y:$Y) -> -14089 | E20: 0
B21: 기말상품재고액(상품) | D21: =SUMIF(PL!$AC:$AC,연결PL!B21,PL!$Y:$Y) -> 189671437 | E21: 215737441
B22: (3)서비스매출원가 | D22: =D25-D26-D27 -> 0 | E22: 0
B23: 기초상품재고액(서비스) | D23: =SUMIF(PL!$AC:$AC,연결PL!B23,PL!$Y:$Y) -> 0 | E23: 0
B24: 당기상품제조원가(서비스) | D24: =SUMIF(PL!$AC:$AC,연결PL!B24,PL!$Y:$Y) -> 0 | E24: 0
B25: 계(서비스) | D25: =SUM(D23:D24) -> 0 | E25: 0
B26: 타계정대체(서비스) | D26: =SUMIF(PL!$AC:$AC,연결PL!B26,PL!$Y:$Y) -> 0 | E26: 0
B27: 기말상품재고액(서비스) | D27: =SUMIF(PL!$AC:$AC,연결PL!B27,PL!$Y:$Y) -> 0 | E27: 0
B28: (4)식음료매출원가 | D28: =D31-D32-D33 -> 10236844 | E28: 13802545
B29: 기초상품재고액(식음료) | D29: =SUMIF(PL!$AC:$AC,연결PL!B29,PL!$Y:$Y) -> 0 | E29: 0
B30: 당기상품제조원가(식음료) | D30: =SUMIF(PL!$AC:$AC,연결PL!B30,PL!$Y:$Y) -> 10236844 | E30: 13802545
B31: 계(식음료) | D31: =SUM(D29:D30) -> 10236844 | E31: 13802545
B32: 타계정대체(식음료) | D32: =SUMIF(PL!$AC:$AC,연결PL!B32,PL!$Y:$Y) -> 0 | E32: 0
B33: 기말상품재고액(식음료) | D33: =SUMIF(PL!$AC:$AC,연결PL!B33,PL!$Y:$Y) -> 0 | E33: 0
B34: 매출총이익 | D34: =D2-D7 -> 5178026848 | E34: 5860064977
B35: 판매비와관리비 | D35: =SUM(D36:D67) -> 5969068326 | E35: 4763859751
B36: 급여 | D36: =SUMIF(PL!$AC:$AC,연결PL!B36,PL!$Y:$Y) -> 1503402249 | E36: 1770176545
B37: 퇴직급여 | D37: =SUMIF(PL!$AC:$AC,연결PL!B37,PL!$Y:$Y) -> 110359296 | E37: 104651910
B38: 해고급여 | D38: =SUMIF(PL!$AC:$AC,연결PL!B38,PL!$Y:$Y) -> 45930430
B39: 주식보상비 | D39: =SUMIF(PL!$AC:$AC,연결PL!B39,PL!$Y:$Y) -> 0 | E39: 0
B40: 복리후생비 | D40: =SUMIF(PL!$AC:$AC,연결PL!B40,PL!$Y:$Y) -> 197164634 | E40: 203301261
B41: 여비교통비 | D41: =SUMIF(PL!$AC:$AC,연결PL!B41,PL!$Y:$Y) -> 231770961 | E41: 289230504
B42: 접대비 | D42: =SUMIF(PL!$AC:$AC,연결PL!B42,PL!$Y:$Y) -> 35747090 | E42: 90031148
B43: 통신비 | D43: =SUMIF(PL!$AC:$AC,연결PL!B43,PL!$Y:$Y) -> 13834390 | E43: 14000818
B44: 수도광열비 | D44: =SUMIF(PL!$AC:$AC,연결PL!B44,PL!$Y:$Y) -> 4711948 | E44: 4497562
B45: 전력비 | D45: =SUMIF(PL!$AC:$AC,연결PL!B45,PL!$Y:$Y) -> 3879022 | E45: 3182290
B46: 세금과공과금 | D46: =SUMIF(PL!$AC:$AC,연결PL!B46,PL!$Y:$Y) -> 8510049 | E46: 9690415
B47: 감가상각비 | D47: =SUMIF(PL!$AC:$AC,연결PL!B47,PL!$Y:$Y) -> 181372149 | E47: 222390521
B48: 지급임차료 | D48: =SUMIF(PL!$AC:$AC,연결PL!B48,PL!$Y:$Y) -> 89571233 | E48: 32002073
B49: 수선비 | D49: =SUMIF(PL!$AC:$AC,연결PL!B49,PL!$Y:$Y) -> 2127578 | E49: 2184493
B50: 보험료 | D50: =SUMIF(PL!$AC:$AC,연결PL!B50,PL!$Y:$Y) -> 4498285 | E50: 10243379
... B67: 인력개발비 | D67: =SUMIF(PL!$AC:$AC,연결PL!B67,PL!$Y:$Y) -> 1380000 | E67: 1378699
B68: 영업이익(손실) | D68: =D34-D35 -> -791041478 | E68: 1096205226
B69: 기타영업수익 | D69: =SUM(D70:D76) -> 2109602184 | E69: 8256143
B70: 외환차익(기타) | D70: =SUMIF(PL!$AC:$AC,연결PL!B70,PL!$Y:$Y) -> 0 | E70: 0
B71: 외화환산이익(기타) | D71: =SUMIF(PL!$AC:$AC,연결PL!B71,PL!$Y:$Y) -> 0 | E71: 0
B72: 수입임대료 | D72: =SUMIF(PL!$AC:$AC,연결PL!B72,PL!$Y:$Y) -> 0 | E72: 0
B73: 기타의대손상각비환입 | D73: =SUMIF(PL!$AC:$AC,연결PL!B73,PL!$Y:$Y) -> 3000000 | E73: 3000000
B74: 유형자산처분이익 | D74: =SUMIF(PL!$AC:$AC,연결PL!B74,PL!$Y:$Y) -> 1202135 | E74: 1054000
B75: 관계기업투자주식처분이익 | D75: =SUMIF(PL!$AC:$AC,연결PL!B75,PL!$Y:$Y) -> 2067945777 | E75: 0
B76: 잡이익 | D76: =SUMIF(PL!$AC:$AC,연결PL!B76,PL!$Y:$Y) -> 37454272 | E76: 4202143
B77: 기타영업비용 | D77: =SUM(D78:D84) -> 9488772 | E77: 7087062
B78: 기타의대손상각비 | D78: =SUMIF(PL!$AC:$AC,연결PL!B78,PL!$Y:$Y) -> 0 | E78: 0
B79: 기부금 | D79: =SUMIF(PL!$AC:$AC,연결PL!B79,PL!$Y:$Y) -> 132762 | E79: 128604
B80: 외화환산손실(기타) | D80: =SUMIF(PL!$AC:$AC,연결PL!B80,PL!$Y:$Y) -> 0 | E80: 0
B81: 유형자산처분손실 | D81: =SUMIF(PL!$AC:$AC,연결PL!B81,PL!$Y:$Y) -> 4825402 | E81: 3098042
B82: 관계기업투자주식처분손실 | D82: =SUMIF(PL!$AC:$AC,연결PL!B82,PL!$Y:$Y) -> 0 | E82: 0
B83: 보상비 | D83: =SUMIF(PL!$AC:$AC,연결PL!B83,PL!$Y:$Y) -> 0 | E83: 0
B84: 잡손실 | D84: =SUMIF(PL!$AC:$AC,연결PL!B84,PL!$Y:$Y) -> 4530608 | E84: 3860416
B85: 금융수익 | D85: =SUM(D86:D89) -> 169546726 | E85: 48738081
B86: 이자수익 | D86: =SUMIF(PL!$AC:$AC,연결PL!B86,PL!$Y:$Y) -> 22101454 | E86: 28253274
B87: 파생금융자산평가이익 | D87: =SUMIF(PL!$AC:$AC,연결PL!B87,PL!$Y:$Y) -> 0 | E87: 0
B88: 외환차익 | D88: =SUMIF(PL!$AC:$AC,연결PL!B88,PL!$Y:$Y) -> 109841433 | E88: 20481765
B89: 외화환산이익 | D89: =SUMIF(PL!$AC:$AC,연결PL!B89,PL!$Y:$Y) -> 37603839 | E89: 3042
B90: 금융비용 | D90: =SUM(D91:D95) -> 273243495 | E90: 145282026
B91: 이자비용 | D91: =SUMIF(PL!$AC:$AC,연결PL!B91,PL!$Y:$Y) -> 98954951 | E91: 45786340
B92: 당기손익-공정가치측정금융자산평가손실 | D92: =SUMIF(PL!$AC:$AC,연결PL!B92,PL!$Y:$Y) -> 0 | E92: 0
B93: 사채상환손실 | D93: =SUMIF(PL!$AC:$AC,연결PL!B93,PL!$Y:$Y) -> 0 | E93: 0
B94: 외환차손 | D94: =SUMIF(PL!$AC:$AC,연결PL!B94,PL!$Y:$Y) -> 174288542 | E94: 41293761
B95: 외화환산손실 | D95: =SUMIF(PL!$AC:$AC,연결PL!B95,PL!$Y:$Y) -> 2 | E95: 58201925
B96: 관계기업투자이익(손실) | D96: =D97-D98 -> -2067945777 | E96: 0
B97: 관계기업투자이익 | D97: =SUMIF(PL!$AC:$AC,연결PL!B97,PL!$Y:$Y) -> 0 | E97: 0
B98: 관계기업투자손실 | D98: =SUMIF(PL!$AC:$AC,연결PL!B98,PL!$Y:$Y) -> 2067945777 | E98: 0
B99: 법인세비용차감전순이익 | D99: =D68+D69-D77+D85-D90+D96 -> -862570612 | E99: 1000830362
B100: 법인세비용 | D100: =SUMIF(PL!$AC:$AC,연결PL!B100,PL!$Y:$Y) -> 4983889 | E100: 4894989
B101: 당기순이익(손실) | D101: =D99-D100 -> -867554501 | E101: 995935373
B102: 1.지배기업소유주지분 | D102: =D101 -> -867554501 | E102: 995935373
B103: 2.비지배주주지분 | D103: 0 | E103: 0
B104: 기타포괄손익 | D104: =D105+D107 -> 11298394 | E104: -26600734
B105: 당기손익으로 재분류되지 않는 포괄손익 | D105: =D106 -> 0 | E105: 0
B106: 종업원급여 재측정요소 | D106: =SUMIF(PL!$AC:$AC,연결PL!B106,PL!$Y:$Y) -> 0 | E106: 0
B107: 후속적으로 당기손익으로 재분류되는 항목 | D107: =D108 -> 11298394 | E107: -26600734
B108: 해외사업환산손익 | D108: =SUMIF(PL!$AC:$AC,연결PL!B108,PL!$Y:$Y) -> 11298394 | E108: -26600734
B109: 총포괄손익 | D109: =D101+D104 -> -856256107 | E109: 969334639
B110: 1.지배기업소유주지분 | D110: =D109 -> -856256107 | E110: 969334639
B111: 2.비지배주주지분 | D111: 0 | E111: 0
B112: 주당이익
B113: 기본주당순이익 | D113: ='31'!D12 -> -76 | E113: 159
B114: 희석주당순이익 | D114: ='31'!D46 -> -76 | E114: 157
D117: =D101-PL!Y113 -> 0

Sheet 연결PL_IFRS18
B1: 연결 손익계산서 정산표 (IFRS 18 기준)
B2: ※ [연결PL]·[PL] 시트의 금액을 그대로 연동하여 IFRS 18 범주(영업·투자·재무·법인세)로 재분류한 연결 손익 정산표입니다. 재분류는 하단 [부록 1] R열(노란색·파란글씨)에서 변경하면 자동 반영됩니다.
D3: =연결PL!D1 -> 46203 | E3: =연결PL!E1 -> 45838
B4: 계정과목 | D4: 당기 연결 | E4: 전기 연결 | G4: =PL!I2 -> 울트라브이 | H4: =PL!J2 -> 울트라브이팜 | I4: =PL!K2 -> ULTRA V HONG KONG LIMITED | J4: =PL!L2 -> DERMASTER HONG KONG LIMITED | K4: =PL!M2 -> ULTRA V SHANGHAI LIMITED | L4: =PL!N2 -> ULTRA V (SG) PTE.LTD (24년 설립) | M4: =PL!O2 -> ATGC | N4: 단순합산 | O4: 연결조정(상계·지분법 등)
B5: Ⅰ. 영업 범주
B6: 매출액 | D6: =SUMIFS(D$69:D$133,$R$69:$R$133,$B6) -> 8812244469 | E6: =SUMIFS(E$69:E$133,$R$69:$R$133,$B6) -> 9441165967 | G6: =SUMIFS(G$69:G$133,$R$69:$R$133,$B6) -> 8288170687 | H6: =SUMIFS(H$69:H$133,$R$69:$R$133,$B6) -> 0 | I6: =SUMIFS(I$69:I$133,$R$69:$R$133,$B6) -> 807627666 | J6: =SUMIFS(J$69:J$133,$R$69:$R$133,$B6) -> 110521930 | K6: =SUMIFS(K$69:K$133,$R$69:$R$133,$B6) -> 0 | L6: =SUMIFS(L$69:L$133,$R$69:$R$133,$B6) -> 0 | M6: =SUMIFS(M$69:M$133,$R$69:$R$133,$B6) -> 0 | N6: =SUMIFS(N$69:N$133,$R$69:$R$133,$B6) -> 9206320283 | O6: =SUMIFS(O$69:O$133,$R$69:$R$133,$B6) -> -394075814
B7: 매출원가 | D7: =SUMIFS(D$69:D$133,$R$69:$R$133,$B7) -> 3634217621 | E7: =SUMIFS(E$69:E$133,$R$69:$R$133,$B7) -> 3581100990 | G7: =SUMIFS(G$69:G$133,$R$69:$R$133,$B7) -> 3596633522 | H7: =SUMIFS(H$69:H$133,$R$69:$R$133,$B7) -> 0 | I7: =SUMIFS(I$69:I$133,$R$69:$R$133,$B7) -> 378103308 | J7: =SUMIFS(J$69:J$133,$R$69:$R$133,$B7) -> 24568846 | K7: =SUMIFS(K$69:K$133,$R$69:$R$133,$B7) -> 0 | L7: =SUMIFS(L$69:L$133,$R$69:$R$133,$B7) -> 0 | M7: =SUMIFS(M$69:M$133,$R$69:$R$133,$B7) -> 0 | N7: =SUMIFS(N$69:N$133,$R$69:$R$133,$B7) -> 3999305676 | O7: =SUMIFS(O$69:O$133,$R$69:$R$133,$B7) -> -365088055
B8: 매출총이익 | D8: =D6-D7 -> 5178026848 | E8: =E6-E7 -> 5860064977 | G8: =G6-G7 -> 4691537165 | H8: =H6-H7 -> 0 | I8: =I6-I7 -> 429524358 | J8: =J6-J7 -> 85953084 | K8: =K6-K7 -> 0 | L8: =L6-L7 -> 0 | M8: =M6-M7 -> 0 | N8: =N6-N7 -> 5207014607 | O8: =O6-O7 -> -28987759
B9: 판매비와관리비 | D9: =SUMIFS(D$69:D$133,$R$69:$R$133,$B9) -> 5969068326 | E9: =SUMIFS(E$69:E$133,$R$69:$R$133,$B9) -> 4763859751 | G9: =SUMIFS(G$69:G$133,$R$69:$R$133,$B9) -> 5378351282 | H9: =SUMIFS(H$69:H$133,$R$69:$R$133,$B9) -> 0 | I9: =SUMIFS(I$69:I$133,$R$69:$R$133,$B9) -> 382954300 | J9: =SUMIFS(J$69:J$133,$R$69:$R$133,$B9) -> 182867798 | K9: =SUMIFS(K$69:K$133,$R$69:$R$133,$B9) -> 15619049 | L9: =SUMIFS(L$69:L$133,$R$69:$R$133,$B9) -> 8656005 | M9: =SUMIFS(M$69:M$133,$R$69:$R$133,$B9) -> 0 | N9: =SUMIFS(N$69:N$133,$R$69:$R$133,$B9) -> 5968448434 | O9: =SUMIFS(O$69:O$133,$R$69:$R$133,$B9) -> 619892
B10: 기타영업수익 | D10: =SUMIFS(D$69:D$133,$R$69:$R$133,$B10) -> 189101679 | E10: =SUMIFS(E$69:E$133,$R$69:$R$133,$B10) -> 28740950 | G10: =SUMIFS(G$69:G$133,$R$69:$R$133,$B10) -> 151841271 | H10: =SUMIFS(H$69:H$133,$R$69:$R$133,$B10) -> 0 | I10: =SUMIFS(I$69:I$133,$R$69:$R$133,$B10) -> 8686 | J10: =SUMIFS(J$69:J$133,$R$69:$R$133,$B10) -> 1183 | K10: =SUMIFS(K$69:K$133,$R$69:$R$133,$B10) -> 37250539 | L10: =SUMIFS(L$69:L$133,$R$69:$R$133,$B10) -> 0 | M10: =SUMIFS(M$69:M$133,$R$69:$R$133,$B10) -> 0 | N10: =SUMIFS(N$69:N$133,$R$69:$R$133,$B10) -> 189101679 | O10: =SUMIFS(O$69:O$133,$R$69:$R$133,$B10) -> 0
B11: 기타영업비용 | D11: =SUMIFS(D$69:D$133,$R$69:$R$133,$B11) -> 183777316 | E11: =SUMIFS(E$69:E$133,$R$69:$R$133,$B11) -> 106582748 | G11: =SUMIFS(G$69:G$133,$R$69:$R$133,$B11) -> 177020574 | H11: =SUMIFS(H$69:H$133,$R$69:$R$133,$B11) -> 0 | I11: =SUMIFS(I$69:I$133,$R$69:$R$133,$B11) -> 2371511 | J11: =SUMIFS(J$69:J$133,$R$69:$R$133,$B11) -> 12851 | K11: =SUMIFS(K$69:K$133,$R$69:$R$133,$B11) -> 4342354 | L11: =SUMIFS(L$69:L$133,$R$69:$R$133,$B11) -> 30026 | M11: =SUMIFS(M$69:M$133,$R$69:$R$133,$B11) -> 0 | N11: =SUMIFS(N$69:N$133,$R$69:$R$133,$B11) -> 183777316 | O11: =SUMIFS(O$69:O$133,$R$69:$R$133,$B11) -> 0
B12: 영업손익 | D12: =D8-D9+D10-D11 -> -785717115 | E12: =E8-E9+E10-E11 -> 1018363428 | G12: =G8-G9+G10-G11 -> -711993420 | H12: =H8-H9+H10-H11 -> 0 | I12: =I8-I9+I10-I11 -> 44207233 | J12: =J8-J9+J10-J11 -> -96926382 | K12: =K8-K9+K10-K11 -> 17289136 | L12: =L8-L9+L10-L11 -> -8686031 | M12: =M8-M9+M10-M11 -> 0 | N12: =N8-N9+N10-N11 -> -756109464 | O12: =O8-O9+O10-O11 -> -29607651
B14: Ⅱ. 투자 범주
B15: 투자수익 | D15: =SUMIFS(D$69:D$133,$R$69:$R$133,$B15) -> 2090047231 | E15: =SUMIFS(E$69:E$133,$R$69:$R$133,$B15) -> 28253274 | G15: =SUMIFS(G$69:G$133,$R$69:$R$133,$B15) -> 22098561 | H15: =SUMIFS(H$69:H$133,$R$69:$R$133,$B15) -> 0 | I15: =SUMIFS(I$69:I$133,$R$69:$R$133,$B15) -> 658 | J15: =SUMIFS(J$69:J$133,$R$69:$R$133,$B15) -> 53 | K15: =SUMIFS(K$69:K$133,$R$69:$R$133,$B15) -> 2182 | L15: =SUMIFS(L$69:L$133,$R$69:$R$133,$B15) -> 0 | M15: =SUMIFS(M$69:M$133,$R$69:$R$133,$B15) -> 0 | N15: =SUMIFS(N$69:N$133,$R$69:$R$133,$B15) -> 22101454 | O15: =SUMIFS(O$69:O$133,$R$69:$R$133,$B15) -> 2067945777
B16: 투자비용 | D16: =SUMIFS(D$69:D$133,$R$69:$R$133,$B16) -> 2067945777 | E16: =SUMIFS(E$69:E$133,$R$69:$R$133,$B16) -> 0 | G16: =SUMIFS(G$69:G$133,$R$69:$R$133,$B16) -> 0 | H16: =SUMIFS(H$69:H$133,$R$69:$R$133,$B16) -> 0 | I16: =SUMIFS(I$69:I$133,$R$69:$R$133,$B16) -> 0 | J16: =SUMIFS(J$69:J$133,$R$69:$R$133,$B16) -> 0 | K16: =SUMIFS(K$69:K$133,$R$69:$R$133,$B16) -> 0 | L16: =SUMIFS(L$69:L$133,$R$69:$R$133,$B16) -> 0 | M16: =SUMIFS(M$69:M$133,$R$69:$R$133,$B16) -> 0 | N16: =SUMIFS(N$69:N$133,$R$69:$R$133,$B16) -> 0 | O16: =SUMIFS(O$69:O$133,$R$69:$R$133,$B16) -> 2067945777
B17: 투자손익 | D17: =D15-D16 -> 22101454 | E17: =E15-E16 -> 28253274 | G17: =G15-G16 -> 22098561 | H17: =H15-H16 -> 0 | I17: =I15-I16 -> 658 | J17: =J15-J16 -> 53 | K17: =K15-K16 -> 2182 | L17: =L15-L16 -> 0 | M17: =M15-M16 -> 0 | N17: =N15-N16 -> 22101454 | O17: =O15-O16 -> 0
B18: 재무 및 법인세 전 손익 | D18: =D12+D17 -> -763615661 | E18: =E12+E17 -> 1046616702 | G18: =G12+G17 -> -689894859 | H18: =H12+H17 -> 0 | I18: =I12+I17 -> 44207891 | J18: =J12+J17 -> -96926329 | K18: =K12+K17 -> 17291318 | L18: =L12+L17 -> -8686031 | M18: =M12+M17 -> 0 | N18: =N12+N17 -> -734008010 | O18: =O12+O17 -> -29607651
B20: Ⅲ. 재무 범주
B21: 재무수익 | D21: =SUMIFS(D$69:D$133,$R$69:$R$133,$B21) -> 0 | E21: =SUMIFS(E$69:E$133,$R$69:$R$133,$B21) -> 0 | G21: =SUMIFS(G$69:G$133,$R$69:$R$133,$B21) -> 0 | H21: =SUMIFS(H$69:H$133,$R$69:$R$133,$B21) -> 0 | I21: =SUMIFS(I$69:I$133,$R$69:$R$133,$B21) -> 0 | J21: =SUMIFS(J$69:J$133,$R$69:$R$133,$B21) -> 0 | K21: =SUMIFS(K$69:K$133,$R$69:$R$133,$B21) -> 0 | L21: =SUMIFS(L$69:L$133,$R$69:$R$133,$B21) -> 0 | M21: =SUMIFS(M$69:M$133,$R$69:$R$133,$B21) -> 0 | N21: =SUMIFS(N$69:N$133,$R$69:$R$133,$B21) -> 0 | O21: =SUMIFS(O$69:O$133,$R$69:$R$133,$B21) -> 0
B22: 재무비용 | D22: =SUMIFS(D$69:D$133,$R$69:$R$133,$B22) -> 98954951 | E22: =SUMIFS(E$69:E$133,$R$69:$R$133,$B22) -> 45786340 | G22: =SUMIFS(G$69:G$133,$R$69:$R$133,$B22) -> 98954951 | H22: =SUMIFS(H$69:H$133,$R$69:$R$133,$B22) -> 0 | I22: =SUMIFS(I$69:I$133,$R$69:$R$133,$B22) -> 0 | J22: =SUMIFS(J$69:J$133,$R$69:$R$133,$B22) -> 0 | K22: =SUMIFS(K$69:K$133,$R$69:$R$133,$B22) -> 0 | L22: =SUMIFS(L$69:L$133,$R$69:$R$133,$B22) -> 0 | M22: =SUMIFS(M$69:M$133,$R$69:$R$133,$B22) -> 0 | N22: =SUMIFS(N$69:N$133,$R$69:$R$133,$B22) -> 98954951 | O22: =SUMIFS(O$69:O$133,$R$69:$R$133,$B22) -> 0
B23: 재무손익 | D23: =D21-D22 -> -98954951 | E23: =E21-E22 -> -45786340 | G23: =G21-G22 -> -98954951 | H23: =H21-H22 -> 0 | I23: =I21-I22 -> 0 | J23: =J21-J22 -> 0 | K23: =K21-K22 -> 0 | L23: =L21-L22 -> 0 | M23: =M21-M22 -> 0 | N23: =N21-N22 -> -98954951 | O23: =O21-O22 -> 0
B25: 법인세비용차감전손익 | D25: =D18+D23 -> -862570612 | E25: =E18+E23 -> 1000830362 | G25: =G18+G23 -> -788849810 | H25: =H18+H23 -> 0 | I25: =I18+I23 -> 44207891 | J25: =J18+J23 -> -96926329 | K25: =K18+K23 -> 17291318 | L25: =L18+L23 -> -8686031 | M25: =M18+M23 -> 0 | N25: =N18+N23 -> -832962961 | O25: =O18+O23 -> -29607651
B26: 법인세비용 | D26: =SUMIFS(D$69:D$133,$R$69:$R$133,$B26) -> 4983889 | E26: =SUMIFS(E$69:E$133,$R$69:$R$133,$B26) -> 4894989 | G26: =SUMIFS(G$69:G$133,$R$69:$R$133,$B26) -> 0 | H26: =SUMIFS(H$69:H$133,$R$69:$R$133,$B26) -> 0 | I26: =SUMIFS(I$69:I$133,$R$69:$R$133,$B26) -> 0 | J26: =SUMIFS(J$69:J$133,$R$69:$R$133,$B26) -> 0 | K26: =SUMIFS(K$69:K$133,$R$69:$R$133,$B26) -> 0 | L26: =SUMIFS(L$69:L$133,$R$69:$R$133,$B26) -> 0 | M26: =SUMIFS(M$69:M$133,$R$69:$R$133,$B26) -> 0 | N26: =SUMIFS(N$69:N$133,$R$69:$R$133,$B26) -> 0 | O26: =SUMIFS(O$69:O$133,$R$69:$R$133,$B26) -> 4983889
B27: 당기순이익(손실) | D27: =D25-D26 -> -867554501 | E27: =E25-E26 -> 995935373 | G27: =G25-G26 -> -788849810 | H27: =H25-H26 -> 0 | I27: =I25-I26 -> 44207891 | J27: =J25-J26 -> -96926329 | K27: =K25-K26 -> 17291318 | L27: =L25-L26 -> -8686031 | M27: =M25-M26 -> 0 | N27: =N25-N26 -> -832962961 | O27: =O25-O26 -> -34591540
B28: 기타포괄손익(재분류 불가) | D28: =SUMIFS(D$69:D$133,$R$69:$R$133,$B28) -> 0 | E28: =SUMIFS(E$69:E$133,$R$69:$R$133,$B28) -> 0 | G28: =SUMIFS(G$69:G$133,$R$69:$R$133,$B28) -> 0 | H28: =SUMIFS(H$69:H$133,$R$69:$R$133,$B28) -> 0 | I28: =SUMIFS(I$69:I$133,$R$69:$R$133,$B28) -> 0 | J28: =SUMIFS(J$69:J$133,$R$69:$R$133,$B28) -> 0 | K28: =SUMIFS(K$69:K$133,$R$69:$R$133,$B28) -> 0 | L28: =SUMIFS(L$69:L$133,$R$69:$R$133,$B28) -> 0 | M28: =SUMIFS(M$69:M$133,$R$69:$R$133,$B28) -> 0 | N28: =SUMIFS(N$69:N$133,$R$69:$R$133,$B28) -> 0 | O28: =SUMIFS(O$69:O$133,$R$69:$R$133,$B28) -> 0
B29: 기타포괄손익(재분류 가능) | D29: =SUMIFS(D$69:D$133,$R$69:$R$133,$B29) -> 11298394 | E29: =SUMIFS(E$69:E$133,$R$69:$R$133,$B29) -> -26600734 | G29: =SUMIFS(G$69:G$133,$R$69:$R$133,$B29) -> 0 | H29: =SUMIFS(H$69:H$133,$R$69:$R$133,$B29) -> 0 | I29: =SUMIFS(I$69:I$133,$R$69:$R$133,$B29) -> 99968525 | J29: =SUMIFS(J$69:J$133,$R$69:$R$133,$B29) -> -77454021 | K29: =SUMIFS(K$69:K$133,$R$69:$R$133,$B29) -> -693420 | L29: =SUMIFS(L$69:L$133,$R$69:$R$133,$B29) -> 1741310 | M29: =SUMIFS(M$69:M$133,$R$69:$R$133,$B29) -> 0 | N29: =SUMIFS(N$69:N$133,$R$69:$R$133,$B29) -> 23562394 | O29: =SUMIFS(O$69:O$133,$R$69:$R$133,$B29) -> -12264000
B30: 기타포괄손익 | D30: =D28+D29 -> 11298394 | E30: =E28+E29 -> -26600734 | G30: =G28+G29 -> 0 | H30: =H28+H29 -> 0 | I30: =I28+I29 -> 99968525 | J30: =J28+J29 -> -77454021 | K30: =K28+K29 -> -693420 | L30: =L28+L29 -> 1741310 | M30: =M28+M29 -> 0 | N30: =N28+N29 -> 23562394 | O30: =O28+O29 -> -12264000
B31: 총포괄손익 | D31: =D27+D30 -> -856256107 | E31: =E27+E30 -> 969334639 | G31: =G27+G30 -> -788849810 | H31: =H27+H30 -> 0 | I31: =I27+I30 -> 144176416 | J31: =J27+J30 -> -174380350 | K31: =K27+K30 -> 16597898 | L31: =L27+L30 -> -6944721 | M31: =M27+M30 -> 0 | N31: =N27+N30 -> -809400567 | O31: =O27+O30 -> -46855540
B33: [검증] 기존 [연결PL] 대비 차이 (모두 0이어야 함)
B34: 당기순이익 - 연결PL | D34: =D27-연결PL!D101 -> 0 | E34: =E27-연결PL!E101 -> 0
B35: 총포괄손익 - 연결PL | D35: =D31-연결PL!D109 -> 0 | E35: =E31-연결PL!E109 -> 0
B36: 법인세비용차감전손익 - 연결PL | D36: =D25-연결PL!D99 -> 0 | E36: =E25-연결PL!E99 -> 0
B37: 기타포괄손익 - 연결PL | D37: =D30-연결PL!D104 -> 0 | E37: =E30-연결PL!E104 -> 0
B38: 당기순이익 - [PL]시트 연결열(Y113) | D38: =D27-PL!Y113 -> 0
B39: 단순합산+연결조정 = 연결 (당기순이익) | D39: =N27+O27-D27 -> 0
B40: 표시항목 미지정/오류 계정 수 | D40: =SUMPRODUCT(--ISNA(MATCH($R$69:$R$133,$B$140:$B$151,0))) -> 0
B41: 종합 검증 | D41: =IF(AND(SUMPRODUCT(ABS(D34:E37))=0,D38=0,D39=0,D40=0),"OK","확인필요") -> OK
B43: [조정표] 기존 영업이익 → IFRS 18 영업손익
B44: 기존 영업이익 (연결PL) | D44: =연결PL!D68 -> -791041478 | E44: =연결PL!E68 -> 1096205226
B45: (+) IFRS 18 영업 범주로 편입된 기존 영업외손익 (기타영업손익·외환손익 등) | D45: =SUMPRODUCT(($S$69:$S$133="영업")*($U$69:$U$133=0)*$T$69:$T$133*D$69:D$133) -> 5324363 | E45: =SUMPRODUCT(($S$69:$S$133="영업")*($U$69:$U$133=0)*$T$69:$T$133*E$69:E$133) -> -77841798
B46: (-) 영업 범주에서 제외된 기존 영업손익 | D46: =-SUMPRODUCT(($S$69:$S$133<>"영업")*($U$69:$U$133=1)*$T$69:$T$133*D$69:D$133) -> 0 | E46: =-SUMPRODUCT(($S$69:$S$133<>"영업")*($U$69:$U$133=1)*$T$69:$T$133*E$69:E$133) -> 0
B47: IFRS 18 영업손익 | D47: =D44+D45+D46 -> -785717115 | E47: =E44+E45+E46 -> 1018363428
B48: 검증: 상단 영업손익과의 차이 | D48: =D47-D12 -> 0 | E48: =E47-E12 -> 0
B50: [참고] 성격별 비용 공시 자료 (판관비 기준 - 제조원가 내 비용은 연결PL 구조상 제외, 별도 원가자료 확인 필요)
B51: 감가상각비 (판관비) | D51: =연결PL!D47 -> 181372149 | E51: =연결PL!E47 -> 222390521
B52: 무형자산상각비 (판관비) | D52: =연결PL!D66 -> 21529107 | E52: =연결PL!E66 -> 18799999
B53: 종업원급여 (급여·퇴직·해고·주식보상·복리후생) | D53: =연결PL!D36+연결PL!D37+연결PL!D38+연결PL!D39+연결PL!D40 -> 1856856609 | E53: =연결PL!E36+연결PL!E37+연결PL!E38+연결PL!E39+연결PL!E40 -> 2078129716
B56: [범례 및 가정]
B57: 파란글씨·노란 배경 = 입력(변경 가능) 셀 (부록 1의 R열 표시항목). 검정 글씨 = 수식 ([연결PL]·[PL] 시트 연동, 직접 수정 금지)
B58: 이자수익·파생상품평가이익은 투자, 이자비용·사채상환손실은 재무, 관계기업 지분법손익·투자주식처분손익·FVPL 평가손익은 투자 범주로 분류 (주된 사업활동이 투자/금융이 아님을 전제)
B59: 외환차손익·외화환산손익은 영업 범주로 분류 (IFRS 18 원가/노력 과다 시 영업 범주 단순화 가정) → 차입금 관련분이 식별되면 R열을 재무비용/재무수익으로 변경
B60: 단순합산(N열)은 각 법인 합산(PL시트 I~O열), 연결조정(O열)은 투자자본상계·내부거래제거·지분법/법인세/기타조정 합계(= 연결 - 단순합산)
B67: [부록 1] 계정별 IFRS 18 표시항목 매핑 (R열을 변경하면 상단 손익계산서가 자동 갱신)
B68: 계정과목 | D68: 당기 연결 | E68: 전기 연결 | G68: =PL!I2 -> 울트라브이 | H68: =PL!J2 -> 울트라브이팜 | I68: =PL!K2 -> ULTRA V HONG KONG LIMITED | J68: =PL!L2 -> DERMASTER HONG KONG LIMITED | K68: =PL!M2 -> ULTRA V SHANGHAI LIMITED | L68: =PL!N2 -> ULTRA V (SG) PTE.LTD (24년 설립) | M68: =PL!O2 -> ATGC | N68: 단순합산 | O68: 연결조정(상계·지분법 등) | Q68: 기존 연결PL 구분 | R68: IFRS 18 표시항목 | S68: IFRS 18 구분 | T68: 부호 | U68: 기존영업(1/0)
B69: =연결PL!B3 -> 상품매출 | D69: =연결PL!D3 -> 1181126900 | E69: =연결PL!E3 -> 1049196780 | G69: =SUMIF(PL!$AC:$AC,$B69,PL!I:I) -> 278070981 | H69: =SUMIF(PL!$AC:$AC,$B69,PL!J:J) -> 0 | I69: =SUMIF(PL!$AC:$AC,$B69,PL!K:K) -> 807627666 | J69: =SUMIF(PL!$AC:$AC,$B69,PL!L:L) -> 110521930 | K69: =SUMIF(PL!$AC:$AC,$B69,PL!M:M) -> 0 | L69: =SUMIF(PL!$AC:$AC,$B69,PL!N:N) -> 0 | M69: =SUMIF(PL!$AC:$AC,$B69,PL!O:O) -> 0 | N69: =SUM(G69:M69) -> 1196220577 | O69: =D69-N69 -> -15093677 | Q69: 매출액 | R69: 매출액 | S69: =IFERROR(INDEX($C$140:$C$151,MATCH(R69,$B$140:$B$151,0)),"오류") -> 영업 | T69: =IFERROR(INDEX($D$140:$D$151,MATCH(R69,$B$140:$B$151,0)),0) -> 1 | U69: =IF(OR(Q69="매출액",Q69="매출원가",Q69="판매비와관리비"),1,0) -> 1
B70: =연결PL!B4 -> 제품매출 | D70: =연결PL!D4 -> 7595910549 | E70: =연결PL!E4 -> 8347940342 | G70: =SUMIF(PL!$AC:$AC,$B70,PL!I:I) -> 7974892686 | H70: =SUMIF(PL!$AC:$AC,$B70,PL!J:J) -> 0 | I70: =SUMIF(PL!$AC:$AC,$B70,PL!K:K) -> 0 | J70: =SUMIF(PL!$AC:$AC,$B70,PL!L:L) -> 0 | K70: =SUMIF(PL!$AC:$AC,$B70,PL!M:M) -> 0 | L70: =SUMIF(PL!$AC:$AC,$B70,PL!N:N) -> 0 | M70: =SUMIF(PL!$AC:$AC,$B70,PL!O:O) -> 0 | N70: =SUM(G70:M70) -> 7974892686 | O70: =D70-N70 -> -378982137 | Q70: 매출액 | R70: 매출액 | S70: =IFERROR(INDEX($C$140:$C$151,MATCH(R70,$B$140:$B$151,0)),"오류") -> 영업 | T70: =IFERROR(INDEX($D$140:$D$151,MATCH(R70,$B$140:$B$151,0)),0) -> 1 | U70: =IF(OR(Q70="매출액",Q70="매출원가",Q70="판매비와관리비"),1,0) -> 1
B71: =연결PL!B5 -> 서비스매출 | D71: =연결PL!D5 -> 0 | E71: =연결PL!E5 -> 0 | G71: =SUMIF(PL!$AC:$AC,$B71,PL!I:I) -> 0 | H71: =SUMIF(PL!$AC:$AC,$B71,PL!J:J) -> 0 | I71: =SUMIF(PL!$AC:$AC,$B71,PL!K:K) -> 0 | J71: =SUMIF(PL!$AC:$AC,$B71,PL!L:L) -> 0 | K71: =SUMIF(PL!$AC:$AC,$B71,PL!M:M) -> 0 | L71: =SUMIF(PL!$AC:$AC,$B71,PL!N:N) -> 0 | M71: =SUMIF(PL!$AC:$AC,$B71,PL!O:O) -> 0 | N71: =SUM(G71:M71) -> 0 | O71: =D71-N71 -> 0 | Q71: 매출액 | R71: 매출액 | S71: =IFERROR(INDEX($C$140:$C$151,MATCH(R71,$B$140:$B$151,0)),"오류") -> 영업 | T71: =IFERROR(INDEX($D$140:$D$151,MATCH(R71,$B$140:$B$151,0)),0) -> 1 | U71: =IF(OR(Q71="매출액",Q71="매출원가",Q71="판매비와관리비"),1,0) -> 1
B72: =연결PL!B6 -> 식음료매출 | D72: =연결PL!D6 -> 35207020 | E72: =연결PL!E6 -> 44028845 | G72: =SUMIF(PL!$AC:$AC,$B72,PL!I:I) -> 35207020 | H72: =SUMIF(PL!$AC:$AC,$B72,PL!J:J) -> 0 | I72: =SUMIF(PL!$AC:$AC,$B72,PL!K:K) -> 0 | J72: =SUMIF(PL!$AC:$AC,$B72,PL!L:L) -> 0 | K72: =SUMIF(PL!$AC:$AC,$B72,PL!M:M) -> 0 | L72: =SUMIF(PL!$AC:$AC,$B72,PL!N:N) -> 0 | M72: =SUMIF(PL!$AC:$AC,$B72,PL!O:O) -> 0 | N72: =SUM(G72:M72) -> 35207020 | O72: =D72-N72 -> 0 | Q72: 매출액 | R72: 매출액 | S72: =IFERROR(INDEX($C$140:$C$151,MATCH(R72,$B$140:$B$151,0)),"오류") -> 영업 | T72: =IFERROR(INDEX($D$140:$D$151,MATCH(R72,$B$140:$B$151,0)),0) -> 1 | U72: =IF(OR(Q72="매출액",Q72="매출원가",Q72="판매비와관리비"),1,0) -> 1
B73: =연결PL!B7 -> 매출원가 | D73: =연결PL!D7 -> 3634217621 | E73: =연결PL!E7 -> 3581100990 | G73: =PL!I14 -> 3596633522 | H73: =PL!J14 -> 0 | I73: =PL!K14 -> 378103308 | J73: =PL!L14 -> 24568846 | K73: =PL!M14 -> 0 | L73: =PL!N14 -> 0 | M73: =PL!O14 -> 0 | N73: =SUM(G73:M73) -> 3999305676 | O73: =D73-N73 -> -365088055 | Q73: 매출원가 | R73: 매출원가 | S73: =IFERROR(INDEX($C$140:$C$151,MATCH(R73,$B$140:$B$151,0)),"오류") -> 영업 | T73: =IFERROR(INDEX($D$140:$D$151,MATCH(R73,$B$140:$B$151,0)),0) -> -1 | U73: =IF(OR(Q73="매출액",Q73="매출원가",Q73="판매비와관리비"),1,0) -> 1
B74: =연결PL!B36 -> 급여 | D74: =연결PL!D36 -> 1503402249 | E74: =연결PL!E36 -> 1770176545 | G74: =SUMIF(PL!$AC:$AC,$B74,PL!I:I) -> 1192275225 | H74: =SUMIF(PL!$AC:$AC,$B74,PL!J:J) -> 0 | I74: =SUMIF(PL!$AC:$AC,$B74,PL!K:K) -> 271298424 | J74: =SUMIF(PL!$AC:$AC,$B74,PL!L:L) -> 39828600 | K74: =SUMIF(PL!$AC:$AC,$B74,PL!M:M) -> 0 | L74: =SUMIF(PL!$AC:$AC,$B74,PL!N:N) -> 0 | M74: =SUMIF(PL!$AC:$AC,$B74,PL!O:O) -> 0 | N74: =SUM(G74:M74) -> 1503402249 | O74: =D74-N74 -> 0 | Q74: 판매비와관리비 | R74: 판매비와관리비 | S74: =IFERROR(INDEX($C$140:$C$151,MATCH(R74,$B$140:$B$151,0)),"오류") -> 영업 | T74: =IFERROR(INDEX($D$140:$D$151,MATCH(R74,$B$140:$B$151,0)),0) -> -1 | U74: =IF(OR(Q74="매출액",Q74="매출원가",Q74="판매비와관리비"),1,0) -> 1
B75: =연결PL!B37 -> 퇴직급여 | D75: =연결PL!D37 -> 110359296 | E75: =연결PL!E37 -> 104651910 | G75: =SUMIF(PL!$AC:$AC,$B75,PL!I:I) -> 110359296 | H75: =SUMIF(PL!$AC:$AC,$B75,PL!J:J) -> 0 | I75: =SUMIF(PL!$AC:$AC,$B75,PL!K:K) -> 0 | J75: =SUMIF(PL!$AC:$AC,$B75,PL!L:L) -> 0 | K75: =SUMIF(PL!$AC:$AC,$B75,PL!M:M) -> 0 | L75: =SUMIF(PL!$AC:$AC,$B75,PL!N:N) -> 0 | M75: =SUMIF(PL!$AC:$AC,$B75,PL!O:O) -> 0 | N75: =SUM(G75:M75) -> 110359296 | O75: =D75-N75 -> 0 | Q75: 판매비와관리비 | R75: 판매비와관리비 | S75: =IFERROR(INDEX($C$140:$C$151,MATCH(R75,$B$140:$B$151,0)),"오류") -> 영업 | T75: =IFERROR(INDEX($D$140:$D$151,MATCH(R75,$B$140:$B$151,0)),0) -> -1 | U75: =IF(OR(Q75="매출액",Q75="매출원가",Q75="판매비와관리비"),1,0) -> 1
B76: =연결PL!B38 -> 해고급여 | D76: =연결PL!D38 -> 45930430 | E76: =연결PL!E38 -> 0 | G76: =SUMIF(PL!$AC:$AC,$B76,PL!I:I) -> 45930430 | H76: =SUMIF(PL!$AC:$AC,$B76,PL!J:J) -> 0 | I76: =SUMIF(PL!$AC:$AC,$B76,PL!K:K) -> 0 | J76: =SUMIF(PL!$AC:$AC,$B76,PL!L:L) -> 0 | K76: =SUMIF(PL!$AC:$AC,$B76,PL!M:M) -> 0 | L76: =SUMIF(PL!$AC:$AC,$B76,PL!N:N) -> 0 | M76: =SUMIF(PL!$AC:$AC,$B76,PL!O:O) -> 0 | N76: =SUM(G76:M76) -> 45930430 | O76: =D76-N76 -> 0 | Q76: 판매비와관리비 | R76: 판매비와관리비 | S76: =IFERROR(INDEX($C$140:$C$151,MATCH(R76,$B$140:$B$151,0)),"오류") -> 영업 | T76: =IFERROR(INDEX($D$140:$D$151,MATCH(R76,$B$140:$B$151,0)),0) -> -1 | U76: =IF(OR(Q76="매출액",Q76="매출원가",Q76="판매비와관리비"),1,0) -> 1
B77: =연결PL!B39 -> 주식보상비 | D77: =연결PL!D39 -> 0 | E77: =연결PL!E39 -> 0 | G77: =SUMIF(PL!$AC:$AC,$B77,PL!I:I) -> 0 | H77: =SUMIF(PL!$AC:$AC,$B77,PL!J:J) -> 0 | I77: =SUMIF(PL!$AC:$AC,$B77,PL!K:K) -> 0 | J77: =SUMIF(PL!$AC:$AC,$B77,PL!L:L) -> 0 | K77: =SUMIF(PL!$AC:$AC,$B77,PL!M:M) -> 0 | L77: =SUMIF(PL!$AC:$AC,$B77,PL!N:N) -> 0 | M77: =SUMIF(PL!$AC:$AC,$B77,PL!O:O) -> 0 | N77: =SUM(G77:M77) -> 0 | O77: =D77-N77 -> 0 | Q77: 판매비와관리비 | R77: 판매비와관리비 | S77: =IFERROR(INDEX($C$140:$C$151,MATCH(R77,$B$140:$B$151,0)),"오류") -> 영업 | T77: =IFERROR(INDEX($D$140:$D$151,MATCH(R77,$B$140:$B$151,0)),0) -> -1 | U77: =IF(OR(Q77="매출액",Q77="매출원가",Q77="판매비와관리비"),1,0) -> 1
B78: =연결PL!B40 -> 복리후생비 | D78: =연결PL!D40 -> 197164634 | E78: =연결PL!E40 -> 203301261 | G78: =SUMIF(PL!$AC:$AC,$B78,PL!I:I) -> 187719099 | H78: =SUMIF(PL!$AC:$AC,$B78,PL!J:J) -> 0 | I78: =SUMIF(PL!$AC:$AC,$B78,PL!K:K) -> 7738595 | J78: =SUMIF(PL!$AC:$AC,$B78,PL!L:L) -> 1706940 | K78: =SUMIF(PL!$AC:$AC,$B78,PL!M:M) -> 0 | L78: =SUMIF(PL!$AC:$AC,$B78,PL!N:N) -> 0 | M78: =SUMIF(PL!$AC:$AC,$B78,PL!O:O) -> 0 | N78: =SUM(G78:M78) -> 197164634 | O78: =D78-N78 -> 0 | Q78: 판매비와관리비 | R78: 판매비와관리비 | S78: =IFERROR(INDEX($C$140:$C$151,MATCH(R78,$B$140:$B$151,0)),"오류") -> 영업 | T78: =IFERROR(INDEX($D$140:$D$151,MATCH(R78,$B$140:$B$151,0)),0) -> -1 | U78: =IF(OR(Q78="매출액",Q78="매출원가",Q78="판매비와관리비"),1,0) -> 1
B79: =연결PL!B41 -> 여비교통비 | D79: =연결PL!D41 -> 231770961 | E79: =연결PL!E41 -> 289230504 | G79: =SUMIF(PL!$AC:$AC,$B79,PL!I:I) -> 224812833 | H79: =SUMIF(PL!$AC:$AC,$B79,PL!J:J) -> 0 | I79: =SUMIF(PL!$AC:$AC,$B79,PL!K:K) -> 6958128 | J79: =SUMIF(PL!$AC:$AC,$B79,PL!L:L) -> 0 | K79: =SUMIF(PL!$AC:$AC,$B79,PL!M:M) -> 0 | L79: =SUMIF(PL!$AC:$AC,$B79,PL!N:N) -> 0 | M79: =SUMIF(PL!$AC:$AC,$B79,PL!O:O) -> 0 | N79: =SUM(G79:M79) -> 231770961 | O79: =D79-N79 -> 0 | Q79: 판매비와관리비 | R79: 판매비와관리비 | S79: =IFERROR(INDEX($C$140:$C$151,MATCH(R79,$B$140:$B$151,0)),"오류") -> 영업 | T79: =IFERROR(INDEX($D$140:$D$151,MATCH(R79,$B$140:$B$151,0)),0) -> -1 | U79: =IF(OR(Q79="매출액",Q79="매출원가",Q79="판매비와관리비"),1,0) -> 1
B80: =연결PL!B42 -> 접대비 | D80: =연결PL!D42 -> 35747090 | E80: =연결PL!E42 -> 90031148 | G80: =SUMIF(PL!$AC:$AC,$B80,PL!I:I) -> 25692474 | H80: =SUMIF(PL!$AC:$AC,$B80,PL!J:J) -> 0 | I80: =SUMIF(PL!$AC:$AC,$B80,PL!K:K) -> 9721611 | J80: =SUMIF(PL!$AC:$AC,$B80,PL!L:L) -> 333005 | K80: =SUMIF(PL!$AC:$AC,$B80,PL!M:M) -> 0 | L80: =SUMIF(PL!$AC:$AC,$B80,PL!N:N) -> 0 | M80: =SUMIF(PL!$AC:$AC,$B80,PL!O:O) -> 0 | N80: =SUM(G80:M80) -> 35747090 | O80: =D80-N80 -> 0 | Q80: 판매비와관리비 | R80: 판매비와관리비 | S80: =IFERROR(INDEX($C$140:$C$151,MATCH(R80,$B$140:$B$151,0)),"오류") -> 영업 | T80: =IFERROR(INDEX($D$140:$D$151,MATCH(R80,$B$140:$B$151,0)),0) -> -1 | U80: =IF(OR(Q80="매출액",Q80="매출원가",Q80="판매비와관리비"),1,0) -> 1
B81: =연결PL!B43 -> 통신비 | D81: =연결PL!D43 -> 13834390 | E81: =연결PL!E43 -> 14000818 | G81: =SUMIF(PL!$AC:$AC,$B81,PL!I:I) -> 8042843 | H81: =SUMIF(PL!$AC:$AC,$B81,PL!J:J) -> 0 | I81: =SUMIF(PL!$AC:$AC,$B81,PL!K:K) -> 5377430 | J81: =SUMIF(PL!$AC:$AC,$B81,PL!L:L) -> 414117 | K81: =SUMIF(PL!$AC:$AC,$B81,PL!M:M) -> 0 | L81: =SUMIF(PL!$AC:$AC,$B81,PL!N:N) -> 0 | M81: =SUMIF(PL!$AC:$AC,$B81,PL!O:O) -> 0 | N81: =SUM(G81:M81) -> 13834390 | O81: =D81-N81 -> 0 | Q81: 판매비와관리비 | R81: 판매비와관리비 | S81: =IFERROR(INDEX($C$140:$C$151,MATCH(R81,$B$140:$B$151,0)),"오류") -> 영업 | T81: =IFERROR(INDEX($D$140:$D$151,MATCH(R81,$B$140:$B$151,0)),0) -> -1 | U81: =IF(OR(Q81="매출액",Q81="매출원가",Q81="판매비와관리비"),1,0) -> 1
B82: =연결PL!B44 -> 수도광열비 | D82: =연결PL!D44 -> 4711948 | E82: =연결PL!E44 -> 4497562 | G82: =SUMIF(PL!$AC:$AC,$B82,PL!I:I) -> 2933840 | H82: =SUMIF(PL!$AC:$AC,$B82,PL!J:J) -> 0 | I82: =SUMIF(PL!$AC:$AC,$B82,PL!K:K) -> 0 | J82: =SUMIF(PL!$AC:$AC,$B82,PL!L:L) -> 1778108 | K82: =SUMIF(PL!$AC:$AC,$B82,PL!M:M) -> 0 | L82: =SUMIF(PL!$AC:$AC,$B82,PL!N:N) -> 0 | M82: =SUMIF(PL!$AC:$AC,$B82,PL!O:O) -> 0 | N82: =SUM(G82:M82) -> 4711948 | O82: =D82-N82 -> 0 | Q82: 판매비와관리비 | R82: 판매비와관리비 | S82: =IFERROR(INDEX($C$140:$C$151,MATCH(R82,$B$140:$B$151,0)),"오류") -> 영업 | T82: =IFERROR(INDEX($D$140:$D$151,MATCH(R82,$B$140:$B$151,0)),0) -> -1 | U82: =IF(OR(Q82="매출액",Q82="매출원가",Q82="판매비와관리비"),1,0) -> 1
B83: =연결PL!B45 -> 전력비 | D83: =연결PL!D45 -> 3879022 | E83: =연결PL!E45 -> 3182290 | G83: =SUMIF(PL!$AC:$AC,$B83,PL!I:I) -> 3879022 | H83: =SUMIF(PL!$AC:$AC,$B83,PL!J:J) -> 0 | I83: =SUMIF(PL!$AC:$AC,$B83,PL!K:K) -> 0 | J83: =SUMIF(PL!$AC:$AC,$B83,PL!L:L) -> 0 | K83: =SUMIF(PL!$AC:$AC,$B83,PL!M:M) -> 0 | L83: =SUMIF(PL!$AC:$AC,$B83,PL!N:N) -> 0 | M83: =SUMIF(PL!$AC:$AC,$B83,PL!O:O) -> 0 | N83: =SUM(G83:M83) -> 3879022 | O83: =D83-N83 -> 0 | Q83: 판매비와관리비 | R83: 판매비와관리비 | S83: =IFERROR(INDEX($C$140:$C$151,MATCH(R83,$B$140:$B$151,0)),"오류") -> 영업 | T83: =IFERROR(INDEX($D$140:$D$151,MATCH(R83,$B$140:$B$151,0)),0) -> -1 | U83: =IF(OR(Q83="매출액",Q83="매출원가",Q83="판매비와관리비"),1,0) -> 1
B84: =연결PL!B46 -> 세금과공과금 | D84: =연결PL!D46 -> 8510049 | E84: =연결PL!E46 -> 9690415 | G84: =SUMIF(PL!$AC:$AC,$B84,PL!I:I) -> 8506220 | H84: =SUMIF(PL!$AC:$AC,$B84,PL!J:J) -> 0 | I84: =SUMIF(PL!$AC:$AC,$B84,PL!K:K) -> 0 | J84: =SUMIF(PL!$AC:$AC,$B84,PL!L:L) -> 0 | K84: =SUMIF(PL!$AC:$AC,$B84,PL!M:M) -> 3829 | L84: =SUMIF(PL!$AC:$AC,$B84,PL!N:N) -> 0 | M84: =SUMIF(PL!$AC:$AC,$B84,PL!O:O) -> 0 | N84: =SUM(G84:M84) -> 8510049 | O84: =D84-N84 -> 0 | Q84: 판매비와관리비 | R84: 판매비와관리비 | S84: =IFERROR(INDEX($C$140:$C$151,MATCH(R84,$B$140:$B$151,0)),"오류") -> 영업 | T84: =IFERROR(INDEX($D$140:$D$151,MATCH(R84,$B$140:$B$151,0)),0) -> -1 | U84: =IF(OR(Q84="매출액",Q84="매출원가",Q84="판매비와관리비"),1,0) -> 1
B85: =연결PL!B47 -> 감가상각비 | D85: =연결PL!D47 -> 181372149 | E85: =연결PL!E47 -> 222390521 | G85: =SUMIF(PL!$AC:$AC,$B85,PL!I:I) -> 119880341 | H85: =SUMIF(PL!$AC:$AC,$B85,PL!J:J) -> 0 | I85: =SUMIF(PL!$AC:$AC,$B85,PL!K:K) -> 4176323 | J85: =SUMIF(PL!$AC:$AC,$B85,PL!L:L) -> 56277298 | K85: =SUMIF(PL!$AC:$AC,$B85,PL!M:M) -> 0 | L85: =SUMIF(PL!$AC:$AC,$B85,PL!N:N) -> 0 | M85: =SUMIF(PL!$AC:$AC,$B85,PL!O:O) -> 0 | N85: =SUM(G85:M85) -> 180333962 | O85: =D85-N85 -> 1038187 | Q85: 판매비와관리비 | R85: 판매비와관리비 | S85: =IFERROR(INDEX($C$140:$C$151,MATCH(R85,$B$140:$B$151,0)),"오류") -> 영업 | T85: =IFERROR(INDEX($D$140:$D$151,MATCH(R85,$B$140:$B$151,0)),0) -> -1 | U85: =IF(OR(Q85="매출액",Q85="매출원가",Q85="판매비와관리비"),1,0) -> 1
... B105: =연결PL!B67 -> 인력개발비 | D105: =연결PL!D67 -> 1380000 | E105: =연결PL!E67 -> 1378699 | G105: =SUMIF(PL!$AC:$AC,$B105,PL!I:I) -> 1380000 | H105: =SUMIF(PL!$AC:$AC,$B105,PL!J:J) -> 0 | I105: =SUMIF(PL!$AC:$AC,$B105,PL!K:K) -> 0 | J105: =SUMIF(PL!$AC:$AC,$B105,PL!L:L) -> 0 | K105: =SUMIF(PL!$AC:$AC,$B105,PL!M:M) -> 0 | L105: =SUMIF(PL!$AC:$AC,$B105,PL!N:N) -> 0 | M105: =SUMIF(PL!$AC:$AC,$B105,PL!O:O) -> 0 | N105: =SUM(G105:M105) -> 1380000 | O105: =D105-N105 -> 0 | Q105: 판매비와관리비 | R105: 판매비와관리비 | S105: =IFERROR(INDEX($C$140:$C$151,MATCH(R105,$B$140:$B$151,0)),"오류") -> 영업 | T105: =IFERROR(INDEX($D$140:$D$151,MATCH(R105,$B$140:$B$151,0)),0) -> -1 | U105: =IF(OR(Q105="매출액",Q105="매출원가",Q105="판매비와관리비"),1,0) -> 1
B106: =연결PL!B70 -> 외환차익(기타) | D106: =연결PL!D70 -> 0 | E106: =연결PL!E70 -> 0 | G106: =SUMIF(PL!$AC:$AC,$B106,PL!I:I) -> 0 | H106: =SUMIF(PL!$AC:$AC,$B106,PL!J:J) -> 0 | I106: =SUMIF(PL!$AC:$AC,$B106,PL!K:K) -> 0 | J106: =SUMIF(PL!$AC:$AC,$B106,PL!L:L) -> 0 | K106: =SUMIF(PL!$AC:$AC,$B106,PL!M:M) -> 0 | L106: =SUMIF(PL!$AC:$AC,$B106,PL!N:N) -> 0 | M106: =SUMIF(PL!$AC:$AC,$B106,PL!O:O) -> 0 | N106: =SUM(G106:M106) -> 0 | O106: =D106-N106 -> 0 | Q106: 기타영업수익 | R106: 기타영업수익 | S106: =IFERROR(INDEX($C$140:$C$151,MATCH(R106,$B$140:$B$151,0)),"오류") -> 영업 | T106: =IFERROR(INDEX($D$140:$D$151,MATCH(R106,$B$140:$B$151,0)),0) -> 1 | U106: =IF(OR(Q106="매출액",Q106="매출원가",Q106="판매비와관리비"),1,0) -> 0
B107: =연결PL!B71 -> 외화환산이익(기타) | D107: =연결PL!D71 -> 0 | E107: =연결PL!E71 -> 0 | G107: =SUMIF(PL!$AC:$AC,$B107,PL!I:I) -> 0 | H107: =SUMIF(PL!$AC:$AC,$B107,PL!J:J) -> 0 | I107: =SUMIF(PL!$AC:$AC,$B107,PL!K:K) -> 0 | J107: =SUMIF(PL!$AC:$AC,$B107,PL!L:L) -> 0 | K107: =SUMIF(PL!$AC:$AC,$B107,PL!M:M) -> 0 | L107: =SUMIF(PL!$AC:$AC,$B107,PL!N:N) -> 0 | M107: =SUMIF(PL!$AC:$AC,$B107,PL!O:O) -> 0 | N107: =SUM(G107:M107) -> 0 | O107: =D107-N107 -> 0 | Q107: 기타영업수익 | R107: 기타영업수익 | S107: =IFERROR(INDEX($C$140:$C$151,MATCH(R107,$B$140:$B$151,0)),"오류") -> 영업 | T107: =IFERROR(INDEX($D$140:$D$151,MATCH(R107,$B$140:$B$151,0)),0) -> 1 | U107: =IF(OR(Q107="매출액",Q107="매출원가",Q107="판매비와관리비"),1,0) -> 0
B108: =연결PL!B72 -> 수입임대료 | D108: =연결PL!D72 -> 0 | E108: =연결PL!E72 -> 0 | G108: =SUMIF(PL!$AC:$AC,$B108,PL!I:I) -> 0 | H108: =SUMIF(PL!$AC:$AC,$B108,PL!J:J) -> 0 | I108: =SUMIF(PL!$AC:$AC,$B108,PL!K:K) -> 0 | J108: =SUMIF(PL!$AC:$AC,$B108,PL!L:L) -> 0 | K108: =SUMIF(PL!$AC:$AC,$B108,PL!M:M) -> 0 | L108: =SUMIF(PL!$AC:$AC,$B108,PL!N:N) -> 0 | M108: =SUMIF(PL!$AC:$AC,$B108,PL!O:O) -> 0 | N108: =SUM(G108:M108) -> 0 | O108: =D108-N108 -> 0 | Q108: 기타영업수익 | R108: 기타영업수익 | S108: =IFERROR(INDEX($C$140:$C$151,MATCH(R108,$B$140:$B$151,0)),"오류") -> 영업 | T108: =IFERROR(INDEX($D$140:$D$151,MATCH(R108,$B$140:$B$151,0)),0) -> 1 | U108: =IF(OR(Q108="매출액",Q108="매출원가",Q108="판매비와관리비"),1,0) -> 0
B109: =연결PL!B73 -> 기타의대손상각비환입 | D109: =연결PL!D73 -> 3000000 | E109: =연결PL!E73 -> 3000000 | G109: =SUMIF(PL!$AC:$AC,$B109,PL!I:I) -> 3000000 | H109: =SUMIF(PL!$AC:$AC,$B109,PL!J:J) -> 0 | I109: =SUMIF(PL!$AC:$AC,$B109,PL!K:K) -> 0 | J109: =SUMIF(PL!$AC:$AC,$B109,PL!L:L) -> 0 | K109: =SUMIF(PL!$AC:$AC,$B109,PL!M:M) -> 0 | L109: =SUMIF(PL!$AC:$AC,$B109,PL!N:N) -> 0 | M109: =SUMIF(PL!$AC:$AC,$B109,PL!O:O) -> 0 | N109: =SUM(G109:M109) -> 3000000 | O109: =D109-N109 -> 0 | Q109: 기타영업수익 | R109: 기타영업수익 | S109: =IFERROR(INDEX($C$140:$C$151,MATCH(R109,$B$140:$B$151,0)),"오류") -> 영업 | T109: =IFERROR(INDEX($D$140:$D$151,MATCH(R109,$B$140:$B$151,0)),0) -> 1 | U109: =IF(OR(Q109="매출액",Q109="매출원가",Q109="판매비와관리비"),1,0) -> 0
B110: =연결PL!B74 -> 유형자산처분이익 | D110: =연결PL!D74 -> 1202135 | E110: =연결PL!E74 -> 1054000 | G110: =SUMIF(PL!$AC:$AC,$B110,PL!I:I) -> 1202135 | H110: =SUMIF(PL!$AC:$AC,$B110,PL!J:J) -> 0 | I110: =SUMIF(PL!$AC:$AC,$B110,PL!K:K) -> 0 | J110: =SUMIF(PL!$AC:$AC,$B110,PL!L:L) -> 0 | K110: =SUMIF(PL!$AC:$AC,$B110,PL!M:M) -> 0 | L110: =SUMIF(PL!$AC:$AC,$B110,PL!N:N) -> 0 | M110: =SUMIF(PL!$AC:$AC,$B110,PL!O:O) -> 0 | N110: =SUM(G110:M110) -> 1202135 | O110: =D110-N110 -> 0 | Q110: 기타영업수익 | R110: 기타영업수익 | S110: =IFERROR(INDEX($C$140:$C$151,MATCH(R110,$B$140:$B$151,0)),"오류") -> 영업 | T110: =IFERROR(INDEX($D$140:$D$151,MATCH(R110,$B$140:$B$151,0)),0) -> 1 | U110: =IF(OR(Q110="매출액",Q110="매출원가",Q110="판매비와관리비"),1,0) -> 0
B111: =연결PL!B75 -> 관계기업투자주식처분이익 | D111: =연결PL!D75 -> 2067945777 | E111: =연결PL!E75 -> 0 | G111: =SUMIF(PL!$AC:$AC,$B111,PL!I:I) -> 0 | H111: =SUMIF(PL!$AC:$AC,$B111,PL!J:J) -> 0 | I111: =SUMIF(PL!$AC:$AC,$B111,PL!K:K) -> 0 | J111: =SUMIF(PL!$AC:$AC,$B111,PL!L:L) -> 0 | K111: =SUMIF(PL!$AC:$AC,$B111,PL!M:M) -> 0 | L111: =SUMIF(PL!$AC:$AC,$B111,PL!N:N) -> 0 | M111: =SUMIF(PL!$AC:$AC,$B111,PL!O:O) -> 0 | N111: =SUM(G111:M111) -> 0 | O111: =D111-N111 -> 2067945777 | Q111: 기타영업수익 | R111: 투자수익 | S111: =IFERROR(INDEX($C$140:$C$151,MATCH(R111,$B$140:$B$151,0)),"오류") -> 투자 | T111: =IFERROR(INDEX($D$140:$D$151,MATCH(R111,$B$140:$B$151,0)),0) -> 1 | U111: =IF(OR(Q111="매출액",Q111="매출원가",Q111="판매비와관리비"),1,0) -> 0
B112: =연결PL!B76 -> 잡이익 | D112: =연결PL!D76 -> 37454272 | E112: =연결PL!E76 -> 4202143 | G112: =SUMIF(PL!$AC:$AC,$B112,PL!I:I) -> 193864 | H112: =SUMIF(PL!$AC:$AC,$B112,PL!J:J) -> 0 | I112: =SUMIF(PL!$AC:$AC,$B112,PL!K:K) -> 8686 | J112: =SUMIF(PL!$AC:$AC,$B112,PL!L:L) -> 1183 | K112: =SUMIF(PL!$AC:$AC,$B112,PL!M:M) -> 37250539 | L112: =SUMIF(PL!$AC:$AC,$B112,PL!N:N) -> 0 | M112: =SUMIF(PL!$AC:$AC,$B112,PL!O:O) -> 0 | N112: =SUM(G112:M112) -> 37454272 | O112: =D112-N112 -> 0 | Q112: 기타영업수익 | R112: 기타영업수익 | S112: =IFERROR(INDEX($C$140:$C$151,MATCH(R112,$B$140:$B$151,0)),"오류") -> 영업 | T112: =IFERROR(INDEX($D$140:$D$151,MATCH(R112,$B$140:$B$151,0)),0) -> 1 | U112: =IF(OR(Q112="매출액",Q112="매출원가",Q112="판매비와관리비"),1,0) -> 0
B113: =연결PL!B78 -> 기타의대손상각비 | D113: =연결PL!D78 -> 0 | E113: =연결PL!E78 -> 0 | G113: =SUMIF(PL!$AC:$AC,$B113,PL!I:I) -> 0 | H113: =SUMIF(PL!$AC:$AC,$B113,PL!J:J) -> 0 | I113: =SUMIF(PL!$AC:$AC,$B113,PL!K:K) -> 0 | J113: =SUMIF(PL!$AC:$AC,$B113,PL!L:L) -> 0 | K113: =SUMIF(PL!$AC:$AC,$B113,PL!M:M) -> 0 | L113: =SUMIF(PL!$AC:$AC,$B113,PL!N:N) -> 0 | M113: =SUMIF(PL!$AC:$AC,$B113,PL!O:O) -> 0 | N113: =SUM(G113:M113) -> 0 | O113: =D113-N113 -> 0 | Q113: 기타영업비용 | R113: 기타영업비용 | S113: =IFERROR(INDEX($C$140:$C$151,MATCH(R113,$B$140:$B$151,0)),"오류") -> 영업 | T113: =IFERROR(INDEX($D$140:$D$151,MATCH(R113,$B$140:$B$151,0)),0) -> -1 | U113: =IF(OR(Q113="매출액",Q113="매출원가",Q113="판매비와관리비"),1,0) -> 0
B114: =연결PL!B79 -> 기부금 | D114: =연결PL!D79 -> 132762 | E114: =연결PL!E79 -> 128604 | G114: =SUMIF(PL!$AC:$AC,$B114,PL!I:I) -> 0 | H114: =SUMIF(PL!$AC:$AC,$B114,PL!J:J) -> 0 | I114: =SUMIF(PL!$AC:$AC,$B114,PL!K:K) -> 132762 | J114: =SUMIF(PL!$AC:$AC,$B114,PL!L:L) -> 0 | K114: =SUMIF(PL!$AC:$AC,$B114,PL!M:M) -> 0 | L114: =SUMIF(PL!$AC:$AC,$B114,PL!N:N) -> 0 | M114: =SUMIF(PL!$AC:$AC,$B114,PL!O:O) -> 0 | N114: =SUM(G114:M114) -> 132762 | O114: =D114-N114 -> 0 | Q114: 기타영업비용 | R114: 기타영업비용 | S114: =IFERROR(INDEX($C$140:$C$151,MATCH(R114,$B$140:$B$151,0)),"오류") -> 영업 | T114: =IFERROR(INDEX($D$140:$D$151,MATCH(R114,$B$140:$B$151,0)),0) -> -1 | U114: =IF(OR(Q114="매출액",Q114="매출원가",Q114="판매비와관리비"),1,0) -> 0
B115: =연결PL!B80 -> 외화환산손실(기타) | D115: =연결PL!D80 -> 0 | E115: =연결PL!E80 -> 0 | G115: =SUMIF(PL!$AC:$AC,$B115,PL!I:I) -> 0 | H115: =SUMIF(PL!$AC:$AC,$B115,PL!J:J) -> 0 | I115: =SUMIF(PL!$AC:$AC,$B115,PL!K:K) -> 0 | J115: =SUMIF(PL!$AC:$AC,$B115,PL!L:L) -> 0 | K115: =SUMIF(PL!$AC:$AC,$B115,PL!M:M) -> 0 | L115: =SUMIF(PL!$AC:$AC,$B115,PL!N:N) -> 0 | M115: =SUMIF(PL!$AC:$AC,$B115,PL!O:O) -> 0 | N115: =SUM(G115:M115) -> 0 | O115: =D115-N115 -> 0 | Q115: 기타영업비용 | R115: 기타영업비용 | S115: =IFERROR(INDEX($C$140:$C$151,MATCH(R115,$B$140:$B$151,0)),"오류") -> 영업 | T115: =IFERROR(INDEX($D$140:$D$151,MATCH(R115,$B$140:$B$151,0)),0) -> -1 | U115: =IF(OR(Q115="매출액",Q115="매출원가",Q115="판매비와관리비"),1,0) -> 0
B116: =연결PL!B81 -> 유형자산처분손실 | D116: =연결PL!D81 -> 4825402 | E116: =연결PL!E81 -> 3098042 | G116: =SUMIF(PL!$AC:$AC,$B116,PL!I:I) -> 4825402 | H116: =SUMIF(PL!$AC:$AC,$B116,PL!J:J) -> 0 | I116: =SUMIF(PL!$AC:$AC,$B116,PL!K:K) -> 0 | J116: =SUMIF(PL!$AC:$AC,$B116,PL!L:L) -> 0 | K116: =SUMIF(PL!$AC:$AC,$B116,PL!M:M) -> 0 | L116: =SUMIF(PL!$AC:$AC,$B116,PL!N:N) -> 0 | M116: =SUMIF(PL!$AC:$AC,$B116,PL!O:O) -> 0 | N116: =SUM(G116:M116) -> 4825402 | O116: =D116-N116 -> 0 | Q116: 기타영업비용 | R116: 기타영업비용 | S116: =IFERROR(INDEX($C$140:$C$151,MATCH(R116,$B$140:$B$151,0)),"오류") -> 영업 | T116: =IFERROR(INDEX($D$140:$D$151,MATCH(R116,$B$140:$B$151,0)),0) -> -1 | U116: =IF(OR(Q116="매출액",Q116="매출원가",Q116="판매비와관리비"),1,0) -> 0
B117: =연결PL!B82 -> 관계기업투자주식처분손실 | D117: =연결PL!D82 -> 0 | E117: =연결PL!E82 -> 0 | G117: =SUMIF(PL!$AC:$AC,$B117,PL!I:I) -> 0 | H117: =SUMIF(PL!$AC:$AC,$B117,PL!J:J) -> 0 | I117: =SUMIF(PL!$AC:$AC,$B117,PL!K:K) -> 0 | J117: =SUMIF(PL!$AC:$AC,$B117,PL!L:L) -> 0 | K117: =SUMIF(PL!$AC:$AC,$B117,PL!M:M) -> 0 | L117: =SUMIF(PL!$AC:$AC,$B117,PL!N:N) -> 0 | M117: =SUMIF(PL!$AC:$AC,$B117,PL!O:O) -> 0 | N117: =SUM(G117:M117) -> 0 | O117: =D117-N117 -> 0 | Q117: 기타영업비용 | R117: 투자비용 | S117: =IFERROR(INDEX($C$140:$C$151,MATCH(R117,$B$140:$B$151,0)),"오류") -> 투자 | T117: =IFERROR(INDEX($D$140:$D$151,MATCH(R117,$B$140:$B$151,0)),0) -> -1 | U117: =IF(OR(Q117="매출액",Q117="매출원가",Q117="판매비와관리비"),1,0) -> 0
B118: =연결PL!B83 -> 보상비 | D118: =연결PL!D83 -> 0 | E118: =연결PL!E83 -> 0 | G118: =SUMIF(PL!$AC:$AC,$B118,PL!I:I) -> 0 | H118: =SUMIF(PL!$AC:$AC,$B118,PL!J:J) -> 0 | I118: =SUMIF(PL!$AC:$AC,$B118,PL!K:K) -> 0 | J118: =SUMIF(PL!$AC:$AC,$B118,PL!L:L) -> 0 | K118: =SUMIF(PL!$AC:$AC,$B118,PL!M:M) -> 0 | L118: =SUMIF(PL!$AC:$AC,$B118,PL!N:N) -> 0 | M118: =SUMIF(PL!$AC:$AC,$B118,PL!O:O) -> 0 | N118: =SUM(G118:M118) -> 0 | O118: =D118-N118 -> 0 | Q118: 기타영업비용 | R118: 기타영업비용 | S118: =IFERROR(INDEX($C$140:$C$151,MATCH(R118,$B$140:$B$151,0)),"오류") -> 영업 | T118: =IFERROR(INDEX($D$140:$D$151,MATCH(R118,$B$140:$B$151,0)),0) -> -1 | U118: =IF(OR(Q118="매출액",Q118="매출원가",Q118="판매비와관리비"),1,0) -> 0
B119: =연결PL!B84 -> 잡손실 | D119: =연결PL!D84 -> 4530608 | E119: =연결PL!E84 -> 3860416 | G119: =SUMIF(PL!$AC:$AC,$B119,PL!I:I) -> 210 | H119: =SUMIF(PL!$AC:$AC,$B119,PL!J:J) -> 0 | I119: =SUMIF(PL!$AC:$AC,$B119,PL!K:K) -> 409319 | J119: =SUMIF(PL!$AC:$AC,$B119,PL!L:L) -> 12707 | K119: =SUMIF(PL!$AC:$AC,$B119,PL!M:M) -> 4108372 | L119: =SUMIF(PL!$AC:$AC,$B119,PL!N:N) -> 0 | M119: =SUMIF(PL!$AC:$AC,$B119,PL!O:O) -> 0 | N119: =SUM(G119:M119) -> 4530608 | O119: =D119-N119 -> 0 | Q119: 기타영업비용 | R119: 기타영업비용 | S119: =IFERROR(INDEX($C$140:$C$151,MATCH(R119,$B$140:$B$151,0)),"오류") -> 영업 | T119: =IFERROR(INDEX($D$140:$D$151,MATCH(R119,$B$140:$B$151,0)),0) -> -1 | U119: =IF(OR(Q119="매출액",Q119="매출원가",Q119="판매비와관리비"),1,0) -> 0
B120: =연결PL!B86 -> 이자수익 | D120: =연결PL!D86 -> 22101454 | E120: =연결PL!E86 -> 28253274 | G120: =SUMIF(PL!$AC:$AC,$B120,PL!I:I) -> 22098561 | H120: =SUMIF(PL!$AC:$AC,$B120,PL!J:J) -> 0 | I120: =SUMIF(PL!$AC:$AC,$B120,PL!K:K) -> 658 | J120: =SUMIF(PL!$AC:$AC,$B120,PL!L:L) -> 53 | K120: =SUMIF(PL!$AC:$AC,$B120,PL!M:M) -> 2182 | L120: =SUMIF(PL!$AC:$AC,$B120,PL!N:N) -> 0 | M120: =SUMIF(PL!$AC:$AC,$B120,PL!O:O) -> 0 | N120: =SUM(G120:M120) -> 22101454 | O120: =D120-N120 -> 0 | Q120: 금융수익 | R120: 투자수익 | S120: =IFERROR(INDEX($C$140:$C$151,MATCH(R120,$B$140:$B$151,0)),"오류") -> 투자 | T120: =IFERROR(INDEX($D$140:$D$151,MATCH(R120,$B$140:$B$151,0)),0) -> 1 | U120: =IF(OR(Q120="매출액",Q120="매출원가",Q120="판매비와관리비"),1,0) -> 0
B121: =연결PL!B87 -> 파생금융자산평가이익 | D121: =연결PL!D87 -> 0 | E121: =연결PL!E87 -> 0 | G121: =SUMIF(PL!$AC:$AC,$B121,PL!I:I) -> 0 | H121: =SUMIF(PL!$AC:$AC,$B121,PL!J:J) -> 0 | I121: =SUMIF(PL!$AC:$AC,$B121,PL!K:K) -> 0 | J121: =SUMIF(PL!$AC:$AC,$B121,PL!L:L) -> 0 | K121: =SUMIF(PL!$AC:$AC,$B121,PL!M:M) -> 0 | L121: =SUMIF(PL!$AC:$AC,$B121,PL!N:N) -> 0 | M121: =SUMIF(PL!$AC:$AC,$B121,PL!O:O) -> 0 | N121: =SUM(G121:M121) -> 0 | O121: =D121-N121 -> 0 | Q121: 금융수익 | R121: 투자수익 | S121: =IFERROR(INDEX($C$140:$C$151,MATCH(R121,$B$140:$B$151,0)),"오류") -> 투자 | T121: =IFERROR(INDEX($D$140:$D$151,MATCH(R121,$B$140:$B$151,0)),0) -> 1 | U121: =IF(OR(Q121="매출액",Q121="매출원가",Q121="판매비와관리비"),1,0) -> 0
B122: =연결PL!B88 -> 외환차익 | D122: =연결PL!D88 -> 109841433 | E122: =연결PL!E88 -> 20481765 | G122: =SUMIF(PL!$AC:$AC,$B122,PL!I:I) -> 109841433 | H122: =SUMIF(PL!$AC:$AC,$B122,PL!J:J) -> 0 | I122: =SUMIF(PL!$AC:$AC,$B122,PL!K:K) -> 0 | J122: =SUMIF(PL!$AC:$AC,$B122,PL!L:L) -> 0 | K122: =SUMIF(PL!$AC:$AC,$B122,PL!M:M) -> 0 | L122: =SUMIF(PL!$AC:$AC,$B122,PL!N:N) -> 0 | M122: =SUMIF(PL!$AC:$AC,$B122,PL!O:O) -> 0 | N122: =SUM(G122:M122) -> 109841433 | O122: =D122-N122 -> 0 | Q122: 금융수익 | R122: 기타영업수익 | S122: =IFERROR(INDEX($C$140:$C$151,MATCH(R122,$B$140:$B$151,0)),"오류") -> 영업 | T122: =IFERROR(INDEX($D$140:$D$151,MATCH(R122,$B$140:$B$151,0)),0) -> 1 | U122: =IF(OR(Q122="매출액",Q122="매출원가",Q122="판매비와관리비"),1,0) -> 0
B123: =연결PL!B89 -> 외화환산이익 | D123: =연결PL!D89 -> 37603839 | E123: =연결PL!E89 -> 3042 | G123: =SUMIF(PL!$AC:$AC,$B123,PL!I:I) -> 37603839 | H123: =SUMIF(PL!$AC:$AC,$B123,PL!J:J) -> 0 | I123: =SUMIF(PL!$AC:$AC,$B123,PL!K:K) -> 0 | J123: =SUMIF(PL!$AC:$AC,$B123,PL!L:L) -> 0 | K123: =SUMIF(PL!$AC:$AC,$B123,PL!M:M) -> 0 | L123: =SUMIF(PL!$AC:$AC,$B123,PL!N:N) -> 0 | M123: =SUMIF(PL!$AC:$AC,$B123,PL!O:O) -> 0 | N123: =SUM(G123:M123) -> 37603839 | O123: =D123-N123 -> 0 | Q123: 금융수익 | R123: 기타영업수익 | S123: =IFERROR(INDEX($C$140:$C$151,MATCH(R123,$B$140:$B$151,0)),"오류") -> 영업 | T123: =IFERROR(INDEX($D$140:$D$151,MATCH(R123,$B$140:$B$151,0)),0) -> 1 | U123: =IF(OR(Q123="매출액",Q123="매출원가",Q123="판매비와관리비"),1,0) -> 0
B124: =연결PL!B91 -> 이자비용 | D124: =연결PL!D91 -> 98954951 | E124: =연결PL!E91 -> 45786340 | G124: =SUMIF(PL!$AC:$AC,$B124,PL!I:I) -> 98954951 | H124: =SUMIF(PL!$AC:$AC,$B124,PL!J:J) -> 0 | I124: =SUMIF(PL!$AC:$AC,$B124,PL!K:K) -> 0 | J124: =SUMIF(PL!$AC:$AC,$B124,PL!L:L) -> 0 | K124: =SUMIF(PL!$AC:$AC,$B124,PL!M:M) -> 0 | L124: =SUMIF(PL!$AC:$AC,$B124,PL!N:N) -> 0 | M124: =SUMIF(PL!$AC:$AC,$B124,PL!O:O) -> 0 | N124: =SUM(G124:M124) -> 98954951 | O124: =D124-N124 -> 0 | Q124: 금융비용 | R124: 재무비용 | S124: =IFERROR(INDEX($C$140:$C$151,MATCH(R124,$B$140:$B$151,0)),"오류") -> 재무 | T124: =IFERROR(INDEX($D$140:$D$151,MATCH(R124,$B$140:$B$151,0)),0) -> -1 | U124: =IF(OR(Q124="매출액",Q124="매출원가",Q124="판매비와관리비"),1,0) -> 0
B125: =연결PL!B92 -> 당기손익-공정가치측정금융자산평가손실 | D125: =연결PL!D92 -> 0 | E125: =연결PL!E92 -> 0 | G125: =SUMIF(PL!$AC:$AC,$B125,PL!I:I) -> 0 | H125: =SUMIF(PL!$AC:$AC,$B125,PL!J:J) -> 0 | I125: =SUMIF(PL!$AC:$AC,$B125,PL!K:K) -> 0 | J125: =SUMIF(PL!$AC:$AC,$B125,PL!L:L) -> 0 | K125: =SUMIF(PL!$AC:$AC,$B125,PL!M:M) -> 0 | L125: =SUMIF(PL!$AC:$AC,$B125,PL!N:N) -> 0 | M125: =SUMIF(PL!$AC:$AC,$B125,PL!O:O) -> 0 | N125: =SUM(G125:M125) -> 0 | O125: =D125-N125 -> 0 | Q125: 금융비용 | R125: 투자비용 | S125: =IFERROR(INDEX($C$140:$C$151,MATCH(R125,$B$140:$B$151,0)),"오류") -> 투자 | T125: =IFERROR(INDEX($D$140:$D$151,MATCH(R125,$B$140:$B$151,0)),0) -> -1 | U125: =IF(OR(Q125="매출액",Q125="매출원가",Q125="판매비와관리비"),1,0) -> 0
B126: =연결PL!B93 -> 사채상환손실 | D126: =연결PL!D93 -> 0 | E126: =연결PL!E93 -> 0 | G126: =SUMIF(PL!$AC:$AC,$B126,PL!I:I) -> 0 | H126: =SUMIF(PL!$AC:$AC,$B126,PL!J:J) -> 0 | I126: =SUMIF(PL!$AC:$AC,$B126,PL!K:K) -> 0 | J126: =SUMIF(PL!$AC:$AC,$B126,PL!L:L) -> 0 | K126: =SUMIF(PL!$AC:$AC,$B126,PL!M:M) -> 0 | L126: =SUMIF(PL!$AC:$AC,$B126,PL!N:N) -> 0 | M126: =SUMIF(PL!$AC:$AC,$B126,PL!O:O) -> 0 | N126: =SUM(G126:M126) -> 0 | O126: =D126-N126 -> 0 | Q126: 금융비용 | R126: 재무비용 | S126: =IFERROR(INDEX($C$140:$C$151,MATCH(R126,$B$140:$B$151,0)),"오류") -> 재무 | T126: =IFERROR(INDEX($D$140:$D$151,MATCH(R126,$B$140:$B$151,0)),0) -> -1 | U126: =IF(OR(Q126="매출액",Q126="매출원가",Q126="판매비와관리비"),1,0) -> 0
B127: =연결PL!B94 -> 외환차손 | D127: =연결PL!D94 -> 174288542 | E127: =연결PL!E94 -> 41293761 | G127: =SUMIF(PL!$AC:$AC,$B127,PL!I:I) -> 172194962 | H127: =SUMIF(PL!$AC:$AC,$B127,PL!J:J) -> 0 | I127: =SUMIF(PL!$AC:$AC,$B127,PL!K:K) -> 1829428 | J127: =SUMIF(PL!$AC:$AC,$B127,PL!L:L) -> 144 | K127: =SUMIF(PL!$AC:$AC,$B127,PL!M:M) -> 233982 | L127: =SUMIF(PL!$AC:$AC,$B127,PL!N:N) -> 30026 | M127: =SUMIF(PL!$AC:$AC,$B127,PL!O:O) -> 0 | N127: =SUM(G127:M127) -> 174288542 | O127: =D127-N127 -> 0 | Q127: 금융비용 | R127: 기타영업비용 | S127: =IFERROR(INDEX($C$140:$C$151,MATCH(R127,$B$140:$B$151,0)),"오류") -> 영업 | T127: =IFERROR(INDEX($D$140:$D$151,MATCH(R127,$B$140:$B$151,0)),0) -> -1 | U127: =IF(OR(Q127="매출액",Q127="매출원가",Q127="판매비와관리비"),1,0) -> 0
B128: =연결PL!B95 -> 외화환산손실 | D128: =연결PL!D95 -> 2 | E128: =연결PL!E95 -> 58201925 | G128: =SUMIF(PL!$AC:$AC,$B128,PL!I:I) -> 0 | H128: =SUMIF(PL!$AC:$AC,$B128,PL!J:J) -> 0 | I128: =SUMIF(PL!$AC:$AC,$B128,PL!K:K) -> 2 | J128: =SUMIF(PL!$AC:$AC,$B128,PL!L:L) -> 0 | K128: =SUMIF(PL!$AC:$AC,$B128,PL!M:M) -> 0 | L128: =SUMIF(PL!$AC:$AC,$B128,PL!N:N) -> 0 | M128: =SUMIF(PL!$AC:$AC,$B128,PL!O:O) -> 0 | N128: =SUM(G128:M128) -> 2 | O128: =D128-N128 -> 0 | Q128: 금융비용 | R128: 기타영업비용 | S128: =IFERROR(INDEX($C$140:$C$151,MATCH(R128,$B$140:$B$151,0)),"오류") -> 영업 | T128: =IFERROR(INDEX($D$140:$D$151,MATCH(R128,$B$140:$B$151,0)),0) -> -1 | U128: =IF(OR(Q128="매출액",Q128="매출원가",Q128="판매비와관리비"),1,0) -> 0
B129: =연결PL!B97 -> 관계기업투자이익 | D129: =연결PL!D97 -> 0 | E129: =연결PL!E97 -> 0 | G129: =SUMIF(PL!$AC:$AC,$B129,PL!I:I) -> 0 | H129: =SUMIF(PL!$AC:$AC,$B129,PL!J:J) -> 0 | I129: =SUMIF(PL!$AC:$AC,$B129,PL!K:K) -> 0 | J129: =SUMIF(PL!$AC:$AC,$B129,PL!L:L) -> 0 | K129: =SUMIF(PL!$AC:$AC,$B129,PL!M:M) -> 0 | L129: =SUMIF(PL!$AC:$AC,$B129,PL!N:N) -> 0 | M129: =SUMIF(PL!$AC:$AC,$B129,PL!O:O) -> 0 | N129: =SUM(G129:M129) -> 0 | O129: =D129-N129 -> 0 | Q129: 지분법손익 | R129: 투자수익 | S129: =IFERROR(INDEX($C$140:$C$151,MATCH(R129,$B$140:$B$151,0)),"오류") -> 투자 | T129: =IFERROR(INDEX($D$140:$D$151,MATCH(R129,$B$140:$B$151,0)),0) -> 1 | U129: =IF(OR(Q129="매출액",Q129="매출원가",Q129="판매비와관리비"),1,0) -> 0
B130: =연결PL!B98 -> 관계기업투자손실 | D130: =연결PL!D98 -> 2067945777 | E130: =연결PL!E98 -> 0 | G130: =SUMIF(PL!$AC:$AC,$B130,PL!I:I) -> 0 | H130: =SUMIF(PL!$AC:$AC,$B130,PL!J:J) -> 0 | I130: =SUMIF(PL!$AC:$AC,$B130,PL!K:K) -> 0 | J130: =SUMIF(PL!$AC:$AC,$B130,PL!L:L) -> 0 | K130: =SUMIF(PL!$AC:$AC,$B130,PL!M:M) -> 0 | L130: =SUMIF(PL!$AC:$AC,$B130,PL!N:N) -> 0 | M130: =SUMIF(PL!$AC:$AC,$B130,PL!O:O) -> 0 | N130: =SUM(G130:M130) -> 0 | O130: =D130-N130 -> 2067945777 | Q130: 지분법손익 | R130: 투자비용 | S130: =IFERROR(INDEX($C$140:$C$151,MATCH(R130,$B$140:$B$151,0)),"오류") -> 투자 | T130: =IFERROR(INDEX($D$140:$D$151,MATCH(R130,$B$140:$B$151,0)),0) -> -1 | U130: =IF(OR(Q130="매출액",Q130="매출원가",Q130="판매비와관리비"),1,0) -> 0
B131: =연결PL!B100 -> 법인세비용 | D131: =연결PL!D100 -> 4983889 | E131: =연결PL!E100 -> 4894989 | G131: =SUMIF(PL!$AC:$AC,$B131,PL!I:I) -> 0 | H131: =SUMIF(PL!$AC:$AC,$B131,PL!J:J) -> 0 | I131: =SUMIF(PL!$AC:$AC,$B131,PL!K:K) -> 0 | J131: =SUMIF(PL!$AC:$AC,$B131,PL!L:L) -> 0 | K131: =SUMIF(PL!$AC:$AC,$B131,PL!M:M) -> 0 | L131: =SUMIF(PL!$AC:$AC,$B131,PL!N:N) -> 0 | M131: =SUMIF(PL!$AC:$AC,$B131,PL!O:O) -> 0 | N131: =SUM(G131:M131) -> 0 | O131: =D131-N131 -> 4983889 | Q131: 법인세비용 | R131: 법인세비용 | S131: =IFERROR(INDEX($C$140:$C$151,MATCH(R131,$B$140:$B$151,0)),"오류") -> 법인세 | T131: =IFERROR(INDEX($D$140:$D$151,MATCH(R131,$B$140:$B$151,0)),0) -> -1 | U131: =IF(OR(Q131="매출액",Q131="매출원가",Q131="판매비와관리비"),1,0) -> 0
B132: =연결PL!B106 -> 종업원급여 재측정요소 | D132: =연결PL!D106 -> 0 | E132: =연결PL!E106 -> 0 | G132: =SUMIF(PL!$AC:$AC,$B132,PL!I:I) -> 0 | H132: =SUMIF(PL!$AC:$AC,$B132,PL!J:J) -> 0 | I132: =SUMIF(PL!$AC:$AC,$B132,PL!K:K) -> 0 | J132: =SUMIF(PL!$AC:$AC,$B132,PL!L:L) -> 0 | K132: =SUMIF(PL!$AC:$AC,$B132,PL!M:M) -> 0 | L132: =SUMIF(PL!$AC:$AC,$B132,PL!N:N) -> 0 | M132: =SUMIF(PL!$AC:$AC,$B132,PL!O:O) -> 0 | N132: =SUM(G132:M132) -> 0 | O132: =D132-N132 -> 0 | Q132: 기타포괄손익 | R132: 기타포괄손익(재분류 불가) | S132: =IFERROR(INDEX($C$140:$C$151,MATCH(R132,$B$140:$B$151,0)),"오류") -> 기타포괄손익 | T132: =IFERROR(INDEX($D$140:$D$151,MATCH(R132,$B$140:$B$151,0)),0) -> 1 | U132: =IF(OR(Q132="매출액",Q132="매출원가",Q132="판매비와관리비"),1,0) -> 0
B133: =연결PL!B108 -> 해외사업환산손익 | D133: =연결PL!D108 -> 11298394 | E133: =연결PL!E108 -> -26600734 | G133: =SUMIF(PL!$AC:$AC,$B133,PL!I:I) -> 0 | H133: =SUMIF(PL!$AC:$AC,$B133,PL!J:J) -> 0 | I133: =SUMIF(PL!$AC:$AC,$B133,PL!K:K) -> 99968525 | J133: =SUMIF(PL!$AC:$AC,$B133,PL!L:L) -> -77454021 | K133: =SUMIF(PL!$AC:$AC,$B133,PL!M:M) -> -693420 | L133: =SUMIF(PL!$AC:$AC,$B133,PL!N:N) -> 1741310 | M133: =SUMIF(PL!$AC:$AC,$B133,PL!O:O) -> 0 | N133: =SUM(G133:M133) -> 23562394 | O133: =D133-N133 -> -12264000 | Q133: 기타포괄손익 | R133: 기타포괄손익(재분류 가능) | S133: =IFERROR(INDEX($C$140:$C$151,MATCH(R133,$B$140:$B$151,0)),"오류") -> 기타포괄손익 | T133: =IFERROR(INDEX($D$140:$D$151,MATCH(R133,$B$140:$B$151,0)),0) -> 1 | U133: =IF(OR(Q133="매출액",Q133="매출원가",Q133="판매비와관리비"),1,0) -> 0
...

Sheet 연결CF
B1: 과목 | C1: =연결PL!D1 -> 46203 | D1: =C1-365 -> 45838 | L1: 과목 | M1: 45838
B2: Ⅰ.영업활동으로인한현금흐름 | C2: =C3+C36+C37+C38 -> 1202295393 | D2: =D3+D36+D37+D38 -> 1183882268 | L2: Ⅰ.영업활동으로인한현금흐름 | M2: =M3+M36+M37+M38 -> 1183882268 | N2: =M2-D2 -> 0
B3: 1.영업에서창출된현금 | C3: =C4+C5+C27 -> 1276280827 | D3: =D4+D5+D27 -> 1244383314 | L3: 1.영업에서창출된현금 | M3: =M4+M5+M27 -> 1244383314 | N3: =M3-D3 -> 0
B4: 가.당기순이익 | C4: =연결PL!D101 -> -867554501 | D4: =M4 -> 995935373 | L4: 가.당기순이익 | M4: 995935373 | N4: =M4-D4 -> 0
B5: 나.조정 | C5: =SUM(C6:C26) -> 917008474 | D5: =SUM(D6:D26) -> 1002829676 | E5: PL | F5: 차이 | L5: 나.조정 | M5: =SUM(M6:M26) -> 1002829676 | N5: =M5-D5 -> 0
B6: 대손상각비 | C6: =SUMIF(CF정산표!$F$179:$F$210,연결CF!B6,CF정산표!$H$179:$H$210) -> -83305712 | D6: =IFERROR(VLOOKUP(B6,$L$6:$M$65,2,0),) -> 56559960 | E6: =연결PL!D62 -> -83305712 | F6: =C6=E6 -> TRUE | L6: 대손상각비 | M6: 56559960
B7: 이자수익 | C7: =SUMIF(CF정산표!$F$179:$F$210,연결CF!B7,CF정산표!$H$179:$H$210) -> -22101454 | D7: =IFERROR(VLOOKUP(B7,$L$6:$M$65,2,0),) -> -28253274 | E7: =연결PL!D86 -> 22101454 | F7: =C7=-E7 -> TRUE | L7: 이자수익 | M7: -28253274
B8: 유형자산처분이익 | C8: =SUMIF(CF정산표!$F$179:$F$210,연결CF!B8,CF정산표!$H$179:$H$210) -> -1202135 | D8: =IFERROR(VLOOKUP(B8,$L$6:$M$65,2,0),) -> -1054000 | E8: =연결PL!D74 -> 1202135 | F8: =E8=-C8 -> TRUE | L8: 유형자산처분이익 | M8: -1054000
B9: 외화환산이익 | C9: =SUMIF(CF정산표!$F$179:$F$210,연결CF!B9,CF정산표!$H$179:$H$210) -> -37603839 | D9: =IFERROR(VLOOKUP(B9,$L$6:$M$65,2,0),) -> -3042 | E9: =연결PL!D89 -> 37603839 | F9: =C9--E9 -> 0 | L9: 외화환산이익 | M9: -3042
B10: 재고자산평가손실(환입) | C10: =SUMIF(CF정산표!$F$179:$F$210,연결CF!B10,CF정산표!$H$179:$H$210) -> 131193174 | D10: =IFERROR(VLOOKUP(B10,$L$6:$M$65,2,0),) -> 15216604 | L10: 재고자산평가손실(환입) | M10: 15216604
B11: 퇴직급여 | C11: =SUMIF(CF정산표!$F$179:$F$210,연결CF!B11,CF정산표!$H$179:$H$210) -> 188019390 | D11: =IFERROR(VLOOKUP(B11,$L$6:$M$65,2,0),) -> 177665682 | E11: ='20'!C21 -> 188019390 | F11: =E11=C11 -> TRUE | L11: 퇴직급여 | M11: 177665682
B12: 주식보상비 | C12: =SUMIF(CF정산표!$F$179:$F$210,연결CF!B12,CF정산표!$H$179:$H$210) -> 0 | D12: =IFERROR(VLOOKUP(B12,$L$6:$M$65,2,0),) -> 0 | E12: =연결PL!D39 -> 0 | F12: =C12=E12 -> TRUE | L12: 주식보상비 | M12: 0
B13: 이자비용 | C13: =SUMIF(CF정산표!$F$179:$F$210,연결CF!B13,CF정산표!$H$179:$H$210) -> 98954951 | D13: =IFERROR(VLOOKUP(B13,$L$6:$M$65,2,0),) -> 45786340 | E13: =연결PL!D91 -> 98954951 | F13: =C13=E13 -> TRUE | L13: 이자비용 | M13: 45786340
B14: 감가상각비 | C14: =SUMIF(CF정산표!$F$179:$F$210,연결CF!B14,CF정산표!$H$179:$H$210) -> 585661920 | D14: =IFERROR(VLOOKUP(B14,$L$6:$M$65,2,0),) -> 497372122 | E14: ='28'!D13 -> 607191027 | F14: =C14+C15-E14 -> 0 | L14: 감가상각비 | M14: 497372122
B15: 무형자산상각비 | C15: =SUMIF(CF정산표!$F$179:$F$210,연결CF!B15,CF정산표!$H$179:$H$210) -> 21529107 | D15: =IFERROR(VLOOKUP(B15,$L$6:$M$65,2,0),) -> 144426793 | E15: =-'13'!F27 -> 21529107 | F15: =C15+C16-E15 -> 0 | L15: 무형자산상각비 | M15: 144426793
B16: 영업권손상차손 | C16: =SUMIF(CF정산표!$F$179:$F$210,연결CF!B16,CF정산표!$H$179:$H$210) -> 0 | D16: =IFERROR(VLOOKUP(B16,$L$6:$M$65,2,0),) -> 0 | L16: 영업권손상차손 | M16: 0
B17: 유형자산처분손실 | C17: =SUMIF(CF정산표!$F$179:$F$210,연결CF!B17,CF정산표!$H$179:$H$210) -> 4825402 | D17: =IFERROR(VLOOKUP(B17,$L$6:$M$65,2,0),) -> 3098042 | E17: =연결PL!D81 -> 4825402 | F17: =C17-E17 -> 0 | L17: 유형자산처분손실 | M17: 3098042
B18: 외화환산손실 | C18: =SUMIF(CF정산표!$F$179:$F$210,연결CF!B18,CF정산표!$H$179:$H$210) -> 2 | D18: =IFERROR(VLOOKUP(B18,$L$6:$M$65,2,0),) -> 58201925 | E18: =연결PL!D95 -> 2 | F18: =C18-E18 -> 0 | L18: 외화환산손실 | M18: 58201925
B19: 법인세비용 | C19: =SUMIF(CF정산표!$F$179:$F$210,연결CF!B19,CF정산표!$H$179:$H$210) -> 4983889 | D19: =IFERROR(VLOOKUP(B19,$L$6:$M$65,2,0),) -> 4894989 | E19: =연결PL!D100 -> 4983889 | F19: =C19-E19 -> 0 | L19: 법인세비용 | M19: 4894989
B20: 복리후생비 | C20: =SUMIF(CF정산표!$F$179:$F$210,연결CF!B20,CF정산표!$H$179:$H$210) -> 37001898 | D20: =IFERROR(VLOOKUP(B20,$L$6:$M$65,2,0),) -> 34571148 | L20: 복리후생비 | M20: 34571148
B21: 상환전환우선주부채평가손실 | C21: =SUMIF(CF정산표!$F$179:$F$210,연결CF!B21,CF정산표!$H$179:$H$210) -> 0 | D21: =IFERROR(VLOOKUP(B21,$L$6:$M$65,2,0),) -> 0 | L21: 상환전환우선주부채평가손실 | M21: 0
B22: 당기손익공정가치측정금융자산평가손실 | C22: =SUMIF(CF정산표!$F$179:$F$210,연결CF!B22,CF정산표!$H$179:$H$210) -> 0 | D22: =IFERROR(VLOOKUP(B22,$L$6:$M$65,2,0),) -> 0 | E22: =연결PL!D92 -> 0 | F22: =C22=E22 -> TRUE | L22: 사채상환손실 | M22: 0
B23: 기타의 대손상각비(환입) | C23: =SUMIF(CF정산표!$F$179:$F$210,연결CF!B23,CF정산표!$H$179:$H$210) -> -3000000 | D23: =IFERROR(VLOOKUP(B23,$L$6:$M$65,2,0),) -> -3000000 | E23: =-연결PL!D73 -> -3000000 | F23: =C23=E23 -> TRUE | L23: 기타의 대손상각비(환입) | M23: -3000000
B24: 관계기업투자주식처분이익 | C24: =SUMIF(CF정산표!$F$179:$F$210,연결CF!B24,CF정산표!$H$179:$H$210) -> -2067945777 | D24: =IFERROR(VLOOKUP(B24,$L$6:$M$65,2,0),) -> 0 | L24: 관계기업투자주식처분손실 | M24: 0
B25: 지분법손실 | C25: =SUMIF(CF정산표!$F$179:$F$210,연결CF!B25,CF정산표!$H$179:$H$210) -> 2067945777 | D25: =IFERROR(VLOOKUP(B25,$L$6:$M$65,2,0),) -> 0 | E25: =연결PL!D98 -> 2067945777 | F25: =C25-E25 -> 0 | L25: 관계기업투자이익 | M25: 0
B26: 환불부채 | C26: =SUMIF(CF정산표!$F$179:$F$210,연결CF!B26,CF정산표!$H$179:$H$210) -> -7948119 | D26: =IFERROR(VLOOKUP(B26,$L$6:$M$65,2,0),) -> -2653613 | L26: 환불부채 | M26: -2653613
B27: 다.영업활동으로인한자산부채의변동 | C27: =SUM(C28:C35) -> 1226826854 | D27: =SUM(D28:D35) -> -754381735 | E27: =CF정산표!N170 -> 1226826854 | F27: =E27=C27 -> TRUE | L27: 다.영업활동으로인한자산부채의변동 | M27: =SUM(M28:M35) -> -754381735
B28: 매출채권및기타채권의 감소(증가) | C28: =SUMIF(CF정산표!$K$179:$K$199,연결CF!B28,CF정산표!$N$179:$N$199) -> 502587042 | D28: =IFERROR(VLOOKUP(B28,$L$6:$M$65,2,0),) -> -146111841 | L28: 매출채권및기타채권의 감소(증가) | M28: -146111841
B29: 기타유동자산의 감소(증가) | C29: =SUMIF(CF정산표!$K$179:$K$199,연결CF!B29,CF정산표!$N$179:$N$199) -> 433657614 | D29: =IFERROR(VLOOKUP(B29,$L$6:$M$65,2,0),) -> -140049917 | L29: 기타유동자산의 감소(증가) | M29: -140049917
B30: 재고자산의 감소(증가) | C30: =SUMIF(CF정산표!$K$179:$K$199,연결CF!B30,CF정산표!$N$179:$N$199) -> -326232101 | D30: =IFERROR(VLOOKUP(B30,$L$6:$M$65,2,0),) -> 77359122 | L30: 재고자산의 감소(증가) | M30: 77359122
B31: 매입채무및기타채무의 증가(감소) | C31: =SUMIF(CF정산표!$K$179:$K$199,연결CF!B31,CF정산표!$N$179:$N$199) -> 1866250998 | D31: =IFERROR(VLOOKUP(B31,$L$6:$M$65,2,0),) -> -456512459 | L31: 매입채무및기타채무의 증가(감소) | M31: -456512459
B32: 임차보증금유동 | C32: =SUMIF(CF정산표!$K$179:$K$199,연결CF!B32,CF정산표!$N$179:$N$199) -> 0 | D32: =IFERROR(VLOOKUP(B32,$L$6:$M$65,2,0),) -> 0 | L32: 임차보증금유동 | M32: 0
B33: 기타유동부채의 증가(감소) | C33: =SUMIF(CF정산표!$K$179:$K$199,연결CF!B33,CF정산표!$N$179:$N$199) -> -180207725 | D33: =IFERROR(VLOOKUP(B33,$L$6:$M$65,2,0),) -> -27252178 | L33: 기타유동부채의 증가(감소) | M33: -27252178
B34: 기타장기종업원급여의 증가(감소) | C34: =SUMIF(CF정산표!$K$179:$K$199,연결CF!B34,CF정산표!$N$179:$N$199) -> -4380000 | D34: =IFERROR(VLOOKUP(B34,$L$6:$M$65,2,0),) -> 0 | L34: 기타장기종업원급여의 증가(감소) | M34: 0
B35: 퇴직금의 지급 | C35: =SUMIF(CF정산표!$K$179:$K$199,연결CF!B35,CF정산표!$N$179:$N$199) -> -1064848974 | D35: =IFERROR(VLOOKUP(B35,$L$6:$M$65,2,0),) -> -61814462 | L35: 퇴직금의 지급 | M35: -61814462
B36: 2.이자의수취 | C36: =SUMIF(CF정산표!$K$179:$K$199,연결CF!B36,CF정산표!$N$179:$N$199) -> 14072249 | D36: =IFERROR(VLOOKUP(B36,$L$6:$M$65,2,0),) -> 21717532 | L36: 2.이자의수취 | M36: 21717532
B37: 3.이자의지급 | C37: =SUMIF(CF정산표!$K$179:$K$199,연결CF!B37,CF정산표!$N$179:$N$199) -> -91837405 | D37: =IFERROR(VLOOKUP(B37,$L$6:$M$65,2,0),) -> -84792594 | L37: 3.이자의지급 | M37: -84792594
B38: 4.법인세등환급액(부담액) | C38: =SUMIF(CF정산표!$K$179:$K$199,연결CF!B38,CF정산표!$N$179:$N$199) -> 3779722 | D38: =IFERROR(VLOOKUP(B38,$L$6:$M$65,2,0),) -> 2574016 | L38: 4.법인세등환급액(부담액) | M38: 2574016
B39: Ⅱ.투자활동으로인한현금흐름 | C39: =C40+C46 -> -8347846978 | D39: =D40+D46 -> -520360666 | L39: Ⅱ.투자활동으로인한현금흐름 | M39: =M40+M46 -> -520360666 | N39: =M39-D39 -> 0
B40: 1. 투자활동으로 인한 현금유입액 | C40: =SUM(C41:C45) -> 18208436 | D40: =SUM(D41:D45) -> 28087257 | L40: 1. 투자활동으로 인한 현금유입액 | M40: =SUM(M41:M45) -> 28087257
B41: 단기대여금의 감소 | C41: =CF정산표!T180 -> 1250001 | D41: =IFERROR(VLOOKUP(B41,$L$6:$M$65,2,0),) -> 3333335 | L41: 단기대여금의 감소 | M41: 3333335
B42: 단기금융상품의 감소 | C42: =CF정산표!T179 -> 0 | D42: =IFERROR(VLOOKUP(B42,$L$6:$M$65,2,0),) -> 0 | L42: 단기금융상품의 감소 | M42: 0
B43: 유형자산의 처분 | C43: =CF정산표!T69 -> 452135 | D43: =IFERROR(VLOOKUP(B43,$L$6:$M$65,2,0),) -> 5900000 | L43: 유형자산의 처분 | M43: 5900000
B44: 기타비유동금융자산의 감소 | C44: =CF정산표!T185+CF정산표!T184 -> 16506300 | D44: =IFERROR(VLOOKUP(B44,$L$6:$M$65,2,0),) -> 16853922 | L44: 기타비유동금융자산의 감소 | M44: 16853922
B45: 기타유동금융자산의 감소 | C45: 0 | D45: =IFERROR(VLOOKUP(B45,$L$6:$M$65,2,0),) -> 2000000 | L45: 기타유동금융자산의 감소 | M45: 2000000
B46: 2. 투자활동으로 인한 현금유출액 | C46: =-SUM(C47:C52) -> -8366055414 | D46: =-SUM(D47:D52) -> -548447923 | L46: 2. 투자활동으로 인한 현금유출액 | M46: =-SUM(M47:M53) -> -548447923
B47: 단기대여금의 증가 | C47: 0 | D47: =IFERROR(VLOOKUP(B47,$L$6:$M$65,2,0),) -> 0 | L47: 단기금융상품의 증가 | M47: 0
B48: 기타보증금의 증가 | C48: =CF정산표!Q185 -> 640000 | D48: =IFERROR(VLOOKUP(B48,$L$6:$M$65,2,0),) -> 0 | L48: 단기대여금의 증가 | M48: 0
B49: 임차보증금의 증가 | C49: =CF정산표!Q184 -> 6000000 | D49: =IFERROR(VLOOKUP(B49,$L$6:$M$65,2,0),) -> 0 | L49: 종속기업투자주식의 증가 | M49: 0
B50: 유형자산의 취득 | C50: =CF정산표!Q182 -> 940715535 | D50: =IFERROR(VLOOKUP(B50,$L$6:$M$65,2,0),) -> 548447923 | L50: 임차보증금의 증가 | M50: 0
B51: 무형자산의 취득 | C51: =CF정산표!Q183 -> 95882479 | D51: =IFERROR(VLOOKUP(B51,$L$6:$M$65,2,0),) -> 0 | L51: 유형자산의 취득 | M51: 548447923
B52: 연결범위변동 | C52: =CF정산표!Q180 -> 7322817400 | D52: =IFERROR(VLOOKUP(B52,$L$6:$M$65,2,0),) -> 0 | L52: 무형자산의 취득 | M52: 0
B53: Ⅲ.재무활동으로인한현금흐름 | C53: =C54+C59 -> -359236850 | D53: =D54+D59 -> -261431357 | L53: 기타비유동금융자산의 증가 | M53: 0 | N53: =M54-D53 -> 0
B54: 1.재무활동으로인한현금유입액 | C54: =SUM(C55:C58) -> 0 | D54: =SUM(D55:D58) -> 92265834 | L54: Ⅲ.재무활동으로인한현금흐름 | M54: =M55+M61 -> -261431357
B55: 유상증자 | C55: =CF정산표!Z183 -> 0 | D55: =IFERROR(VLOOKUP(B55,$L$6:$M$65,2,0),) -> 0 | L55: 1.재무활동으로인한현금유입액 | M55: =SUM(M56:M60) -> 92265834
B56: 단기차입금의 차입 | C56: =CF정산표!Z179 -> 0 | D56: =IFERROR(VLOOKUP(B56,$L$6:$M$65,2,0),) -> 0 | L56: 단기차입금의 차입 | M56: 0
B57: 장기차입금의 차입 | C57: =CF정산표!Z180 -> 0 | D57: =IFERROR(VLOOKUP(B57,$L$6:$M$65,2,0),) -> 0 | L57: 장기차입금의 차입 | M57: 0
B58: 주식선택권 행사 | C58: =CF정산표!Z182 -> 0 | D58: =IFERROR(VLOOKUP(B58,$L$6:$M$65,2,0),) -> 92265834 | L58: 유상증자 | M58: 0
B59: 2.재무활동으로인한현금유출액 | C59: =-SUM(C60:C62) -> -359236850 | D59: =-SUM(D60:D62) -> -353697191 | L59: 장기차입금의 차입 | M59: 0
B60: 단기차입금의 상환 | C60: =CF정산표!W180 -> 0 | D60: =IFERROR(VLOOKUP(B60,$L$6:$M$65,2,0),) -> 0 | L60: 주식선택권 행사 | M60: 92265834
B61: 리스부채의 상환 | C61: =CF정산표!W179 -> 275936850 | D61: =IFERROR(VLOOKUP(B61,$L$6:$M$65,2,0),) -> 303717191 | L61: 2.재무활동으로인한현금유출액 | M61: =-SUM(M62:M64) -> -353697191
B62: 유동성장기차입금 상환 | C62: =CF정산표!W181 -> 83300000 | D62: =IFERROR(VLOOKUP(B62,$L$6:$M$65,2,0),) -> 49980000 | L62: 단기차입금의 상환 | M62: 0
B63: IV.현금및현금성자산의 환율변동효과 | C63: =CF정산표!AC11+CF정산표!H11-CF정산표!K11 -> -13318794 | D63: =IFERROR(VLOOKUP(B63,$L$6:$M$68,2,0),) -> 13508450 | L63: 리스부채의 상환 | M63: 303717191
B64: V.현금의증가(Ⅰ+Ⅱ+Ⅲ+IV) | C64: =C2+C39+C53+C63 -> -7518107229 | D64: =D2+D39+D53+D63 -> 415598695 | L64: 유동성장기차입금 상환 | M64: 49980000
B65: VI.기초의현금 | C65: =연결BS!E4 -> 19371699448 | D65: 2245118706 | L65: IV.현금및현금성자산의 환율변동효과 | M65: 13508450
B66: VII.기말의현금 | C66: =SUM(C64:C65) -> 11853592219 | D66: =SUM(D64:D65) -> 2660717401 | L66: V.현금의증가(Ⅰ+Ⅱ+Ⅲ+IV) | M66: =M2+M39+M54+M65 -> 415598695
C67: =연결BS!D4 -> 11853592219 | D67: =M68 -> 2660717401 | L67: VI.기초의현금 | M67: 2245118706
C68: =C66-C67 -> 0 | D68: =D66-D67 -> 0 | L68: VII.기말의현금 | M68: =SUM(M66:M67) -> 2660717401
C69: =C67=C66 -> TRUE | D69: =D67=D66 -> TRUE

Sheet 연결CF_IFRS18
B1: 연결 현금흐름표 (IFRS 18 / IAS 7 개정 기준)
B2: ※ [연결CF] 시트 금액을 연동. IFRS 18(IAS 7 개정): ①간접법 출발점을 영업손익으로 변경 ②이자·배당 수취는 투자, 이자·배당 지급은 재무로 고정 ③영업손익에 포함되지 않는 손익(투자·재무·법인세)은 조정항목에서 제외
B3: 과목 | D3: =연결CF!C1 -> 46203 | E3: =연결CF!D1 -> 45838 | G3: 손익 범주 판정용 계정과목 (입력) | H3: IFRS 18 구분 | I3: 비고
B4: Ⅰ.영업활동으로인한현금흐름 | D4: =D5+D38 -> 1280060549 | E4: =E5+E38 -> 1246957330
B5: 1.영업에서창출된현금 | D5: =D6+D7+D29 -> 1276280827 | E5: =E6+E7+E29 -> 1244383314
B6: 가.영업손익 (IFRS 18) | D6: ='연결PL_IFRS18'!D12 -> -785717115 | E6: ='연결PL_IFRS18'!E12 -> 1018363428
B7: 나.조정 (영업손익에 포함된 비현금 항목) | D7: =SUM(D8:D28) -> 835171088 | E7: =SUM(E8:E28) -> 980401621
B8: =연결CF!B6 -> 대손상각비 | D8: =IF($H8="영업",연결CF!C6,0) -> -83305712 | E8: =IF($H8="영업",연결CF!D6,0) -> 56559960 | G8: 대손상각비 | H8: =IF(G8="","영업",IFERROR(INDEX('연결PL_IFRS18'!$S$69:$S$133,MATCH(G8,'연결PL_IFRS18'!$B$69:$B$133,0)),"오류")) -> 영업 | I8: =IF(H8="영업","",IF(H8="오류","계정과목명 확인 필요","영업손익 미포함 → 조정 제외"))
B9: =연결CF!B7 -> 이자수익 | D9: =IF($H9="영업",연결CF!C7,0) -> 0 | E9: =IF($H9="영업",연결CF!D7,0) -> 0 | G9: 이자수익 | H9: =IF(G9="","영업",IFERROR(INDEX('연결PL_IFRS18'!$S$69:$S$133,MATCH(G9,'연결PL_IFRS18'!$B$69:$B$133,0)),"오류")) -> 투자 | I9: =IF(H9="영업","",IF(H9="오류","계정과목명 확인 필요","영업손익 미포함 → 조정 제외")) -> 영업손익 미포함 → 조정 제외
B10: =연결CF!B8 -> 유형자산처분이익 | D10: =IF($H10="영업",연결CF!C8,0) -> -1202135 | E10: =IF($H10="영업",연결CF!D8,0) -> -1054000 | G10: 유형자산처분이익 | H10: =IF(G10="","영업",IFERROR(INDEX('연결PL_IFRS18'!$S$69:$S$133,MATCH(G10,'연결PL_IFRS18'!$B$69:$B$133,0)),"오류")) -> 영업 | I10: =IF(H10="영업","",IF(H10="오류","계정과목명 확인 필요","영업손익 미포함 → 조정 제외"))
B11: =연결CF!B9 -> 외화환산이익 | D11: =IF($H11="영업",연결CF!C9,0) -> -37603839 | E11: =IF($H11="영업",연결CF!D9,0) -> -3042 | G11: 외화환산이익 | H11: =IF(G11="","영업",IFERROR(INDEX('연결PL_IFRS18'!$S$69:$S$133,MATCH(G11,'연결PL_IFRS18'!$B$69:$B$133,0)),"오류")) -> 영업 | I11: =IF(H11="영업","",IF(H11="오류","계정과목명 확인 필요","영업손익 미포함 → 조정 제외"))
B12: =연결CF!B10 -> 재고자산평가손실(환입) | D12: =IF($H12="영업",연결CF!C10,0) -> 131193174 | E12: =IF($H12="영업",연결CF!D10,0) -> 15216604 | H12: =IF(G12="","영업",IFERROR(INDEX('연결PL_IFRS18'!$S$69:$S$133,MATCH(G12,'연결PL_IFRS18'!$B$69:$B$133,0)),"오류")) -> 영업 | I12: =IF(H12="영업","",IF(H12="오류","계정과목명 확인 필요","영업손익 미포함 → 조정 제외"))
B13: =연결CF!B11 -> 퇴직급여 | D13: =IF($H13="영업",연결CF!C11,0) -> 188019390 | E13: =IF($H13="영업",연결CF!D11,0) -> 177665682 | G13: 퇴직급여 | H13: =IF(G13="","영업",IFERROR(INDEX('연결PL_IFRS18'!$S$69:$S$133,MATCH(G13,'연결PL_IFRS18'!$B$69:$B$133,0)),"오류")) -> 영업 | I13: =IF(H13="영업","",IF(H13="오류","계정과목명 확인 필요","영업손익 미포함 → 조정 제외"))
B14: =연결CF!B12 -> 주식보상비 | D14: =IF($H14="영업",연결CF!C12,0) -> 0 | E14: =IF($H14="영업",연결CF!D12,0) -> 0 | G14: 주식보상비 | H14: =IF(G14="","영업",IFERROR(INDEX('연결PL_IFRS18'!$S$69:$S$133,MATCH(G14,'연결PL_IFRS18'!$B$69:$B$133,0)),"오류")) -> 영업 | I14: =IF(H14="영업","",IF(H14="오류","계정과목명 확인 필요","영업손익 미포함 → 조정 제외"))
B15: =연결CF!B13 -> 이자비용 | D15: =IF($H15="영업",연결CF!C13,0) -> 0 | E15: =IF($H15="영업",연결CF!D13,0) -> 0 | G15: 이자비용 | H15: =IF(G15="","영업",IFERROR(INDEX('연결PL_IFRS18'!$S$69:$S$133,MATCH(G15,'연결PL_IFRS18'!$B$69:$B$133,0)),"오류")) -> 재무 | I15: =IF(H15="영업","",IF(H15="오류","계정과목명 확인 필요","영업손익 미포함 → 조정 제외")) -> 영업손익 미포함 → 조정 제외
B16: =연결CF!B14 -> 감가상각비 | D16: =IF($H16="영업",연결CF!C14,0) -> 585661920 | E16: =IF($H16="영업",연결CF!D14,0) -> 497372122 | G16: 감가상각비 | H16: =IF(G16="","영업",IFERROR(INDEX('연결PL_IFRS18'!$S$69:$S$133,MATCH(G16,'연결PL_IFRS18'!$B$69:$B$133,0)),"오류")) -> 영업 | I16: =IF(H16="영업","",IF(H16="오류","계정과목명 확인 필요","영업손익 미포함 → 조정 제외"))
B17: =연결CF!B15 -> 무형자산상각비 | D17: =IF($H17="영업",연결CF!C15,0) -> 21529107 | E17: =IF($H17="영업",연결CF!D15,0) -> 144426793 | G17: 무형고정자산상각 | H17: =IF(G17="","영업",IFERROR(INDEX('연결PL_IFRS18'!$S$69:$S$133,MATCH(G17,'연결PL_IFRS18'!$B$69:$B$133,0)),"오류")) -> 영업 | I17: =IF(H17="영업","",IF(H17="오류","계정과목명 확인 필요","영업손익 미포함 → 조정 제외"))
B18: =연결CF!B16 -> 영업권손상차손 | D18: =IF($H18="영업",연결CF!C16,0) -> 0 | E18: =IF($H18="영업",연결CF!D16,0) -> 0 | H18: =IF(G18="","영업",IFERROR(INDEX('연결PL_IFRS18'!$S$69:$S$133,MATCH(G18,'연결PL_IFRS18'!$B$69:$B$133,0)),"오류")) -> 영업 | I18: =IF(H18="영업","",IF(H18="오류","계정과목명 확인 필요","영업손익 미포함 → 조정 제외"))
B19: =연결CF!B17 -> 유형자산처분손실 | D19: =IF($H19="영업",연결CF!C17,0) -> 4825402 | E19: =IF($H19="영업",연결CF!D17,0) -> 3098042 | G19: 유형자산처분손실 | H19: =IF(G19="","영업",IFERROR(INDEX('연결PL_IFRS18'!$S$69:$S$133,MATCH(G19,'연결PL_IFRS18'!$B$69:$B$133,0)),"오류")) -> 영업 | I19: =IF(H19="영업","",IF(H19="오류","계정과목명 확인 필요","영업손익 미포함 → 조정 제외"))
B20: =연결CF!B18 -> 외화환산손실 | D20: =IF($H20="영업",연결CF!C18,0) -> 2 | E20: =IF($H20="영업",연결CF!D18,0) -> 58201925 | G20: 외화환산손실 | H20: =IF(G20="","영업",IFERROR(INDEX('연결PL_IFRS18'!$S$69:$S$133,MATCH(G20,'연결PL_IFRS18'!$B$69:$B$133,0)),"오류")) -> 영업 | I20: =IF(H20="영업","",IF(H20="오류","계정과목명 확인 필요","영업손익 미포함 → 조정 제외"))
B21: =연결CF!B19 -> 법인세비용 | D21: =IF($H21="영업",연결CF!C19,0) -> 0 | E21: =IF($H21="영업",연결CF!D19,0) -> 0 | G21: 법인세비용 | H21: =IF(G21="","영업",IFERROR(INDEX('연결PL_IFRS18'!$S$69:$S$133,MATCH(G21,'연결PL_IFRS18'!$B$69:$B$133,0)),"오류")) -> 법인세 | I21: =IF(H21="영업","",IF(H21="오류","계정과목명 확인 필요","영업손익 미포함 → 조정 제외")) -> 영업손익 미포함 → 조정 제외
B22: =연결CF!B20 -> 복리후생비 | D22: =IF($H22="영업",연결CF!C20,0) -> 37001898 | E22: =IF($H22="영업",연결CF!D20,0) -> 34571148 | H22: =IF(G22="","영업",IFERROR(INDEX('연결PL_IFRS18'!$S$69:$S$133,MATCH(G22,'연결PL_IFRS18'!$B$69:$B$133,0)),"오류")) -> 영업 | I22: =IF(H22="영업","",IF(H22="오류","계정과목명 확인 필요","영업손익 미포함 → 조정 제외"))
B23: =연결CF!B21 -> 상환전환우선주부채평가손실 | D23: =IF($H23="영업",연결CF!C21,0) -> 0 | E23: =IF($H23="영업",연결CF!D21,0) -> 0 | H23: =IF(G23="","영업",IFERROR(INDEX('연결PL_IFRS18'!$S$69:$S$133,MATCH(G23,'연결PL_IFRS18'!$B$69:$B$133,0)),"오류")) -> 영업 | I23: =IF(H23="영업","",IF(H23="오류","계정과목명 확인 필요","영업손익 미포함 → 조정 제외"))
B24: =연결CF!B22 -> 당기손익공정가치측정금융자산평가손실 | D24: =IF($H24="영업",연결CF!C22,0) -> 0 | E24: =IF($H24="영업",연결CF!D22,0) -> 0 | G24: 당기손익-공정가치측정금융자산평가손실 | H24: =IF(G24="","영업",IFERROR(INDEX('연결PL_IFRS18'!$S$69:$S$133,MATCH(G24,'연결PL_IFRS18'!$B$69:$B$133,0)),"오류")) -> 투자 | I24: =IF(H24="영업","",IF(H24="오류","계정과목명 확인 필요","영업손익 미포함 → 조정 제외")) -> 영업손익 미포함 → 조정 제외
B25: =연결CF!B23 -> 기타의 대손상각비(환입) | D25: =IF($H25="영업",연결CF!C23,0) -> -3000000 | E25: =IF($H25="영업",연결CF!D23,0) -> -3000000 | G25: 기타의대손상각비환입 | H25: =IF(G25="","영업",IFERROR(INDEX('연결PL_IFRS18'!$S$69:$S$133,MATCH(G25,'연결PL_IFRS18'!$B$69:$B$133,0)),"오류")) -> 영업 | I25: =IF(H25="영업","",IF(H25="오류","계정과목명 확인 필요","영업손익 미포함 → 조정 제외"))
B26: =연결CF!B24 -> 관계기업투자주식처분이익 | D26: =IF($H26="영업",연결CF!C24,0) -> 0 | E26: =IF($H26="영업",연결CF!D24,0) -> 0 | G26: 관계기업투자주식처분이익 | H26: =IF(G26="","영업",IFERROR(INDEX('연결PL_IFRS18'!$S$69:$S$133,MATCH(G26,'연결PL_IFRS18'!$B$69:$B$133,0)),"오류")) -> 투자 | I26: =IF(H26="영업","",IF(H26="오류","계정과목명 확인 필요","영업손익 미포함 → 조정 제외")) -> 영업손익 미포함 → 조정 제외
B27: =연결CF!B25 -> 지분법손실 | D27: =IF($H27="영업",연결CF!C25,0) -> 0 | E27: =IF($H27="영업",연결CF!D25,0) -> 0 | G27: 관계기업투자손실 | H27: =IF(G27="","영업",IFERROR(INDEX('연결PL_IFRS18'!$S$69:$S$133,MATCH(G27,'연결PL_IFRS18'!$B$69:$B$133,0)),"오류")) -> 투자 | I27: =IF(H27="영업","",IF(H27="오류","계정과목명 확인 필요","영업손익 미포함 → 조정 제외")) -> 영업손익 미포함 → 조정 제외
B28: =연결CF!B26 -> 환불부채 | D28: =IF($H28="영업",연결CF!C26,0) -> -7948119 | E28: =IF($H28="영업",연결CF!D26,0) -> -2653613 | H28: =IF(G28="","영업",IFERROR(INDEX('연결PL_IFRS18'!$S$69:$S$133,MATCH(G28,'연결PL_IFRS18'!$B$69:$B$133,0)),"오류")) -> 영업 | I28: =IF(H28="영업","",IF(H28="오류","계정과목명 확인 필요","영업손익 미포함 → 조정 제외"))
B29: 다.영업활동으로인한자산부채의변동 | D29: =SUM(D30:D37) -> 1226826854 | E29: =SUM(E30:E37) -> -754381735
B30: =연결CF!B28 -> 매출채권및기타채권의 감소(증가) | D30: =연결CF!C28 -> 502587042 | E30: =연결CF!D28 -> -146111841
B31: =연결CF!B29 -> 기타유동자산의 감소(증가) | D31: =연결CF!C29 -> 433657614 | E31: =연결CF!D29 -> -140049917
B32: =연결CF!B30 -> 재고자산의 감소(증가) | D32: =연결CF!C30 -> -326232101 | E32: =연결CF!D30 -> 77359122
B33: =연결CF!B31 -> 매입채무및기타채무의 증가(감소) | D33: =연결CF!C31 -> 1866250998 | E33: =연결CF!D31 -> -456512459
B34: =연결CF!B32 -> 임차보증금유동 | D34: =연결CF!C32 -> 0 | E34: =연결CF!D32 -> 0
B35: =연결CF!B33 -> 기타유동부채의 증가(감소) | D35: =연결CF!C33 -> -180207725 | E35: =연결CF!D33 -> -27252178
B36: =연결CF!B34 -> 기타장기종업원급여의 증가(감소) | D36: =연결CF!C34 -> -4380000 | E36: =연결CF!D34 -> 0
B37: =연결CF!B35 -> 퇴직금의 지급 | D37: =연결CF!C35 -> -1064848974 | E37: =연결CF!D35 -> -61814462
B38: 2.법인세등환급액(부담액) | D38: =연결CF!C38 -> 3779722 | E38: =연결CF!D38 -> 2574016
B39: Ⅱ.투자활동으로인한현금흐름 | D39: =D40+D48 -> -8333774729 | E39: =E40+E48 -> -498643134
B40: 1.투자활동으로 인한 현금유입액 | D40: =SUM(D41:D47) -> 32280685 | E40: =SUM(E41:E47) -> 49804789
B41: =연결CF!B41 -> 단기대여금의 감소 | D41: =연결CF!C41 -> 1250001 | E41: =연결CF!D41 -> 3333335
B42: =연결CF!B42 -> 단기금융상품의 감소 | D42: =연결CF!C42 -> 0 | E42: =연결CF!D42 -> 0
B43: =연결CF!B43 -> 유형자산의 처분 | D43: =연결CF!C43 -> 452135 | E43: =연결CF!D43 -> 5900000
B44: =연결CF!B44 -> 기타비유동금융자산의 감소 | D44: =연결CF!C44 -> 16506300 | E44: =연결CF!D44 -> 16853922
B45: =연결CF!B45 -> 기타유동금융자산의 감소 | D45: =연결CF!C45 -> 0 | E45: =연결CF!D45 -> 2000000
B46: 이자의 수취 (IFRS 18: 투자활동 분류) | D46: =연결CF!C36 -> 14072249 | E46: =연결CF!D36 -> 21717532
B47: 배당금의 수취 (IFRS 18: 투자활동 분류) | D47: 0 | E47: 0
B48: 2.투자활동으로 인한 현금유출액 | D48: =-SUM(D49:D54) -> -8366055414 | E48: =-SUM(E49:E54) -> -548447923
B49: =연결CF!B47 -> 단기대여금의 증가 | D49: =연결CF!C47 -> 0 | E49: =연결CF!D47 -> 0
B50: =연결CF!B48 -> 기타보증금의 증가 | D50: =연결CF!C48 -> 640000 | E50: =연결CF!D48 -> 0
B51: =연결CF!B49 -> 임차보증금의 증가 | D51: =연결CF!C49 -> 6000000 | E51: =연결CF!D49 -> 0
B52: =연결CF!B50 -> 유형자산의 취득 | D52: =연결CF!C50 -> 940715535 | E52: =연결CF!D50 -> 548447923
B53: =연결CF!B51 -> 무형자산의 취득 | D53: =연결CF!C51 -> 95882479 | E53: =연결CF!D51 -> 0
B54: =연결CF!B52 -> 연결범위변동 | D54: =연결CF!C52 -> 7322817400 | E54: =연결CF!D52 -> 0
B55: Ⅲ.재무활동으로인한현금흐름 | D55: =D56+D61 -> -451074255 | E55: =E56+E61 -> -346223951
B56: 1.재무활동으로인한현금유입액 | D56: =SUM(D57:D60) -> 0 | E56: =SUM(E57:E60) -> 92265834
B57: =연결CF!B55 -> 유상증자 | D57: =연결CF!C55 -> 0 | E57: =연결CF!D55 -> 0
B58: =연결CF!B56 -> 단기차입금의 차입 | D58: =연결CF!C56 -> 0 | E58: =연결CF!D56 -> 0
B59: =연결CF!B57 -> 장기차입금의 차입 | D59: =연결CF!C57 -> 0 | E59: =연결CF!D57 -> 0
B60: =연결CF!B58 -> 주식선택권 행사 | D60: =연결CF!C58 -> 0 | E60: =연결CF!D58 -> 92265834
B61: 2.재무활동으로인한현금유출액 | D61: =-SUM(D62:D66) -> -451074255 | E61: =-SUM(E62:E66) -> -438489785
B62: =연결CF!B60 -> 단기차입금의 상환 | D62: =연결CF!C60 -> 0 | E62: =연결CF!D60 -> 0
B63: =연결CF!B61 -> 리스부채의 상환 | D63: =연결CF!C61 -> 275936850 | E63: =연결CF!D61 -> 303717191
B64: =연결CF!B62 -> 유동성장기차입금 상환 | D64: =연결CF!C62 -> 83300000 | E64: =연결CF!D62 -> 49980000
B65: 이자의 지급 (IFRS 18: 재무활동 분류) | D65: =-연결CF!C37 -> 91837405 | E65: =-연결CF!D37 -> 84792594
B66: 배당금의 지급 (재무활동) | D66: 0 | E66: 0
B67: Ⅳ.현금및현금성자산의 환율변동효과 | D67: =연결CF!C63 -> -13318794 | E67: =연결CF!D63 -> 13508450
B68: Ⅴ.현금의증가(Ⅰ+Ⅱ+Ⅲ+Ⅳ) | D68: =D4+D39+D55+D67 -> -7518107229 | E68: =E4+E39+E55+E67 -> 415598695
B69: Ⅵ.기초의현금 | D69: =연결CF!C65 -> 19371699448 | E69: =연결CF!D65 -> 2245118706
B70: Ⅶ.기말의현금 | D70: =D68+D69 -> 11853592219 | E70: =E68+E69 -> 2660717401
B72: [검증] 기존 현금흐름표 대비 (모두 0이어야 함)
B73: 현금의 증가 - 기존 CF | D73: =D68-연결CF!C64 -> 0 | E73: =E68-연결CF!D64 -> 0
B74: 기말의 현금 - 기존 CF | D74: =D70-연결CF!C66 -> 0 | E74: =E70-연결CF!D66 -> 0
B75: 영업활동 현금흐름 변동 = 이자수취·지급 재분류 효과 | D75: =D4-(연결CF!C2-연결CF!C36-연결CF!C37) -> 0 | E75: =E4-(연결CF!D2-연결CF!D36-연결CF!D37) -> 0
B76: 조정항목 구분 오류 건수 | D76: =COUNTIF(H8:H28,"오류") -> 0
B77: 종합 검증 | D77: =IF(SUMPRODUCT(ABS(D73:E76))=0,"OK","확인필요") -> OK
B79: [조정표] 기존 영업활동현금흐름 → IFRS 18 영업활동현금흐름
B80: 기존 영업활동으로인한현금흐름 | D80: =연결CF!C2 -> 1202295393 | E80: =연결CF!D2 -> 1183882268
B81: (-) 이자의 수취 (투자활동으로 이동) | D81: =-연결CF!C36 -> -14072249 | E81: =-연결CF!D36 -> -21717532
B82: (+) 이자의 지급 (재무활동으로 이동) | D82: =-연결CF!C37 -> 91837405 | E82: =-연결CF!D37 -> 84792594
B83: IFRS 18 영업활동으로인한현금흐름 | D83: =SUM(D80:D82) -> 1280060549 | E83: =SUM(E80:E82) -> 1246957330
B85: [범례/가정]
B86: 파란글씨·노란 배경 = 입력 셀. G열에 해당 조정항목의 손익계산서 계정과목명을 입력하면 [연결PL_IFRS18]의 IFRS 18 구분이 H열에 자동 판정되고, 영업이 아니면 조정에서 제외됩니다(비워두면 영업으로 간주).
B87: 이자수취는 투자활동, 이자지급은 재무활동으로 고정 분류(IFRS 18 에 따른 IAS 7 개정, 선택 불가). 배당금 수취/지급은 해당 시 노란 셀에 입력.
B88: 법인세 납부(환급)는 영업활동 유지 (투자·재무활동에 특정되는 경우 제외). 외화환산손익 등 영업손익 범주 변경 시 비영업 현금 효과는 검증행 3에서 확인.

Sheet 연결CE
B2: 자본변동표
B3: 과목 | C3: 자본금 | D3: 자본잉여금 | E3: 기타자본항목 | F3: 이익잉여금(결손금) | G3: 비지배지분 | H3: 총계
B4: 2025.01.01(전기초) | C4: 3123279500 | D4: 12384121289 | E4: 429109150 | F4: -9977866938 | G4: 0 | H4: =SUM(C4:G4) -> 5958643001 | I4: 5958643001 | J4: =I4-H4 -> 0
B5: 총포괄손익:
B6: 당기순이익 | C6: 0 | D6: 0 | E6: 0 | F6: 989649425 | G6: 0 | H6: =SUM(C6:G6) -> 989649425
B7: 순확정급여부채의 재측정요소 | C7: 0 | D7: 0 | E7: 0 | F7: 40134025 | G7: 0 | H7: =SUM(C7:G7) -> 40134025
B8: 해외사업장환산외환차이 | C8: 0 | D8: 0 | E8: -17279474 | F8: 0 | G8: 0 | H8: =SUM(C8:G8) -> -17279474
B9: 자본에 직접 반영된 소유주와의 거래:
B10: 유상증자 | C10: 2511000000 | D10: 32474515340 | E10: 0 | F10: 0 | G10: 0 | H10: =SUM(C10:G10) -> 34985515340
B11: 주식매수선택권의 행사 | C11: 56912000 | D11: 298745669 | E11: -88626565 | H11: =SUM(C11:G11) -> 267031104
B12: 주식보상비용 | C12: 0 | D12: 0 | E12: 135571460 | F12: 0 | G12: 0 | H12: =SUM(C12:G12) -> 135571460
B13: 2025.12.31(전기말) | C13: =SUM(C4:C12) -> 5691191500 | D13: =SUM(D4:D12) -> 45157382298 | E13: =SUM(E4:E12) -> 458774571 | F13: =SUM(F4:F12) -> -8948083488 | G13: =SUM(G4:G12) -> 0 | H13: =SUM(H4:H12) -> 42359264881 | I13: 42359264881 | J13: =I13-H13 -> 0 | K13: =J13=J4 -> TRUE
B14: 2026.01.01(당기초) | C14: 5691191500 | D14: 45157382298 | E14: 458774571 | F14: -8948083488 | G14: 0 | H14: =SUM(C14:G14) -> 42359264881
B15: 총포괄손익:
B16: 당기순이익 | C16: 0 | D16: 0 | E16: 0 | F16: =연결PL!D101 -> -867554501 | G16: =연결PL!D103 -> 0 | H16: =SUM(C16:G16) -> -867554501
B17: 순확정급여부채의 재측정요소 | C17: 0 | D17: 0 | E17: 0 | F17: =연결PL!D106 -> 0 | G17: 0 | H17: =SUM(C17:G17) -> 0
B18: 해외사업장환산외환차이 | C18: 0 | D18: 0 | E18: =연결PL!D108 -> 11298394 | F18: 0 | G18: 0 | H18: =SUM(C18:G18) -> 11298394
B19: 자본에 직접 반영된 소유주와의 거래:
B20: 유상증자 | C20: 0 | D20: 0 | E20: 0 | F20: 0 | G20: 0 | H20: =SUM(C20:G20) -> 0
B21: 주식매수선택권의 행사 | C21: 0 | D21: 0 | E21: 0 | F21: 0 | G21: 0 | H21: =SUM(C21:G21) -> 0
B22: 연결범위변동 | C22: 0 | D22: 0 | E22: 0 | F22: 0 | G22: =RIC!I73 -> 117986065 | H22: =SUM(C22:G22) -> 117986065
B23: 2026.12.31(당기말) | C23: =SUM(C14:C22) -> 5691191500 | D23: =SUM(D14:D22) -> 45157382298 | E23: =SUM(E14:E22) -> 470072965 | F23: =SUM(F14:F22) -> -9815637989 | G23: =SUM(G14:G22) -> 117986065 | H23: =SUM(H14:H22) -> 41620994839 | I23: =연결BS!D115 -> 41620994839 | J23: =I23-H23 -> 0
C25: =C14-연결BS!E105 -> 0 | D25: =D14-연결BS!E106 -> 0 | E25: =E14-연결BS!E109 -> 0 | F25: =F14-연결BS!E112 -> 0 | H25: =H14-연결BS!E115 -> 0
C26: =C23-연결BS!D104 -> 0 | D26: =D23-연결BS!D106 -> 0 | E26: =E23-연결BS!D109 -> 0 | F26: =F23-연결BS!D112 -> 0 | G26: =G23-연결BS!D114 -> 0 | H26: =H23-연결BS!D115 -> 0

Sheet 공시PL
D2: 과목 | E2: 2026 | F2: 2026 | G2: 2025 | H2: 2025 | K2: 과 목 | L2: 2026
E3: 3개월 | F3: 누적 | G3: 3개월 | H3: 누적 | L3: 3개월 | M3: 누적
D4: 매출액 | E4: =F4-M4 -> 4518456853 | F4: =연결PL!D2 -> 8812244469 | G4: 4268206262 | H4: 9441165967 | K4: 매출액 | M4: 4293787616
D5: 매출원가 | E5: =F5-M5 -> 1797042032 | F5: =연결PL!D7 -> 3634217621 | G5: 1458903526 | H5: 3581100990 | K5: 매출원가 | M5: 1837175589
D6: 매출총이익 | E6: =E4-E5 -> 2721414821 | F6: =F4-F5 -> 5178026848 | G6: 2809302736 | H6: 5860064977 | K6: 매출총이익 | M6: 2456612027
D7: 판매비와관리비 | E7: =F7-M7 -> 3157559749 | F7: =연결PL!D35 -> 5969068326 | G7: 2405235596 | H7: 4763859751 | K7: 판매비와관리비 | M7: 2811508577
D8: 영업이익(손실) | E8: =E6-E7 -> -436144928 | F8: =F6-F7 -> -791041478 | G8: 404067140 | H8: 1096205226 | K8: 영업이익(손실) | M8: -354896550
D9: 기타수익 | E9: =F9-M9 -> 2107337429 | F9: =연결PL!D69 -> 2109602184 | G9: 1934393 | H9: 8256143 | K9: 기타수익 | M9: 2264755
D10: 기타비용 | E10: =F10-M10 -> 9222257 | F10: =연결PL!D77 -> 9488772 | G10: 6528994 | H10: 7087062 | K10: 기타비용 | M10: 266515
D11: 금융수익 | E11: =F11-M11 -> 70594021 | F11: =연결PL!D85 -> 169546726 | G11: 7723398 | H11: 48738081 | K11: 금융수익 | M11: 98952705
D12: 금융비용 | E12: =F12-M12 -> 214204709 | F12: =연결PL!D90 -> 273243495 | G12: 112078187 | H12: 145282026 | K12: 금융비용 | M12: 59038786
D13: 지분법손익 | E13: =F13-M13 -> -1282816342 | F13: =연결PL!D96 -> -2067945777 | G13: 0 | H13: 0 | K13: 지분법손익 | M13: -785129435
D14: 법인세비용차감전순이익(손실) | E14: =E8+E9-E10+E11-E12+E13 -> 235543214 | F14: =F8+F9-F10+F11-F12+F13 -> -862570612 | G14: 295117750 | H14: 1000830362 | K14: 법인세비용차감전순이익(손실) | M14: -1098113826
D15: 법인세비용 | E15: =F15-M15 -> -3009004 | F15: =연결PL!D100 -> 4983889 | G15: -3233729 | H15: 4894989 | K15: 법인세비용 | M15: 7992893
D16: 분기순이익(손실) | E16: =E14-E15 -> 238552218 | F16: =F14-F15 -> -867554501 | G16: 298351479 | H16: 995935373 | K16: 반기순이익(손실) | M16: -1106106719
D17: 지배기업의 소유주 귀속 분기순이익 | E17: =E16 -> 238552218 | F17: =F16 -> -867554501 | G17: 298351479 | H17: 995935373 | K17: 지배기업의 소유주 귀속 반기순이익 | M17: -1106106719
D18: 비지배지분 귀속 분기순이익 | E18: 0 | F18: 0 | G18: 0 | H18: 0 | K18: 비지배지분 귀속 반기순이익 | M18: 0
D19: 기타포괄손익 | E19: =E20+E22 -> 3267871 | F19: =F20+F22 -> 11298394 | G19: -17734655 | H19: -26600734 | K19: 기타포괄손익 | M19: 8030523
D20: 당기손익으로 재분류되지 않는 항목 | E20: =E21 -> 0 | F20: =F21 -> 0 | G20: 0 | H20: 0 | K20: 당기손익으로 재분류되지 않는 항목 | M20: 0
D21: 순확정급여부채의 재측정요소 | E21: =F21-M21 -> 0 | F21: =연결PL!D106 -> 0 | G21: 0 | H21: 0 | K21: 순확정급여부채의 재측정요소 | M21: 0
D22: 후속적으로당기손익으로 재분류되는항목 | E22: =E23 -> 3267871 | F22: =F23 -> 11298394 | G22: -17734655 | H22: -26600734 | K22: 후속적으로당기손익으로 재분류되는항목 | M22: 8030523
D23: 해외사업장환산외화차이 | E23: =F23-M23 -> 3267871 | F23: =연결PL!D108 -> 11298394 | G23: -17734655 | H23: -26600734 | K23: 해외사업장환산외화차이 | M23: 8030523
D24: 총포괄손익 | E24: =E16+E19 -> 241820089 | F24: =F16+F19 -> -856256107 | G24: 280616824 | H24: 969334639 | K24: 총포괄손익 | M24: -1098076196
D25: 지배기업의 소유주 귀속 총포괄손익 | E25: =E24 -> 241820089 | F25: =F24 -> -856256107 | G25: 280616824 | H25: 969334639 | K25: 지배기업의 소유주 귀속 총포괄손익 | M25: -1098076196
D26: 비지배지분 귀속 총포괄손익 | E26: 0 | F26: 0 | G26: 0 | H26: 0 | K26: 비지배지분 귀속 총포괄손익 | M26: 0
D27: 주당이익(손실) | K27: 주당이익(손실)
D28: 기본주당이익(손실) | E28: ='31'!C12 -> 21 | F28: ='31'!D12 -> -76 | G28: 47 | H28: 159 | K28: 기본주당이익(손실) | M28: -97
D29: 희석주당손익(손실) | E29: ='31'!C46 -> 21 | F29: ='31'!D46 -> -76 | G29: 47 | H29: 157 | K29: 희석주당손익(손실) | M29: -97
F30: =F24=연결PL!D109 -> TRUE

Sheet 공시PL_IFRS18
B1: 연결 손익계산서 (IFRS 18 기준)
B2: ※ [연결PL_IFRS18] 시트 연동 (범주 재분류는 해당 시트 매핑표에서 변경). 3개월 기간 컬럼은 1분기 계정별 자료가 없어 제외하고 누적 기준으로만 표시했습니다.
B4: 과 목 | C4: 주석 | D4: =연결PL!D1 -> 46203 | E4: =연결PL!E1 -> 45838
B5: Ⅰ. 영업 범주
B6: 매출액 | D6: ='연결PL_IFRS18'!D6 -> 8812244469 | E6: ='연결PL_IFRS18'!E6 -> 9441165967
B7: 매출원가 | D7: ='연결PL_IFRS18'!D7 -> 3634217621 | E7: ='연결PL_IFRS18'!E7 -> 3581100990
B8: 매출총이익 | D8: ='연결PL_IFRS18'!D8 -> 5178026848 | E8: ='연결PL_IFRS18'!E8 -> 5860064977
B9: 판매비와관리비 | D9: ='연결PL_IFRS18'!D9 -> 5969068326 | E9: ='연결PL_IFRS18'!E9 -> 4763859751
B10: 기타영업수익 | D10: ='연결PL_IFRS18'!D10 -> 189101679 | E10: ='연결PL_IFRS18'!E10 -> 28740950
B11: 기타영업비용 | D11: ='연결PL_IFRS18'!D11 -> 183777316 | E11: ='연결PL_IFRS18'!E11 -> 106582748
B12: 영업이익(손실) | D12: ='연결PL_IFRS18'!D12 -> -785717115 | E12: ='연결PL_IFRS18'!E12 -> 1018363428
B13: Ⅱ. 투자 범주
B14: 투자수익 | D14: ='연결PL_IFRS18'!D15 -> 2090047231 | E14: ='연결PL_IFRS18'!E15 -> 28253274
B15: 투자비용 | D15: ='연결PL_IFRS18'!D16 -> 2067945777 | E15: ='연결PL_IFRS18'!E16 -> 0
B16: 투자손익 | D16: ='연결PL_IFRS18'!D17 -> 22101454 | E16: ='연결PL_IFRS18'!E17 -> 28253274
B17: 재무 및 법인세 전 손익 | D17: ='연결PL_IFRS18'!D18 -> -763615661 | E17: ='연결PL_IFRS18'!E18 -> 1046616702
B18: Ⅲ. 재무 범주
B19: 재무수익 | D19: ='연결PL_IFRS18'!D21 -> 0 | E19: ='연결PL_IFRS18'!E21 -> 0
B20: 재무비용 | D20: ='연결PL_IFRS18'!D22 -> 98954951 | E20: ='연결PL_IFRS18'!E22 -> 45786340
B21: 재무손익 | D21: ='연결PL_IFRS18'!D23 -> -98954951 | E21: ='연결PL_IFRS18'!E23 -> -45786340
B22: 법인세비용차감전순이익(손실) | D22: ='연결PL_IFRS18'!D25 -> -862570612 | E22: ='연결PL_IFRS18'!E25 -> 1000830362
B23: 법인세비용 | D23: ='연결PL_IFRS18'!D26 -> 4983889 | E23: ='연결PL_IFRS18'!E26 -> 4894989
B24: 당기순이익(손실) | D24: ='연결PL_IFRS18'!D27 -> -867554501 | E24: ='연결PL_IFRS18'!E27 -> 995935373
B25: 1.지배기업소유주지분 | D25: =D24-D26 -> -867554501 | E25: =E24-E26 -> 995935373
B26: 2.비지배지분 | D26: =연결PL!D103 -> 0 | E26: =연결PL!E103 -> 0
B27: 기타포괄손익 | D27: ='연결PL_IFRS18'!D30 -> 11298394 | E27: ='연결PL_IFRS18'!E30 -> -26600734
B28: 당기손익으로 재분류되지 않는 항목 | D28: ='연결PL_IFRS18'!D28 -> 0 | E28: ='연결PL_IFRS18'!E28 -> 0
B29: 후속적으로 당기손익으로 재분류되는 항목 | D29: ='연결PL_IFRS18'!D29 -> 11298394 | E29: ='연결PL_IFRS18'!E29 -> -26600734
B30: 총포괄손익 | D30: =D24+D27 -> -856256107 | E30: =E24+E27 -> 969334639
B31: 1.지배기업소유주지분 | D31: =D30-D32 -> -856256107 | E31: =E30-E32 -> 969334639
B32: 2.비지배지분 | D32: =연결PL!D111 -> 0 | E32: =연결PL!E111 -> 0
B33: 주당이익
B34: 기본주당이익(손실) | D34: =연결PL!D113 -> -76 | E34: =연결PL!E113 -> 159
B35: 희석주당손익(손실) | D35: =연결PL!D114 -> -76 | E35: =연결PL!E114 -> 157
B37: [검증] 기존 손익계산서 대비 (0이어야 함)
B38: 당기순이익 - [연결PL] | D38: =D24-연결PL!D101 -> 0 | E38: =E24-연결PL!E101 -> 0
B39: 총포괄손익 - [연결PL] | D39: =D30-연결PL!D109 -> 0 | E39: =E30-연결PL!E109 -> 0
B40: 당기순이익 - [공시PL] | D40: =D24-공시PL!F16 -> 0
B41: 종합 검증 | D41: =IF(SUMPRODUCT(ABS(D38:E40))=0,"OK","확인필요") -> OK

Sheet 연결BS
B1: 계정과목 | C1: 주석 | D1: =A0!E7 -> 46203 | E1: 46022
B2: 자산
B3: 유동자산 | D3: =D4+D6+D7+D14+D25+D34+D31 -> 19569724244 | E3: 26088866610
B4: 현금및현금성자산 | D4: =D5 -> 11853592219 | E4: 19371699448
B5: 현금및현금성자산 | D5: =SUMIF(BS!$Y:$Y,연결BS!B5,BS!$X:$X) -> 11853592219 | E5: 19371699448
B6: 단기금융상품 | D6: =SUMIF(BS!$Y:$Y,연결BS!B6,BS!$X:$X) -> 1000000000 | E6: 0
B7: 매출채권및기타채권 | D7: =SUM(D8:D13) -> 1542306044 | E7: 1742211093
B8: 매출채권 | D8: =SUMIF(BS!$Y:$Y,연결BS!B8,BS!$X:$X) -> 1093289891 | E8: 1667334063
B9: 매출채권대손충당금 | D9: =SUMIF(BS!$Y:$Y,연결BS!B9,BS!$X:$X) -> -79701518 | E9: -163007230
B10: 미수수익 | D10: =SUMIF(BS!$Y:$Y,연결BS!B10,BS!$X:$X) -> 8344109 | E10: 0
B11: 미수수익대손충당금 | D11: =SUMIF(BS!$Y:$Y,연결BS!B11,BS!$X:$X) -> 0 | E11: 0
B12: 미수금 | D12: =SUMIF(BS!$Y:$Y,연결BS!B12,BS!$X:$X) -> 544512562 | E12: 265023260
B13: 미수금대손충당금 | D13: =SUMIF(BS!$Y:$Y,연결BS!B13,BS!$X:$X) -> -24139000 | E13: -27139000
B14: 재고자산 | D14: =SUM(D15:D24) -> 2306724877 | E14: 2120729597
B15: 상품 | D15: =SUMIF(BS!$Y:$Y,연결BS!B15,BS!$X:$X) -> 113083377 | E15: 111295016
B16: 상품평가충당금 | D16: =SUMIF(BS!$Y:$Y,연결BS!B16,BS!$X:$X) -> 0 | E16: -14089
B17: 제품 | D17: =SUMIF(BS!$Y:$Y,연결BS!B17,BS!$X:$X) -> 2573602294 | E17: 2367206763
B18: 제품평가충당금 | D18: =SUMIF(BS!$Y:$Y,연결BS!B18,BS!$X:$X) -> -827921741 | E18: -725171962
B19: 원재료 | D19: =SUMIF(BS!$Y:$Y,연결BS!B19,BS!$X:$X) -> 487254381 | E19: 354984836
B20: 원재료평가충당금 | D20: =SUMIF(BS!$Y:$Y,연결BS!B20,BS!$X:$X) -> -67100184 | E20: -34479470
B21: 부재료 | D21: =SUMIF(BS!$Y:$Y,연결BS!B21,BS!$X:$X) -> 48405072 | E21: 49267189
B22: 부재료평가충당금 | D22: =SUMIF(BS!$Y:$Y,연결BS!B22,BS!$X:$X) -> -20598322 | E22: -2358686
B23: 재공품 | D23: =SUMIF(BS!$Y:$Y,연결BS!B23,BS!$X:$X) -> 1451631047 | E23: 0
B24: 재공품평가충당금 | D24: =SUMIF(BS!$Y:$Y,연결BS!B24,BS!$X:$X) -> -1451631047 | E24: 0
B25: 기타유동자산 | D25: =SUM(D26:D30) -> 2793009371 | E25: 2780553225
B26: 선급금 | D26: =SUMIF(BS!$Y:$Y,연결BS!B26,BS!$X:$X) -> 1238992451 | E26: 2298824241
B27: 선급금대손충당금 | D27: =SUMIF(BS!$Y:$Y,연결BS!B27,BS!$X:$X) -> -564300000 | E27: 0
B28: 선급비용 | D28: =SUMIF(BS!$Y:$Y,연결BS!B28,BS!$X:$X) -> 1698698289 | E28: 474036344
B29: 환불자산 | D29: =SUMIF(BS!$Y:$Y,연결BS!B29,BS!$X:$X) -> 4272227 | E29: 7692640
B30: 부가세대급금 | D30: =SUMIF(BS!$Y:$Y,연결BS!B30,BS!$X:$X) -> 415346404 | E30: 0
B31: 기타유동금융자산 | D31: =SUM(D32:D33) -> 58432567 | E31: 56059511
B32: 임차보증금(유동) | D32: =SUMIF(BS!$Y:$Y,연결BS!B32,BS!$X:$X) -> 58432567 | E32: 54809510
B33: 주 . 임.종단기채권 | D33: =SUMIF(BS!$Y:$Y,연결BS!B33,BS!$X:$X) -> 0 | E33: 1250001
B34: 당기법인세자산 | D34: =SUMIF(BS!$Y:$Y,연결BS!B34,BS!$X:$X) -> 15659166 | E34: 17613736
B35: 비유동자산 | D35: =D36+D40+D43+D62+D73+D39+D71 -> 47987765603 | E35: 29206530706
B36: 기타비유동금융자산 | D36: =SUM(D37:D38) -> 715041595 | E36: 388220275
B37: 임차보증금 | D37: =SUMIF(BS!$Y:$Y,연결BS!B37,BS!$X:$X) -> 696916809 | E37: 378196105
B38: 기타보증금 | D38: =SUMIF(BS!$Y:$Y,연결BS!B38,BS!$X:$X) -> 18124786 | E38: 10024170
B39: 당기손익-공정가치금융자산 | D39: =SUMIF(BS!$Y:$Y,연결BS!B39,BS!$X:$X) -> 172664940 | E39: 172664940
B40: 종속기업및관계기업투자 | D40: =SUM(D41:D42) -> 0 | E40: 16999999500
B41: 종속기업투자 | D41: =SUMIF(BS!$Y:$Y,연결BS!B41,BS!$X:$X) -> 0 | E41: 0
B42: 관계기업투자 | D42: =SUMIF(BS!$Y:$Y,연결BS!B42,BS!$X:$X) -> 0 | E42: 16999999500
B43: 유형자산 | D43: =SUM(D44:D61) -> 10878025531 | E43: 9040172270
B44: 토지 | D44: =SUMIF(BS!$Y:$Y,연결BS!B44,BS!$X:$X) -> 1115280040 | E44: 557640020
B45: 건물 | D45: =SUMIF(BS!$Y:$Y,연결BS!B45,BS!$X:$X) -> 2832428420 | E45: 1355889942
B46: 건물감가상각누계액 | D46: =SUMIF(BS!$Y:$Y,연결BS!B46,BS!$X:$X) -> -61959374 | E46: -31072481
B47: 기계장치 | D47: =SUMIF(BS!$Y:$Y,연결BS!B47,BS!$X:$X) -> 4880028475 | E47: 1819453967
B48: 기계감가상각누계액 | D48: =SUMIF(BS!$Y:$Y,연결BS!B48,BS!$X:$X) -> -2996965212 | E48: -1210652849
B49: 차량운반구 | D49: =SUMIF(BS!$Y:$Y,연결BS!B49,BS!$X:$X) -> 7974819 | E49: 7974819
B50: 차량감가상각누계액 | D50: =SUMIF(BS!$Y:$Y,연결BS!B50,BS!$X:$X) -> -7972819 | E50: -7972819
B51: 공구와기구 | D51: =SUMIF(BS!$Y:$Y,연결BS!B51,BS!$X:$X) -> 131100000 | E51: 131100000
B52: 공구와기구감가상각누계액 | D52: =SUMIF(BS!$Y:$Y,연결BS!B52,BS!$X:$X) -> -67838194 | E52: -58155206
B53: 집기비품 | D53: =SUMIF(BS!$Y:$Y,연결BS!B53,BS!$X:$X) -> 1535040545 | E53: 614672405
B54: 집기비품감가상각누계액 | D54: =SUMIF(BS!$Y:$Y,연결BS!B54,BS!$X:$X) -> -1221588823 | E54: -434308698
B55: 인테리어 | D55: =SUMIF(BS!$Y:$Y,연결BS!B55,BS!$X:$X) -> 550941423 | E55: 611253322
... B61: 사용권자산상각누계액 | D61: =SUMIF(BS!$Y:$Y,연결BS!B61,BS!$X:$X) -> -2530675437 | E61: -458528774
B62: 무형자산 | D62: =SUM(D63:D70) -> 33200055369 | E62: 50368750
B63: 특허권 | D63: =SUMIF(BS!$Y:$Y,연결BS!B63,BS!$X:$X) -> 4712779068 | E63: 18182933
B64: 상표권 | D64: =SUMIF(BS!$Y:$Y,연결BS!B64,BS!$X:$X) -> 407963698 | E64: 19838530
B65: 영업권 | D65: =SUMIF(BS!$Y:$Y,연결BS!B65,BS!$X:$X) -> 16195983360 | E65: 0
B66: 개발비 | D66: =SUMIF(BS!$Y:$Y,연결BS!B66,BS!$X:$X) -> 5628405039 | E66: 0
B67: 소프트웨어 | D67: =SUMIF(BS!$Y:$Y,연결BS!B67,BS!$X:$X) -> 73116784 | E67: 12347287
B68: 시설이용권 | D68: =SUMIF(BS!$Y:$Y,연결BS!B68,BS!$X:$X) -> 46357920 | E68: 0
B69: 기타의무형자산 | D69: =SUMIF(BS!$Y:$Y,연결BS!B69,BS!$X:$X) -> 6097155442 | E69: 0
B70: 건설중인자산(무형) | D70: =SUMIF(BS!$Y:$Y,연결BS!B70,BS!$X:$X) -> 38294058 | E70: 0
B71: 기타비유동자산 | D71: =D72 -> 466873197 | E71: 0
B72: 장기선급비용 | D72: =SUMIF(BS!$Y:$Y,연결BS!B72,BS!$X:$X) -> 466873197 | E72: 0
B73: 이연법인세자산 | D73: =SUMIF(BS!$Y:$Y,연결BS!B73,BS!$X:$X) -> 2555104971 | E73: 2555104971
B74: 자산총계 | D74: =D35+D3 -> 67557489847 | E74: 55295397316
B75: 부채
B76: 유동부채 | D76: =D77+D83+D84+D86+D85+D82 -> 16544730603 | E76: 6018209801
B77: 매입채무및기타채무 | D77: =SUM(D78:D81) -> 7487585981 | E77: 1700812758
B78: 매입채무 | D78: =SUMIF(BS!$Y:$Y,연결BS!B78,BS!$X:$X) -> 299168927 | E78: 564384003
B79: 미지급금 | D79: =SUMIF(BS!$Y:$Y,연결BS!B79,BS!$X:$X) -> 4343550080 | E79: 293535909
B80: 예수금 | D80: =SUMIF(BS!$Y:$Y,연결BS!B80,BS!$X:$X) -> 85200680 | E80: 0
B81: 미지급비용 | D81: =SUMIF(BS!$Y:$Y,연결BS!B81,BS!$X:$X) -> 2759666294 | E81: 842892846
B82: 당기법인세부채 | D82: =SUMIF(BS!$Y:$Y,연결BS!B82,BS!$X:$X) -> 0 | E82: 0
B83: 단기차입금 | D83: =SUMIF(BS!$Y:$Y,연결BS!B83,BS!$X:$X) -> 1120000000 | E83: 1120000000
B84: 유동성장기차입금 | D84: =SUMIF(BS!$Y:$Y,연결BS!B84,BS!$X:$X) -> 0 | E84: 83300000
B85: 유동성리스부채 | D85: =SUMIF(BS!$Y:$Y,연결BS!B85,BS!$X:$X) -> 899145465 | E85: 545986082
B86: 기타유동부채 | D86: =SUM(D87:D88) -> 7037999157 | E86: 2568110961
B87: 선수금 | D87: =SUMIF(BS!$Y:$Y,연결BS!B87,BS!$X:$X) -> 7028604154 | E87: 2550767839
B88: 환불부채 | D88: =SUMIF(BS!$Y:$Y,연결BS!B88,BS!$X:$X) -> 9395003 | E88: 17343122
B89: 비유동부채 | D89: =D96+D90+D98+D92+D93+D91+D94 -> 9391764405 | E89: 6917922634
B90: 장기차입금 | D90: =SUMIF(BS!$Y:$Y,연결BS!B90,BS!$X:$X) -> 4100000000 | E90: 4100000000
B91: 장기미지급금 | D91: =SUMIF(BS!$Y:$Y,연결BS!B91,BS!$X:$X) -> 299694899 | E91: 0
B92: 리스부채 | D92: =SUMIF(BS!$Y:$Y,연결BS!B92,BS!$X:$X) -> 1535260103 | E92: 1049272823
B93: 이연법인세부채 | D93: =SUMIF(BS!$Y:$Y,연결BS!B93,BS!$X:$X) -> 2462964628 | E93: 8355551
B94: 충당부채 | D94: =D95 -> 77758201 | E94: 0
B95: 복구충당부채 | D95: =SUMIF(BS!$Y:$Y,연결BS!B95,BS!$X:$X) -> 77758201 | E95: 0
B96: 기타비유동부채 | D96: =D97 -> 205709924 | E96: 173088026
B97: 장기종업원급여부채 | D97: =SUMIF(BS!$Y:$Y,연결BS!B97,BS!$X:$X) -> 205709924 | E97: 173088026
B98: 순확정급여부채 | D98: =SUM(D99:D100) -> 710376650 | E98: 1587206234
B99: 퇴직급여충당부채 | D99: =SUMIF(BS!$Y:$Y,연결BS!B99,BS!$X:$X) -> 710376650 | E99: 1587206234
B100: 퇴직연금운용자산 | D100: =SUMIF(BS!$Y:$Y,연결BS!B100,BS!$X:$X) -> 0 | E100: 0
B101: 부채총계 | D101: =D89+D76 -> 25936495008 | E101: 12936132435
B102: 자본
B103: 지배기업의 소유주에게 귀속되는 자본 | D103: =SUM(D104,D106,D109,D112) -> 41503008774 | E103: =SUM(E104,E106,E109,E112) -> 42359264881
B104: 자본금 | D104: =D105 -> 5691191500 | E104: 5691191500
B105: 보통주자본금 | D105: =SUMIF(BS!$Y:$Y,연결BS!B105,BS!$X:$X) -> 5691191500 | E105: 5691191500
...

Sheet CF정산표
B1: =+A0!E5 -> 주식회사 울트라브이와 그 종속기업 | F1: <주석 시트 수식 연동
B2: 현 금 흐 름 정 산 표 | AB2: =CF정산표!AC11+CF정산표!H11-CF정산표!K11 -> -13318794
B3: =+A0!E7 -> 46203
B4: 과 목 | G4: 영 업 활 동 으 로 인 한 현 금 흐 름 | P4: 투 자 활 동 으 로 인 한 현 금 흐 름 | V4: 재 무 활 동 으 로 인 한 현 금 흐 름 | AB4: 대 체 거 래
D5: 전 기 말 | E5: 당 기 말 | F5: 증감액 | G5: 현금의 유입이 없는 수익등 | J5: 현금의 유출이 없는 비용등 | M5: 영업활동으로인한 자산·부채의 변동 | P5: 차 변 (현 금 의 유 출) | S5: 대 변 (현 금 의 유 입) | V5: 차 변 (현 금 의 유 출) | Y5: 대 변 (현 금 의 유 입) | AB5: 차 변 | AE5: 대 변 | AH5: 차 이
D6: 금 액 | E6: 금 액 | G6: 내 역 | H6: 금 액 | J6: 내 역 | K6: 금 액 | M6: 내 역 | N6: 금 액 | P6: 내 역 | Q6: 금 액 | S6: 내 역 | T6: 금 액 | V6: 내 역 | W6: 금 액 | Y6: 내 역 | Z6: 금 액 | AB6: 내 역 | AC6: 금 액 | AE6: 내 역 | AF6: 금 액
D7: =연결BS!E3-D8 -> 0 | E7: =E8-연결BS!D3 -> 0
B8: Ⅰ. | C8: 유동자산 | D8: =+D10+D13+D18+D37+D52+D30 -> 26088866610 | E8: =+E10+E13+E18+E37+E52+E30 -> 19569724244
C10: =연결BS!B5 -> 현금및현금성자산 | D10: =SUM(D11) -> 19371699448 | E10: =SUM(E11) -> 11853592219
A11: =AH11 -> 0 | C11: =연결BS!B5 -> 현금및현금성자산 | D11: =연결BS!E5 -> 19371699448 | E11: =연결BS!D5 -> 11853592219 | F11: =E11-D11 -> -7518107229 | G11: 외화환산이익 | H11: 5 | J11: 외화환산손실 | K11: 0 | M11: =C11&"의 증가(감소)" -> 현금및현금성자산의 증가(감소) | N11: =D11-E11+H11-K11+Q11-T11+W11-Z11+SUM(AC11:AC12)-AF11 -> 7504788435 | P11: 연결범위변동 | Q11: =-AC12 -> -677182600 | AB11: 해외사업장환산차대 | AC11: =환율변동효과!D16+환율변동효과!D17+환율변동효과!D18 -> -13318799 | AH11: =D11-E11+H11-K11-N11+Q11-T11+W11-Z11+SUM(AC11:AC12)-AF11 -> 0
A12: =AH12 -> 0 | AB12: 연결범위변동(에이티지씨) | AC12: =BS!N8 -> 677182600
A13: =AH13 -> 0 | C13: 단기금융상품 | D13: =SUM(D14) -> 0 | E13: =SUM(E14:E14) -> 1000000000
A14: =AH14 -> 0 | C14: =연결BS!B6 -> 단기금융상품 | D14: =연결BS!E6 -> 0 | E14: =연결BS!D6 -> 1000000000 | F14: =E14-D14 -> 1000000000 | G14: 단기금융상품평가이익 | H14: 0 | J14: 단기금융상품평가손실 | P14: 단기금융상품의 취득 | Q14: 0 | S14: 단기금융상품 처분 | AB14: 연결범위변동(에이티지씨) | AC14: 1000000000 | AH14: =D14-E14+SUM(H14:I17)-SUM(K14:K17)-N14+Q14-T14+W14-Z14+AC14-AF14 -> 0
A15: =AH15 -> 0 | G15: 단기금융상품처분이익 | H15: 0 | J15: 단기금융상품처분손실 | K15: 0
G16: 이자수익 | H16: 0 | J16: 외화환산손실 | K16: 0
A18: =AH18 -> 0 | C18: =연결BS!B7 -> 매출채권및기타채권 | D18: =SUM(D19:D29) -> 1742211093 | E18: =SUM(E19:E29) -> 1542306044
A19: =AH19 -> 0 | C19: =연결BS!B8 -> 매출채권 | D19: =연결BS!E8 -> 1667334063 | E19: =연결BS!D8 -> 1093289891 | F19: =E19-D19 -> -574044172 | G19: 외화환산이익 | H19: 37603834 | J19: 외화환산손실 | K19: 0 | M19: =C19&"의 감소(증가)" -> 매출채권의 감소(증가) | N19: =SUM(D19:D20)-SUM(E19:E20)+SUM(H19:H20)-SUM(K19:K20)+Q19-T19+W19-Z19+SUM(AC19:AC20)-SUM(AF19:AF20) -> 502587042 | AB19: 해외사업장환산차대 | AC19: =환율변동효과!D20+환율변동효과!D21 -> -109060964 | AE19: 매출채권 제각 | AF19: =AC20 -> 0 | AH19: =SUM(D19:D20)-SUM(E19:E20)+SUM(H19:H20)-SUM(K19:K20)-N19+Q19-T19+W19-Z19+SUM(AC19:AC20)-SUM(AF19:AF20) -> 0
A20: =AH20 -> 0 | C20: =연결BS!B9 -> 매출채권대손충당금 | D20: =연결BS!E9 -> -163007230 | E20: =연결BS!D9 -> -79701518 | F20: =E20-D20 -> 83305712 | J20: 대손상각비 | K20: ='8'!D76 -> -83305712 | AB20: 매출채권 제각 | AC20: =-'8'!E76 -> 0
A21: =AH21 -> 0 | C21: =연결BS!B10 -> 미수수익 | D21: =연결BS!E10 -> 0 | E21: =연결BS!D10 -> 8344109 | F21: =E21-D21 -> 8344109 | G21: 이자수익 | H21: =PL!Y97-H83 -> 14072249 | M21: 미수수익의 감소(증가) | N21: 14072249 | AB21: 해외사업장환산차대 | AC21: =환율변동효과!D22 -> 0 | AH21: =SUM(D21:D21)-SUM(E21:E21)+SUM(H21:H21)-SUM(K21:K21)-N21+Q21-T21+W21-Z21+SUM(AC21:AC22)-SUM(AF21:AF21) -> 0
AB22: 연결범위변동(에이티지씨) | AC22: 8344109
A23: =AH23 -> 0 | C23: =연결BS!B11 -> 미수수익대손충당금 | D23: =연결BS!E11 -> 0 | E23: =연결BS!D11 -> 0 | F23: =E23-D23 -> 0 | AB23: 해외사업장환산차대 | AC23: =환율변동효과!D23 -> 0 | AH23: =SUM(D23:D23)-SUM(E23:E23)+SUM(H23:H23)-SUM(K23:K23)-N23+Q23-T23+W23-Z23+SUM(AC23:AC23)-SUM(AF23:AF23) -> 0
A24: =AH24 -> 0 | C24: =연결BS!B12 -> 미수금 | D24: =연결BS!E12 -> 265023260 | E24: =연결BS!D12 -> 544512562 | F24: =E24-D24 -> 279489302 | G24: 외화환산이익 | J24: 외화환산손실 | M24: =C24&"의 감소(증가)" -> 미수금의 감소(증가) | N24: 4005688 | AB24: 연결범위변동(에이티지씨) | AC24: 283494990 | AE24: 팜합병 | AF24: 0 | AH24: =SUM(D24:D25)-SUM(E24:E25)+SUM(H24:H25)-SUM(K24:K25)-N24+Q24-T24+W24-Z24+SUM(AC24:AC25)-SUM(AF24:AF25) -> 0
A25: =AH25 -> 0 | C25: =연결BS!B13 -> 미수금대손충당금 | D25: =연결BS!E13 -> -27139000 | E25: =연결BS!D13 -> -24139000 | F25: =E25-D25 -> 3000000 | G25: 이자수익 | J25: 기타의 대손상각비(환입) | K25: ='8'!D77 -> -3000000 | AB25: 리스 미수금 | AC25: =환율변동효과!D25 -> 0
G26: 외화환산이익
A30: =AH30 -> 0 | C30: =연결BS!B14 -> 재고자산 | D30: =연결BS!E14 -> 2120729597 | E30: =연결BS!D14 -> 2306724877 | M30: 재고자산의 감소(증가) | N30: =SUM(D30:D34)-SUM(E30:E34)+SUM(H30:H34)-SUM(K30:K34)+Q30-T30+W30-Z30+AC30-SUM(AF30:AF33) -> -326232101 | AB30: 해외사업장환산차대 | AC30: =SUM(환율변동효과!D33:D41) -> -9043647 | AH30: =D30-E30+SUM(H30:H34)-SUM(K30:K34)-SUM(N30:N34)+SUM(Q30:Q34)-SUM(T30:T34)+SUM(W30:W34)-SUM(Z30:Z34)+SUM(AC30:AC35)-SUM(AF30:AF35) -> 0
A31: =AH31 -> 0 | G31: 상품평가손실환입 | H31: 14089 | J31: 상품평가손실 | K31: 0 | AB31: 연결범위변동(에이티지씨) | AC31: 0
G32: 제품평가손실환입 | H32: 0 | J32: 제품평가손실 | K32: 102749779
G33: 원재료평가손실환입 | H33: 0 | J33: 원재료평가손실 | K33: 10217848
G34: 부재료평가손실환입 | H34: 0 | J34: 부재료평가손실 | K34: 18239636
A35: =AH35 -> 0
A37: =AH37 -> 0 | C37: =연결BS!B25 -> 기타유동자산 | D37: =SUM(D38:D51) -> 2836612736 | E37: =SUM(E38:E51) -> 2851441938
A38: =AH38 -> 0 | C38: =연결BS!B26 -> 선급금 | D38: =연결BS!E26 -> 2298824241 | E38: =연결BS!D26 -> 1238992451 | F38: =E38-D38 -> -1059831790 | M38: =C38&"의 감소(증가)" -> 선급금의 감소(증가) | N38: =D38-E38+H38-K38+Q38-T38+W38-Z38+SUM(AC38:AC40)-SUM(AF38:AF39) -> 1650893458 | AB38: 해외사업장환산차대 | AC38: =ROUND(환율변동효과!D26,)+3.72529029846191E-09 -> -238332 | AH38: =D38-E38+SUM(H38:I39)-SUM(K38:K39)-SUM(N38:O39)+SUM(Q38:Q39)-SUM(T38:T39)+SUM(W38:W39)-SUM(Z38:Z39)+SUM(AC38:AC40)-SUM(AF38:AF39) -> 0
AB39: 기계장치 반품 | AC39: 27000000
AB40: 연결범위변동(에이티지씨) | AC40: 564300000
C41: =연결BS!B27 -> 선급금대손충당금 | D41: =연결BS!E27 -> 0 | E41: =연결BS!D27 -> -564300000 | F41: =E41-D41 -> -564300000 | J41: 기타의 대손상각비(환입) | K41: 0 | AB41: 해외사업장환산차대 | AC41: =환율변동효과!D27 -> 0 | AH41: =D41-E41+H41-K41-N41+Q41-T41+W41-Z41+SUM(AC41:AC42)-SUM(AF41) -> 0
AB42: 연결범위변동(에이티지씨) | AC42: -564300000
A43: =AH43 -> 0 | C43: =연결BS!B33 -> 주 . 임.종단기채권 | D43: =연결BS!E33 -> 1250001 | E43: =연결BS!D33 -> 0 | F43: =E43-D43 -> -1250001 | P43: 주 . 임.종단기채권의 증가 | Q43: 0 | S43: 주 . 임.종단기채권의 감소 | T43: 1250001 | AB43: 해외사업장환산차대 | AC43: 0 | AH43: =D43-E43+H43-K43-N43+Q43-T43+W43-Z43+SUM(AC43:AC44)-AF43 -> 0
AB44: 연결범위변동(에이티지씨) | AC44: 0
A45: =AH45 -> 0 | C45: =연결BS!B28 -> 선급비용 | D45: =연결BS!E28 -> 474036344 | E45: =연결BS!D28 -> 1698698289 | F45: =E45-D45 -> 1224661945 | M45: =C45&"의 감소(증가)" -> 선급비용의 감소(증가) | N45: =D45-E45+H45-K45+Q45-T45+W45-Z45+AC45-SUM(AF45:AF46) -> -1224661945 | AB45: 해외사업장환산차대 | AC45: 0 | AH45: =D45-E45+H45-K45-N45+Q45-T45+W45-Z45+AC45-AF45 -> 0
A46: =AH46 -> 0 | C46: =연결BS!B29 -> 환불자산 | D46: =연결BS!E29 -> 7692640 | E46: =연결BS!D29 -> 4272227 | F46: =E46-D46 -> -3420413 | M46: =C46&"의 감소(증가)" -> 환불자산의 감소(증가) | N46: =SUM(D46:D47)-SUM(E46:E47)+SUM(H46:H47)-SUM(K46:K47)+Q46-T46+W46-Z46+SUM(AC46:AC47)-SUM(AF46:AF47) -> 3420413 | AB46: 현할차설정 | AH46: =SUM(D46:D47)-SUM(E46:E47)+SUM(H46:H47)-SUM(K46:K47)-N46+Q46-T46+W46-Z46+SUM(AC46:AC47)-SUM(AF46:AF47) -> 0
AB47: 해외사업장환산차대 | AC47: =환율변동효과!D28 -> 0
A49: =AH49 -> 0 | C49: =연결BS!B32 -> 임차보증금(유동) | D49: =연결BS!E32 -> 54809510 | E49: =연결BS!D32 -> 58432567 | F49: =E49-D49 -> 3623057 | P49: 임차보증금의 증가 | Q49: 0 | S49: 임차보증금의 감소 | T49: 0 | AB49: 유동성대체 | AC49: =SUM(AF83:AF86)-AC86 -> 0 | AH49: =SUM(D49:D50)-SUM(E49:E50)+SUM(H49:H50)-SUM(K49:K50)-N49+Q49-T49+W49-Z49+SUM(AC49:AC50)-SUM(AF49:AF50) -> 0
A50: =AH50 -> 0 | AB50: 해외사업장환산차대 | AC50: 3623057
A51: =AH51 -> 0 | C51: =연결BS!B30 -> 부가세대급금 | D51: =연결BS!E30 -> 0 | E51: =연결BS!D30 -> 415346404 | F51: =E51-D51 -> 415346404 | M51: =C51&"의 감소(증가)" -> 부가세대급금의 감소(증가) | N51: =D51-E51+H51-K51+Q51-T51+W51-Z51+AC51-SUM(AF51:AF52) -> 0 | AB51: 연결범위변동(에이티지씨) | AC51: 415346404 | AH51: =D51-E51+H51-K51-N51+Q51-T51+W51-Z51+AC51-AF51 -> 0
A52: =AH52 -> 0 | C52: =연결BS!B34 -> 당기법인세자산 | D52: =D53 -> 17613736 | E52: =E53 -> 15659166
A53: =AH53 -> 0 | C53: =연결BS!B34 -> 당기법인세자산 | D53: =연결BS!E34 -> 17613736 | E53: =연결BS!D34 -> 15659166 | J53: 법인세비용 | K53: =PL!Y112 -> 4983889 | M53: 법인세의 납부1 | N53: =D53-E53+H53-K53+Q53-T53+W53-Z53+AC53+AC54+AC55-AF53 -> -1204167 | AB53: 해외사업장환산차대 | AC53: =환율변동효과!D31 -> -785278 | AH53: {=D53-E53+H53-K53-N53+Q53-T53+W53-Z53+SUM(AC53:AC55-AF53)} -> 0
AB54: 연결범위변동(에이티지씨) | AC54: 2610430
AB55: 보험수리적손익 법인세효과 | AC55: 0
A58: =AH58 -> 0 | D58: =D59=연결BS!E35 -> TRUE | E58: =E59-연결BS!D35 -> 0
A59: =AH59 -> 0 | B59: Ⅱ | C59: 비유동자산 | D59: =D61+D65+D68+D77+D82+D90+D88 -> 29206530706 | E59: =E61+E65+E68+E77+E82+E90+E88 -> 47987765603
A60: =AH60 -> 0
A61: =AH61 -> 0 | C61: =연결BS!B39 -> 당기손익-공정가치금융자산 | D61: =D62 -> 172664940 | E61: =E62 -> 172664940
A62: =AH62 -> 0 | C62: =연결BS!B39 -> 당기손익-공정가치금융자산 | D62: =연결BS!E39 -> 172664940 | E62: =연결BS!D39 -> 172664940 | F62: =E62-D62 -> 0 | G62: 당기손익공정가치측정금융자산평가이익 | H62: 0 | J62: 당기손익공정가치측정금융자산평가손실 | K62: 0 | P62: 당기손익공정가치측정금융자산의 취득 | Q62: 0 | S62: 당기손익공정가치측정금융자산의 처분 | T62: 0 | AB62: FVPL대체 | AC62: =AF65 -> 0 | AH62: =D62-E62+SUM(H62:H63)-SUM(K62:K63)-N62+Q62-T62+W62-Z62+AC62-AF62-AF63 -> 0
A63: =AH63 -> 0
A64: =AH64 -> 0
A65: =AH65 -> 0 | C65: =연결BS!B40 -> 종속기업및관계기업투자 | D65: =연결BS!E40 -> 16999999500 | E65: =연결BS!D40 -> 0 | G65: 지분법손실 | H65: -2067945777 | J65: 관계기업투자주식처분이익 | K65: =-연결PL!D75 -> -2067945777 | P65: 연결범위변동 | Q65: =지분법계산_에이티지씨!C45 -> 8000000000 | AB65: 해외사업장환산차대 | AC65: 0 | AE65: FVPL대체 | AH65: =D65-E65+H65-K65-N65+Q65-T65+W65-Z65+SUM(AC65:AC66)-AF65 -> 0
A66: =AH66 -> 0 | AB66: 연결범위변동(에이티지씨) | AC66: =-RIC!I71 -> -24999999500
A67: =AH67 -> 0
A68: =AH68 -> 0 | C68: =연결BS!B43 -> 유형자산 | D68: =연결BS!E43 -> 9040172270 | E68: =연결BS!D43 -> 10878025531 | F68: =E68-D68 -> 1837853261 | AH68: =D68-E68+SUM(H68:H76)-SUM(K68:K76)-SUM(N68:N76)+SUM(Q68:Q76)-SUM(T68:T76)+W68-Z68+SUM(AC68:AC76)-SUM(AF68:AF76) -> 0
A69: =AH69 -> 0 | G69: 유형자산처분이익 | H69: =PL!Y84 -> 1202135 | J69: 유형자산처분손실 | K69: =PL!Y88 -> 4825402 | P69: 유형자산의 취득 | Q69: ='12'!D33-'12'!D31 -> 940715535 | S69: 유형자산의 처분 | T69: =-('12'!E33-'12'!E31)+연결PL!D74-연결PL!D81-AF71 -> 452135 | AB69: 해외사업장환산차대 | AC69: ='12'!I33 -> 21436385 | AE69: 유형자산 취득 미지급금 | AF69: 0
A70: =AH70 -> 0 | J70: 유형자산손상차손 | K70: 0 | AB70: 사용권자산 신규 | AC70: ='12'!D31 -> 9012918 | AE70: 사용권자산 종료 | AF70: 18218466
A71: =AH71 -> 0 | J71: 감가상각비 | K71: =-'12'!G33 -> 585661920 | AB71: 차입원가자본화 | AC71: 25031561 | AE71: 기계장치 반품 | AF71: =AC39+AC99 -> 90000000
A72: =AH72 -> 0 | AB72: 연결범위변동(에이티지씨) | AC72: =SUM('12'!H136:H146) -> 1539612650
A73: =AH73 -> 0
A74: =AH74 -> 0
A75: =AH75 -> 0
A76: =AH76 -> 0
A77: =AH77 -> 0 | C77: =연결BS!B62 -> 무형자산 | D77: =연결BS!E62 -> 50368750 | E77: =연결BS!D62 -> 33200055369 | F77: =E77-D77 -> 33149686619 | AH77: =D77-E77+SUM(H77:H81)-SUM(K77:K81)-SUM(N77:N81)+SUM(Q77:Q81)-SUM(T77:T81)+SUM(W77:W81)-SUM(Z77:Z81)+SUM(AC77:AC81)-SUM(AF77:AF81) -> 0
J78: 무형자산상각비 | K78: =-'13'!F27 -> 21529107 | P78: 무형자산의 취득 | Q78: ='13'!D27 -> 95882479 | S78: 무형자산의 처분 | AB78: 해외사업장환산차대 | AC78: =SUM(환율변동효과!D58:D62) -> 0
AB79: 연결범위변동(에이티지씨) | AC79: =RIC!F76+RIC!F77+RIC!F78+RIC!F79+BS!N68 -> 33075333247
A82: =AH82 -> 0 | C82: =연결BS!B36 -> 기타비유동금융자산 | D82: =SUM(D83:D87) -> 388220275 | E82: =SUM(E83:E87) -> 715041595
A83: =AH83 -> 0 | C83: =연결BS!B37 -> 임차보증금 | D83: =연결BS!E37 -> 378196105 | E83: =연결BS!D37 -> 696916809 | F83: =E83-D83 -> 318720704 | G83: 이자수익 | H83: 8029205 | P83: 임차보증금의 증가 | Q83: 6000000 | S83: 임차보증금의 감소 | T83: 15978000 | AB83: 해외사업장환산차대 | AC83: 0 | AE83: 유동성대체 | AF83: 0 | AH83: =SUM(D83:D83)-SUM(E83:E83)+SUM(H83:H83)-SUM(K83:K83)-N83+Q83-T83+W83-Z83+SUM(AC83:AC85)-SUM(AF83:AF83) -> 0
AB84: 연결범위변동(에이티지씨) | AC84: =400000000-79029697 -> 320970303
AB85: 사용권자산 신규/처분 | AC85: -300804
A86: =AH86 -> 0 | C86: =연결BS!B38 -> 기타보증금 | D86: =연결BS!E38 -> 10024170 | E86: =연결BS!D38 -> 18124786 | F86: =E86-D86 -> 8100616 | P86: 기타보증금의 증가 | Q86: 640000 | S86: 기타보증금의 감소 | T86: 528300 | AB86: 계정대체 | AH86: =SUM(D86:D86)-SUM(E86:E86)+SUM(H86:H86)-SUM(K86:K86)-N86+Q86-T86+W86-Z86+SUM(AC86:AC87)-SUM(AF86:AF86) -> 0
AB87: 연결범위변동(에이티지씨) | AC87: 7988916
A88: =AH88 -> 0 | C88: =연결BS!B72 -> 장기선급비용 | D88: =연결BS!E72 -> 0 | E88: =연결BS!D72 -> 466873197 | AB88: 연결범위변동(에이티지씨) | AC88: 466873197 | AH88: =SUM(D88:D88)-SUM(E88:E88)+SUM(H88:H88)-SUM(K88:K88)-N88+Q88-T88+W88-Z88+SUM(AC88:AC88)-SUM(AF88:AF88) -> 0
A90: =AH90 -> 0 | C90: =연결BS!B73 -> 이연법인세자산 | D90: =연결BS!E73 -> 2555104971 | E90: =연결BS!D73 -> 2555104971 | J90: 법인세비용 | M90: 법인세의 납부2 | N90: =D90-E90+H90-K90+Q90-T90+W90-Z90+AC90-AF90+AC91 -> 0 | AB90: 해외사업장환산차대 | AC90: =환율변동효과!D65 -> 0 | AH90: =D90-E90+H90-K90-N90+Q90-T90+W90-Z90+AC90-AF90+AC91 -> 0
A91: =AH91 -> 0
A92: =AH92 -> 0
A93: =AH93 -> 0 | B93: 자산총계 | D93: =D59+D8 -> 55295397316 | E93: =E59+E8 -> 67557489847
A94: =AH94 -> 0 | D94: =D93=연결BS!E74 -> TRUE | E94: =E93=연결BS!D74 -> TRUE
A95: =AH95 -> 0 | B95: Ⅰ. | C95: 유동부채 | D95: =D97+D107+D110+D120+D125 -> 6018209801 | E95: =E97+E107+E110+E120+E125 -> 16544730603
A96: =AH96 -> 0 | D96: =D95=연결BS!E76 -> TRUE | E96: =E95=연결BS!D76 -> TRUE
A97: =AH97 -> 0 | C97: =연결BS!B77 -> 매입채무및기타채무 | D97: =SUM(D98:D106) -> 1700812758 | E97: =SUM(E98:E106) -> 7487585981
A98: =AH98 -> 0 | C98: =연결BS!B78 -> 매입채무 | D98: =연결BS!E78 -> 564384003 | E98: =연결BS!D78 -> 299168927 | F98: =E98-D98 -> -265215076 | G98: 외화환산이익 | H98: 0 | J98: 외화환산손실 | K98: 2 | M98: =C98&"의 증가(감소)" -> 매입채무의 증가(감소) | N98: =-(D98-E98)+H98-K98+Q98-T98+W98-Z98+AC98-AF98 -> 116569589 | AE98: 해외사업장환산차대 | AF98: =환율변동효과!D68-251926863 -> -381784667 | AH98: =-(D98-E98)+H98-K98-N98+Q98-T98+W98-Z98+AC98-AF98 -> 0 | AJ98: 환율변동효과 탭에서는 내부거래제거 전 효과를 산출함. 차이나는 금액은 대부분 별도(매출채권)<->홍콩(매입채무)간의 채권채무 상계시 발생하는 것으로 판단되므로, 차이금액을 매입채무 환율변동효과에서 수기조정
A99: =AH99 -> 0 | C99: =연결BS!B79 -> 미지급금 | D99: =연결BS!E79 -> 293535909 | E99: =연결BS!D79 -> 4343550080 | F99: =E99-D99 -> 4050014171 | G99: 외화환산이익 | H99: 0 | J99: 외화환산손실 | M99: =C99&"의 증가(감소)" -> 미지급금의 증가(감소) | N99: =-(D99-E99)+H99-SUM(K99:L99)+Q99-T99+W99-Z99+SUM(AC99:AC100)-AF99 -> -22895999 | AB99: =AE71 -> 기계장치 반품 | AC99: 63000000 | AE99: 해외사업장환산차대 | AF99: =환율변동효과!D69 -> 0 | AH99: =-(D99-E99)+H99-SUM(K99:K100)-N99+Q99-T99+W99-Z99+SUM(AC99:AC100)-SUM(AF99:AG99) -> 0
AB100: 연결범위변동(에이티지씨) | AC100: =-BS!N92 -> -4135910170
A101: =AH101 -> 0 | C101: =연결BS!B81 -> 미지급비용 | D101: =연결BS!E81-D102 -> 840331711 | E101: =연결BS!D81-E102 -> 2752017725 | F101: =E101-D101 -> 1911686014 | M101: =C101&"의 증가(감소)" -> 미지급비용의 증가(감소) | N101: =-(D101-E101)+H101-K101+Q101-T101+W101-Z101+AC101-AF101 -> 1772577408 | AB101: 연결범위변동(에이티지씨) | AC101: =-BS!N98 -> -143171601 | AE101: 해외사업장환산차대 | AF101: =환율변동효과!D75 -> -4062995 | AH101: =-(D101-E101)+H101-SUM(K101)-N101+Q101-T101+W101-Z101+AC101-AF101 -> 0
A102: =AH102 -> 0 | C102: 미지급이자 | D102: 2561135 | E102: 7648569 | F102: =E102-D102 -> 5087434 | J102: 이자비용 | K102: =연결PL!D91-K136 -> 71893278 | M102: 이자의 지급 | N102: =-(D102-E102)+H102-K102+Q102-T102+W102-Z102+AC102-AF102 -> -91837405 | AE102: 차입원가자본화 | AF102: =AC71 -> 25031561 | AH102: =-(D102-E102)+H102-K102-N102+Q102-T102+W102-Z102+AC102-AF102 -> 0
A104: =AH104 -> 0 | C104: =연결BS!B80 -> 예수금 | D104: =연결BS!E80 -> 0 | E104: =연결BS!D80 -> 85200680 | F104: =E104-D104 -> 85200680 | M104: =C104&"의 증가(감소)" -> 예수금의 증가(감소) | N104: =-(D104-E104)+H104-K104+Q104-T104+W104-Z104+AC104-AF104 -> 85200680 | AE104: 해외사업장환산차대 | AF104: =환율변동효과!D70 -> 0 | AH104: =-(D104-E104)+H104-K104-N104+Q104-T104+W104-Z104+AC104-AF104 -> 0
A106: =AH106 -> 0
A107: =AH107 -> 0 | D107: =SUM(D108) -> 0 | E107: =SUM(E108) -> 0
A108: =AH108 -> 0 | C108: 당기법인세부채 | D108: =연결BS!E82 -> 0 | E108: =연결BS!D82 -> 0 | F108: =E108-D108 -> 0 | J108: 법인세비용 | K108: =-K149-K90 -> 0 | M108: 법인세의 납부2 | N108: =-(D108-E108)+H108-K108+Q108-T108+W108-Z108+AC108-AF108 -> 0 | AE108: 해외사업장환산차대 | AF108: =환율변동효과!D76 -> 0 | AH108: =-(D108-E108)+H108-K108-N108+Q108-T108+W108-Z108+AC108-AF108 -> 0
A110: =AH110 -> 0 | C110: =연결BS!B86 -> 기타유동부채 | D110: =SUM(D111:D116) -> 2568110961 | E110: =SUM(E111:E116) -> 7037999157
A111: =AH111 -> 0 | C111: =연결BS!B87 -> 선수금 | D111: =연결BS!E87 -> 2550767839 | E111: =연결BS!D87 -> 7028604154 | F111: =E111-D111 -> 4477836315 | M111: =C111&"의 증가(감소)" -> 선수금의 증가(감소) | N111: =-(D111-E111)+H111-K111+Q111-T111+W111-Z111+AC111-AF111 -> -265408405 | AB111: 연결범위변동(에이티지씨) | AC111: =-BS!N95 -> -4747430895 | AE111: 해외사업장환산차대 | AF111: =환율변동효과!D72 -> -4186175 | AH111: =-(D111-E111)+H111-K111-N111+Q111-T111+W111-Z111+AC111-AF111 -> 0
A112: =AH112 -> 0 | C112: =연결BS!B88 -> 환불부채 | D112: =연결BS!E88 -> 17343122 | E112: =연결BS!D88 -> 9395003 | F112: =E112-D112 -> -7948119 | J112: 환불부채 | K112: -7948119 | M112: =C112&"의 증가(감소)" -> 환불부채의 증가(감소) | N112: =-(D112-E112)+H112-K112+Q112-T112+W112-Z112+AC112-AF112 -> 0 | AE112: 해외사업장환산차대 | AF112: =환율변동효과!D73 -> 0 | AH112: =-(D112-E112)+H112-K112-N112+Q112-T112+W112-Z112+AC112-AF112 -> 0
A120: =AH120 -> 0 | C120: =연결BS!B85 -> 유동성리스부채 | D120: =SUM(D121:D124) -> 545986082 | E120: =SUM(E121:E124) -> 899145465
A121: =AH121 -> 0 | C121: =연결BS!B85 -> 유동성리스부채 | D121: =연결BS!E85 -> 545986082 | E121: =연결BS!D85 -> 899145465 | F121: =E121-D121 -> 353159383 | V121: 리스부채의 상환 | W121: =-'19'!C185-W136 -> 0 | AB121: 연결범위변동(에이티지씨) | AC121: =-BS!N102 -> -362078348 | AE121: 해외사업장환산차대 | AF121: ='19'!C187 -> 0 | AH121: =-(D121-E121)+H121-K121-N121+Q121-T121+W121-Z121+SUM(AC121:AC122)-SUM(AF121:AF123) -> 0
AB122: 리스중단 | AC122: 15273120 | AE122: 리스부채 유동성대체 | AF122: 0
...

Sheet BS
A1: Level | B1: 계정과목명(Account) | G1: Code | H1: 울트라브이 | I1: 울트라브이팜 | J1: ULTRA V HONG KONG LIMITED | K1: DERMASTER HONG KONG LIMITED | L1: ULTRA V SHANGHAI LIMITED | M1: ULTRA V (SG) PTE.LTD (24년 설립) | N1: ATGC | O1: 단순합산 | P1: 투자자본상계 | R1: IFRS(투자자본상계) | S1: 내부거래상계 | U1: IFRS(내부거래상계) | V1: 연결조정 | X1: 연결IFRS | Y1: 공시용mapping
P2: 차변 | Q2: 대변 | S2: 차변 | T2: 대변 | V2: 차변 | W2: 대변
A4: 1 | B4: 자산 | H4: =H5+H39 -> 54543045905 | I4: =I5+I39 -> 0 | J4: =J5+J39 -> 2268065089 | K4: =K5+K39 -> 358233996 | L4: =L5+L39 -> 2287111 | M4: =M5+M39 -> 22492142 | N4: =N5+N39 -> 10738913487 | O4: =O5+O39 -> 67933037730 | R4: =R5+R39 -> 71425319191 | U4: =U5+U39 -> 69331585038 | X4: =X5+X39 -> 67557489847
A5: 2 | C5: 유동자산 | H5: =H6+H24+H36 -> 16937363250 | I5: =I6+I24+I36 -> 0 | J5: =J6+J24+J36 -> 2042118015 | K5: =K6+K24+K36 -> 66475063 | L5: =L6+L24+L36 -> 2287111 | M5: =M6+M24+M36 -> 22492142 | N5: =N6+N24+N36 -> 2658778533 | O5: =O6+O24+O36 -> 21729514114 | R5: =R6+R24+R36 -> 21729514114 | U5: =U6+U24+U36 -> 19637356152 | X5: =X6+X24+X36 -> 19569724244
A6: 3 | D6: 당좌자산 | H6: =SUM(H7:H23) -> 14734753629 | I6: =SUM(I7:I23) -> 0 | J6: =SUM(J7:J23) -> 1882310421 | K6: =SUM(K7:K23) -> 26031396 | L6: =SUM(L7:L23) -> 2287111 | M6: =SUM(M7:M23) -> 22492142 | N6: =SUM(N7:N23) -> 2658778533 | O6: =SUM(O7:O23) -> 19326653232 | R6: =SUM(R7:R23) -> 19326653232 | U6: =SUM(U7:U23) -> 17315340360 | X6: =SUM(X7:X23) -> 17204566800
A7: 4 | E7: 현금 | G7: 10100 | H7: =SUMIF(별도정산표!$G:$G,BS!G7,별도정산표!$E:$E) -> 0 | I7: =SUMIF(울트라팜_FS!$A:$A,BS!G7,울트라팜_FS!$D:$D) -> 0 | J7: =SUMIF(HK_BS!$A:$A,BS!G7,HK_BS!$K:$K) -> 807554 | K7: =SUMIF(DHK_BS!$A:$A,BS!G7,DHK_BS!$K:$K) -> 0 | L7: =SUMIF(상해_BS!$A:$A,BS!G7,상해_BS!$K:$K) -> 0 | M7: =SUMIF(SG_BS!$A:$A,BS!G7,SG_BS!$K:$K) -> 0 | N7: =SUMIF(ATGC_BS!$H:$H,BS!G7,ATGC_BS!$I:$I) -> 0 | O7: =SUM(H7:N7) -> 807554 | P7: =SUMIF(RIC!D:D,BS!G7,RIC!F:F) -> 0 | Q7: =SUMIF(RIC!G:G,BS!G7,RIC!I:I) -> 0 | R7: =O7+P7-Q7 -> 807554 | S7: =SUMIF(RIT!H:H,BS!G7,RIT!J:J) -> 0 | T7: =SUMIF(RIT!K:K,BS!G7,RIT!M:M) -> 0 | U7: =R7+S7-T7 -> 807554 | V7: =SUMIF(지분법및기타!$D:$D,BS!G7,지분법및기타!$F:$F) -> 0 | W7: =SUMIF(지분법및기타!$G:$G,BS!G7,지분법및기타!$I:$I) -> 0 | X7: =U7+V7-W7 -> 807554 | Y7: 현금및현금성자산 | AA7: =X7-O7 -> 0
A8: 4 | E8: 보통예금 | G8: 10300 | H8: =SUMIF(별도정산표!$G:$G,BS!G8,별도정산표!$E:$E) -> 10968165061 | I8: =SUMIF(울트라팜_FS!$A:$A,BS!G8,울트라팜_FS!$D:$D) -> 0 | J8: =SUMIF(HK_BS!$A:$A,BS!G8,HK_BS!$K:$K) -> 160024453 | K8: =SUMIF(DHK_BS!$A:$A,BS!G8,DHK_BS!$K:$K) -> 24830657 | L8: =SUMIF(상해_BS!$A:$A,BS!G8,상해_BS!$K:$K) -> 0 | M8: =SUMIF(SG_BS!$A:$A,BS!G8,SG_BS!$K:$K) -> 14563594 | N8: =SUMIF(ATGC_BS!$H:$H,BS!G8,ATGC_BS!$I:$I) -> 677182600 | O8: =SUM(H8:N8) -> 11844766365 | P8: =SUMIF(RIC!D:D,BS!G8,RIC!F:F) -> 0 | Q8: =SUMIF(RIC!G:G,BS!G8,RIC!I:I) -> 0 | R8: =O8+P8-Q8 -> 11844766365 | S8: =SUMIF(RIT!H:H,BS!G8,RIT!J:J) -> 0 | T8: =SUMIF(RIT!K:K,BS!G8,RIT!M:M) -> 0 | U8: =R8+S8-T8 -> 11844766365 | V8: =SUMIF(지분법및기타!$D:$D,BS!G8,지분법및기타!$F:$F) -> 0 | W8: =SUMIF(지분법및기타!$G:$G,BS!G8,지분법및기타!$I:$I) -> 0 | X8: =U8+V8-W8 -> 11844766365 | Y8: 현금및현금성자산 | AA8: =X8-O8 -> 0
A9: 4 | E9: 외화보통예금 | G9: 10400 | H9: =SUMIF(별도정산표!$G:$G,BS!G9,별도정산표!$E:$E) -> 0 | I9: =SUMIF(울트라팜_FS!$A:$A,BS!G9,울트라팜_FS!$D:$D) -> 0 | J9: =SUMIF(HK_BS!$A:$A,BS!G9,HK_BS!$K:$K) -> 89752 | K9: =SUMIF(DHK_BS!$A:$A,BS!G9,DHK_BS!$K:$K) -> 0 | L9: =SUMIF(상해_BS!$A:$A,BS!G9,상해_BS!$K:$K) -> 0 | M9: =SUMIF(SG_BS!$A:$A,BS!G9,SG_BS!$K:$K) -> 7928548 | N9: =SUMIF(ATGC_BS!$H:$H,BS!G9,ATGC_BS!$I:$I) -> 0 | O9: =SUM(H9:N9) -> 8018300 | P9: =SUMIF(RIC!D:D,BS!G9,RIC!F:F) -> 0 | Q9: =SUMIF(RIC!G:G,BS!G9,RIC!I:I) -> 0 | R9: =O9+P9-Q9 -> 8018300 | S9: =SUMIF(RIT!H:H,BS!G9,RIT!J:J) -> 0 | T9: =SUMIF(RIT!K:K,BS!G9,RIT!M:M) -> 0 | U9: =R9+S9-T9 -> 8018300 | V9: =SUMIF(지분법및기타!$D:$D,BS!G9,지분법및기타!$F:$F) -> 0 | W9: =SUMIF(지분법및기타!$G:$G,BS!G9,지분법및기타!$I:$I) -> 0 | X9: =U9+V9-W9 -> 8018300 | Y9: 현금및현금성자산 | AA9: =X9-O9 -> 0
A10: 4 | E10: 기타단기금융상품 | G10: 10600 | H10: =SUMIF(별도정산표!$G:$G,BS!G10,별도정산표!$E:$E) -> 0 | I10: =SUMIF(울트라팜_FS!$A:$A,BS!G10,울트라팜_FS!$D:$D) -> 0 | J10: =SUMIF(HK_BS!$A:$A,BS!G10,HK_BS!$K:$K) -> 0 | K10: =SUMIF(DHK_BS!$A:$A,BS!G10,DHK_BS!$K:$K) -> 0 | L10: =SUMIF(상해_BS!$A:$A,BS!G10,상해_BS!$K:$K) -> 0 | M10: =SUMIF(SG_BS!$A:$A,BS!G10,SG_BS!$K:$K) -> 0 | N10: =SUMIF(ATGC_BS!$H:$H,BS!G10,ATGC_BS!$I:$I) -> 1000000000 | O10: =SUM(H10:N10) -> 1000000000 | P10: =SUMIF(RIC!D:D,BS!G10,RIC!F:F) -> 0 | Q10: =SUMIF(RIC!G:G,BS!G10,RIC!I:I) -> 0 | R10: =O10+P10-Q10 -> 1000000000 | S10: =SUMIF(RIT!H:H,BS!G10,RIT!J:J) -> 0 | T10: =SUMIF(RIT!K:K,BS!G10,RIT!M:M) -> 0 | U10: =R10+S10-T10 -> 1000000000 | V10: =SUMIF(지분법및기타!$D:$D,BS!G10,지분법및기타!$F:$F) -> 0 | W10: =SUMIF(지분법및기타!$G:$G,BS!G10,지분법및기타!$I:$I) -> 0 | X10: =U10+V10-W10 -> 1000000000 | Y10: 단기금융상품
A11: 4 | E11: 외상매출금 | G11: 10800 | H11: =SUMIF(별도정산표!$G:$G,BS!G11,별도정산표!$E:$E) -> 1535770100 | I11: =SUMIF(울트라팜_FS!$A:$A,BS!G11,울트라팜_FS!$D:$D) -> 0 | J11: =SUMIF(HK_BS!$A:$A,BS!G11,HK_BS!$K:$K) -> 1710243241 | K11: =SUMIF(DHK_BS!$A:$A,BS!G11,DHK_BS!$K:$K) -> 0 | L11: =SUMIF(상해_BS!$A:$A,BS!G11,상해_BS!$K:$K) -> 0 | M11: =SUMIF(SG_BS!$A:$A,BS!G11,SG_BS!$K:$K) -> 0 | N11: =SUMIF(ATGC_BS!$H:$H,BS!G11,ATGC_BS!$I:$I) -> 0 | O11: =SUM(H11:N11) -> 3246013341 | P11: =SUMIF(RIC!D:D,BS!G11,RIC!F:F) -> 0 | Q11: =SUMIF(RIC!G:G,BS!G11,RIC!I:I) -> 0 | R11: =O11+P11-Q11 -> 3246013341 | S11: =SUMIF(RIT!H:H,BS!G11,RIT!J:J) -> 0 | T11: =SUMIF(RIT!K:K,BS!G11,RIT!M:M) -> 2036954016 | U11: =R11+S11-T11 -> 1209059325 | V11: =SUMIF(지분법및기타!$D:$D,BS!G11,지분법및기타!$F:$F) -> 42605437 | W11: =SUMIF(지분법및기타!$G:$G,BS!G11,지분법및기타!$I:$I) -> 158374871 | X11: =U11+V11-W11 -> 1093289891 | Y11: 매출채권 | AA11: =X11-O11 -> -2152723450 | AB11: 전액 내부거래 차이
A12: 4 | E12: 외상매출금_대손충당금 | G12: 10900 | H12: =SUMIF(별도정산표!$G:$G,BS!G12,별도정산표!$E:$E) -> -105342662 | I12: =SUMIF(울트라팜_FS!$A:$A,BS!G12,울트라팜_FS!$D:$D) -> 0 | J12: =SUMIF(HK_BS!$A:$A,BS!G12,HK_BS!$K:$K) -> 0 | K12: =SUMIF(DHK_BS!$A:$A,BS!G12,DHK_BS!$K:$K) -> 0 | L12: =SUMIF(상해_BS!$A:$A,BS!G12,상해_BS!$K:$K) -> 0 | M12: =SUMIF(SG_BS!$A:$A,BS!G12,SG_BS!$K:$K) -> 0 | N12: =SUMIF(ATGC_BS!$H:$H,BS!G12,ATGC_BS!$I:$I) -> 0 | O12: =SUM(H12:N12) -> -105342662 | P12: =SUMIF(RIC!D:D,BS!G12,RIC!F:F) -> 0 | Q12: =SUMIF(RIC!G:G,BS!G12,RIC!I:I) -> 0 | R12: =O12+P12-Q12 -> -105342662 | S12: =SUMIF(RIT!H:H,BS!G12,RIT!J:J) -> 25641144 | T12: =SUMIF(RIT!K:K,BS!G12,RIT!M:M) -> 0 | U12: =R12+S12-T12 -> -79701518 | V12: =SUMIF(지분법및기타!$D:$D,BS!G12,지분법및기타!$F:$F) -> 0 | W12: =SUMIF(지분법및기타!$G:$G,BS!G12,지분법및기타!$I:$I) -> 0 | X12: =U12+V12-W12 -> -79701518 | Y12: 매출채권대손충당금 | AA12: =X12-O12 -> 25641144 | AB12: 전액 내부거래 차이
A13: 4 | E13: 미수수익 | G13: 11600 | H13: =SUMIF(별도정산표!$G:$G,BS!G13,별도정산표!$E:$E) -> 0 | I13: =SUMIF(울트라팜_FS!$A:$A,BS!G13,울트라팜_FS!$D:$D) -> 0 | J13: =SUMIF(HK_BS!$A:$A,BS!G13,HK_BS!$K:$K) -> 0 | K13: =SUMIF(DHK_BS!$A:$A,BS!G13,DHK_BS!$K:$K) -> 0 | L13: =SUMIF(상해_BS!$A:$A,BS!G13,상해_BS!$K:$K) -> 0 | M13: =SUMIF(SG_BS!$A:$A,BS!G13,SG_BS!$K:$K) -> 0 | N13: =SUMIF(ATGC_BS!$H:$H,BS!G13,ATGC_BS!$I:$I) -> 8344109 | O13: =SUM(H13:N13) -> 8344109 | P13: =SUMIF(RIC!D:D,BS!G13,RIC!F:F) -> 0 | Q13: =SUMIF(RIC!G:G,BS!G13,RIC!I:I) -> 0 | R13: =O13+P13-Q13 -> 8344109 | S13: =SUMIF(RIT!H:H,BS!G13,RIT!J:J) -> 0 | T13: =SUMIF(RIT!K:K,BS!G13,RIT!M:M) -> 0 | U13: =R13+S13-T13 -> 8344109 | V13: =SUMIF(지분법및기타!$D:$D,BS!G13,지분법및기타!$F:$F) -> 0 | W13: =SUMIF(지분법및기타!$G:$G,BS!G13,지분법및기타!$I:$I) -> 0 | X13: =U13+V13-W13 -> 8344109 | Y13: 미수수익
E14: 미수수익_대손충당금 | G14: 11700 | H14: =SUMIF(별도정산표!$G:$G,BS!G14,별도정산표!$E:$E) -> 0 | I14: =SUMIF(울트라팜_FS!$A:$A,BS!G14,울트라팜_FS!$D:$D) -> 0 | J14: =SUMIF(HK_BS!$A:$A,BS!G14,HK_BS!$K:$K) -> 0 | K14: =SUMIF(DHK_BS!$A:$A,BS!G14,DHK_BS!$K:$K) -> 0 | L14: =SUMIF(상해_BS!$A:$A,BS!G14,상해_BS!$K:$K) -> 0 | M14: =SUMIF(SG_BS!$A:$A,BS!G14,SG_BS!$K:$K) -> 0 | N14: =SUMIF(ATGC_BS!$H:$H,BS!G14,ATGC_BS!$I:$I) -> 0 | O14: =SUM(H14:N14) -> 0 | P14: =SUMIF(RIC!D:D,BS!G14,RIC!F:F) -> 0 | Q14: =SUMIF(RIC!G:G,BS!G14,RIC!I:I) -> 0 | R14: =O14+P14-Q14 -> 0 | S14: =SUMIF(RIT!H:H,BS!G14,RIT!J:J) -> 0 | T14: =SUMIF(RIT!K:K,BS!G14,RIT!M:M) -> 0 | U14: =R14+S14-T14 -> 0 | V14: =SUMIF(지분법및기타!$D:$D,BS!G14,지분법및기타!$F:$F) -> 0 | W14: =SUMIF(지분법및기타!$G:$G,BS!G14,지분법및기타!$I:$I) -> 0 | X14: =U14+V14-W14 -> 0 | Y14: 미수수익대손충당금
E15: 미수금 | G15: 12000 | H15: =SUMIF(별도정산표!$G:$G,BS!G15,별도정산표!$E:$E) -> 261017572 | I15: =SUMIF(울트라팜_FS!$A:$A,BS!G15,울트라팜_FS!$D:$D) -> 0 | J15: =SUMIF(HK_BS!$A:$A,BS!G15,HK_BS!$K:$K) -> 0 | K15: =SUMIF(DHK_BS!$A:$A,BS!G15,DHK_BS!$K:$K) -> 0 | L15: =SUMIF(상해_BS!$A:$A,BS!G15,상해_BS!$K:$K) -> 0 | M15: =SUMIF(SG_BS!$A:$A,BS!G15,SG_BS!$K:$K) -> 0 | N15: =SUMIF(ATGC_BS!$H:$H,BS!G15,ATGC_BS!$I:$I) -> 283494990 | O15: =SUM(H15:N15) -> 544512562 | P15: =SUMIF(RIC!D:D,BS!G15,RIC!F:F) -> 0 | Q15: =SUMIF(RIC!G:G,BS!G15,RIC!I:I) -> 0 | R15: =O15+P15-Q15 -> 544512562 | S15: =SUMIF(RIT!H:H,BS!G15,RIT!J:J) -> 0 | T15: =SUMIF(RIT!K:K,BS!G15,RIT!M:M) -> 0 | U15: =R15+S15-T15 -> 544512562 | V15: =SUMIF(지분법및기타!$D:$D,BS!G15,지분법및기타!$F:$F) -> 0 | W15: =SUMIF(지분법및기타!$G:$G,BS!G15,지분법및기타!$I:$I) -> 0 | X15: =U15+V15-W15 -> 544512562 | Y15: 미수금 | AA15: =X15-O15 -> 0
A16: 4 | E16: 미수금_대손충당금 | G16: 12100 | H16: =SUMIF(별도정산표!$G:$G,BS!G16,별도정산표!$E:$E) -> -24139000 | I16: =SUMIF(울트라팜_FS!$A:$A,BS!G16,울트라팜_FS!$D:$D) -> 0 | J16: =SUMIF(HK_BS!$A:$A,BS!G16,HK_BS!$K:$K) -> 0 | K16: =SUMIF(DHK_BS!$A:$A,BS!G16,DHK_BS!$K:$K) -> 0 | L16: =SUMIF(상해_BS!$A:$A,BS!G16,상해_BS!$K:$K) -> 0 | M16: =SUMIF(SG_BS!$A:$A,BS!G16,SG_BS!$K:$K) -> 0 | N16: =SUMIF(ATGC_BS!$H:$H,BS!G16,ATGC_BS!$I:$I) -> 0 | O16: =SUM(H16:N16) -> -24139000 | P16: =SUMIF(RIC!D:D,BS!G16,RIC!F:F) -> 0 | Q16: =SUMIF(RIC!G:G,BS!G16,RIC!I:I) -> 0 | R16: =O16+P16-Q16 -> -24139000 | S16: =SUMIF(RIT!H:H,BS!G16,RIT!J:J) -> 0 | T16: =SUMIF(RIT!K:K,BS!G16,RIT!M:M) -> 0 | U16: =R16+S16-T16 -> -24139000 | V16: =SUMIF(지분법및기타!$D:$D,BS!G16,지분법및기타!$F:$F) -> 0 | W16: =SUMIF(지분법및기타!$G:$G,BS!G16,지분법및기타!$I:$I) -> 0 | X16: =U16+V16-W16 -> -24139000 | Y16: 미수금대손충당금 | AA16: =X16-O16 -> 0
A17: 4 | E17: 선급금 | G17: 13100 | H17: =SUMIF(별도정산표!$G:$G,BS!G17,별도정산표!$E:$E) -> 394157762 | I17: =SUMIF(울트라팜_FS!$A:$A,BS!G17,울트라팜_FS!$D:$D) -> 0 | J17: =SUMIF(HK_BS!$A:$A,BS!G17,HK_BS!$K:$K) -> 2538076 | K17: =SUMIF(DHK_BS!$A:$A,BS!G17,DHK_BS!$K:$K) -> 1200739 | L17: =SUMIF(상해_BS!$A:$A,BS!G17,상해_BS!$K:$K) -> 0 | M17: =SUMIF(SG_BS!$A:$A,BS!G17,SG_BS!$K:$K) -> 0 | N17: =SUMIF(ATGC_BS!$H:$H,BS!G17,ATGC_BS!$I:$I) -> 836100000 | O17: =SUM(H17:N17) -> 1233996577 | P17: =SUMIF(RIC!D:D,BS!G17,RIC!F:F) -> 0 | Q17: =SUMIF(RIC!G:G,BS!G17,RIC!I:I) -> 0 | R17: =O17+P17-Q17 -> 1233996577 | S17: =SUMIF(RIT!H:H,BS!G17,RIT!J:J) -> 0 | T17: =SUMIF(RIT!K:K,BS!G17,RIT!M:M) -> 0 | U17: =R17+S17-T17 -> 1233996577 | V17: =SUMIF(지분법및기타!$D:$D,BS!G17,지분법및기타!$F:$F) -> 0 | W17: =SUMIF(지분법및기타!$G:$G,BS!G17,지분법및기타!$I:$I) -> -4995874 | X17: =U17+V17-W17 -> 1238992451 | Y17: 선급금 | AA17: =X17-O17 -> 4995874
A18: 4 | E18: 선급금_대손충당금 | G18: 13200 | H18: =SUMIF(별도정산표!$G:$G,BS!G18,별도정산표!$E:$E) -> 0 | I18: =SUMIF(울트라팜_FS!$A:$A,BS!G18,울트라팜_FS!$D:$D) -> 0 | J18: =SUMIF(HK_BS!$A:$A,BS!G18,HK_BS!$K:$K) -> 0 | K18: =SUMIF(DHK_BS!$A:$A,BS!G18,DHK_BS!$K:$K) -> 0 | L18: =SUMIF(상해_BS!$A:$A,BS!G18,상해_BS!$K:$K) -> 0 | M18: =SUMIF(SG_BS!$A:$A,BS!G18,SG_BS!$K:$K) -> 0 | N18: =SUMIF(ATGC_BS!$H:$H,BS!G18,ATGC_BS!$I:$I) -> -564300000 | O18: =SUM(H18:N18) -> -564300000 | P18: =SUMIF(RIC!D:D,BS!G18,RIC!F:F) -> 0 | Q18: =SUMIF(RIC!G:G,BS!G18,RIC!I:I) -> 0 | R18: =O18+P18-Q18 -> -564300000 | S18: =SUMIF(RIT!H:H,BS!G18,RIT!J:J) -> 0 | T18: =SUMIF(RIT!K:K,BS!G18,RIT!M:M) -> 0 | U18: =R18+S18-T18 -> -564300000 | V18: =SUMIF(지분법및기타!$D:$D,BS!G18,지분법및기타!$F:$F) -> 0 | W18: =SUMIF(지분법및기타!$G:$G,BS!G18,지분법및기타!$I:$I) -> 0 | X18: =U18+V18-W18 -> -564300000 | Y18: 선급금대손충당금
A19: 4 | E19: 선급비용 | G19: 13300 | H19: =SUMIF(별도정산표!$G:$G,BS!G19,별도정산표!$E:$E) -> 1698698289 | I19: =SUMIF(울트라팜_FS!$A:$A,BS!G19,울트라팜_FS!$D:$D) -> 0 | J19: =SUMIF(HK_BS!$A:$A,BS!G19,HK_BS!$K:$K) -> 0 | K19: =SUMIF(DHK_BS!$A:$A,BS!G19,DHK_BS!$K:$K) -> 0 | L19: =SUMIF(상해_BS!$A:$A,BS!G19,상해_BS!$K:$K) -> 0 | M19: =SUMIF(SG_BS!$A:$A,BS!G19,SG_BS!$K:$K) -> 0 | N19: =SUMIF(ATGC_BS!$H:$H,BS!G19,ATGC_BS!$I:$I) -> 0 | O19: =SUM(H19:N19) -> 1698698289 | P19: =SUMIF(RIC!D:D,BS!G19,RIC!F:F) -> 0 | Q19: =SUMIF(RIC!G:G,BS!G19,RIC!I:I) -> 0 | R19: =O19+P19-Q19 -> 1698698289 | S19: =SUMIF(RIT!H:H,BS!G19,RIT!J:J) -> 0 | T19: =SUMIF(RIT!K:K,BS!G19,RIT!M:M) -> 0 | U19: =R19+S19-T19 -> 1698698289 | V19: =SUMIF(지분법및기타!$D:$D,BS!G19,지분법및기타!$F:$F) -> 0 | W19: =SUMIF(지분법및기타!$G:$G,BS!G19,지분법및기타!$I:$I) -> 0 | X19: =U19+V19-W19 -> 1698698289 | Y19: 선급비용 | AA19: =X19-O19 -> 0
A20: 4 | E20: 주임종단기채권 | G20: 13400 | H20: =SUMIF(별도정산표!$G:$G,BS!G20,별도정산표!$E:$E) -> 0 | I20: =SUMIF(울트라팜_FS!$A:$A,BS!G20,울트라팜_FS!$D:$D) -> 0 | J20: =SUMIF(HK_BS!$A:$A,BS!G20,HK_BS!$K:$K) -> 0 | K20: =SUMIF(DHK_BS!$A:$A,BS!G20,DHK_BS!$K:$K) -> 0 | L20: =SUMIF(상해_BS!$A:$A,BS!G20,상해_BS!$K:$K) -> 0 | M20: =SUMIF(SG_BS!$A:$A,BS!G20,SG_BS!$K:$K) -> 0 | N20: =SUMIF(ATGC_BS!$H:$H,BS!G20,ATGC_BS!$I:$I) -> 0 | O20: =SUM(H20:N20) -> 0 | P20: =SUMIF(RIC!D:D,BS!G20,RIC!F:F) -> 0 | Q20: =SUMIF(RIC!G:G,BS!G20,RIC!I:I) -> 0 | R20: =O20+P20-Q20 -> 0 | S20: =SUMIF(RIT!H:H,BS!G20,RIT!J:J) -> 0 | T20: =SUMIF(RIT!K:K,BS!G20,RIT!M:M) -> 0 | U20: =R20+S20-T20 -> 0 | V20: =SUMIF(지분법및기타!$D:$D,BS!G20,지분법및기타!$F:$F) -> 0 | W20: =SUMIF(지분법및기타!$G:$G,BS!G20,지분법및기타!$I:$I) -> 0 | X20: =U20+V20-W20 -> 0 | Y20: 주 . 임.종단기채권 | AA20: =X20-O20 -> 0
A21: 4 | E21: 부가세대급금 | G21: 13500 | H21: =SUMIF(별도정산표!$G:$G,BS!G21,별도정산표!$E:$E) -> 0 | I21: =SUMIF(울트라팜_FS!$A:$A,BS!G21,울트라팜_FS!$D:$D) -> 0 | J21: =SUMIF(HK_BS!$A:$A,BS!G21,HK_BS!$K:$K) -> 0 | K21: =SUMIF(DHK_BS!$A:$A,BS!G21,DHK_BS!$K:$K) -> 0 | L21: =SUMIF(상해_BS!$A:$A,BS!G21,상해_BS!$K:$K) -> 0 | M21: =SUMIF(SG_BS!$A:$A,BS!G21,SG_BS!$K:$K) -> 0 | N21: =SUMIF(ATGC_BS!$H:$H,BS!G21,ATGC_BS!$I:$I) -> 415346404 | O21: =SUM(H21:N21) -> 415346404 | P21: =SUMIF(RIC!D:D,BS!G21,RIC!F:F) -> 0 | Q21: =SUMIF(RIC!G:G,BS!G21,RIC!I:I) -> 0 | R21: =O21+P21-Q21 -> 415346404 | S21: =SUMIF(RIT!H:H,BS!G21,RIT!J:J) -> 0 | T21: =SUMIF(RIT!K:K,BS!G21,RIT!M:M) -> 0 | U21: =R21+S21-T21 -> 415346404 | V21: =SUMIF(지분법및기타!$D:$D,BS!G21,지분법및기타!$F:$F) -> 0 | W21: =SUMIF(지분법및기타!$G:$G,BS!G21,지분법및기타!$I:$I) -> 0 | X21: =U21+V21-W21 -> 415346404 | Y21: 부가세대급금
A22: 4 | E22: 선납법인세 | G22: 13600 | H22: =SUMIF(별도정산표!$G:$G,BS!G22,별도정산표!$E:$E) -> 2154280 | I22: =SUMIF(울트라팜_FS!$A:$A,BS!G22,울트라팜_FS!$D:$D) -> 0 | J22: =SUMIF(HK_BS!$A:$A,BS!G22,HK_BS!$K:$K) -> 8607345 | K22: =SUMIF(DHK_BS!$A:$A,BS!G22,DHK_BS!$K:$K) -> 0 | L22: =SUMIF(상해_BS!$A:$A,BS!G22,상해_BS!$K:$K) -> 2287111 | M22: =SUMIF(SG_BS!$A:$A,BS!G22,SG_BS!$K:$K) -> 0 | N22: =SUMIF(ATGC_BS!$H:$H,BS!G22,ATGC_BS!$I:$I) -> 2610430 | O22: =SUM(H22:N22) -> 15659166 | P22: =SUMIF(RIC!D:D,BS!G22,RIC!F:F) -> 0 | Q22: =SUMIF(RIC!G:G,BS!G22,RIC!I:I) -> 0 | R22: =O22+P22-Q22 -> 15659166 | S22: =SUMIF(RIT!H:H,BS!G22,RIT!J:J) -> 0 | T22: =SUMIF(RIT!K:K,BS!G22,RIT!M:M) -> 0 | U22: =R22+S22-T22 -> 15659166 | V22: =SUMIF(지분법및기타!$D:$D,BS!G22,지분법및기타!$F:$F) -> 0 | W22: =SUMIF(지분법및기타!$G:$G,BS!G22,지분법및기타!$I:$I) -> 0 | X22: =U22+V22-W22 -> 15659166 | Y22: 당기법인세자산 | AA22: =X22-O22 -> 0
A23: 4 | E23: 환불자산 | G23: 14000 | H23: =SUMIF(별도정산표!$G:$G,BS!G23,별도정산표!$E:$E) -> 4272227 | I23: =SUMIF(울트라팜_FS!$A:$A,BS!G23,울트라팜_FS!$D:$D) -> 0 | J23: =SUMIF(HK_BS!$A:$A,BS!G23,HK_BS!$K:$K) -> 0 | K23: =SUMIF(DHK_BS!$A:$A,BS!G23,DHK_BS!$K:$K) -> 0 | L23: =SUMIF(상해_BS!$A:$A,BS!G23,상해_BS!$K:$K) -> 0 | M23: =SUMIF(SG_BS!$A:$A,BS!G23,SG_BS!$K:$K) -> 0 | N23: =SUMIF(ATGC_BS!$H:$H,BS!G23,ATGC_BS!$I:$I) -> 0 | O23: =SUM(H23:N23) -> 4272227 | P23: =SUMIF(RIC!D:D,BS!G23,RIC!F:F) -> 0 | Q23: =SUMIF(RIC!G:G,BS!G23,RIC!I:I) -> 0 | R23: =O23+P23-Q23 -> 4272227 | S23: =SUMIF(RIT!H:H,BS!G23,RIT!J:J) -> 0 | T23: =SUMIF(RIT!K:K,BS!G23,RIT!M:M) -> 0 | U23: =R23+S23-T23 -> 4272227 | V23: =SUMIF(지분법및기타!$D:$D,BS!G23,지분법및기타!$F:$F) -> 0 | W23: =SUMIF(지분법및기타!$G:$G,BS!G23,지분법및기타!$I:$I) -> 0 | X23: =U23+V23-W23 -> 4272227 | Y23: 환불자산
A24: 3 | D24: 재고자산 | H24: =+SUM(H25:H35) -> 2202609621 | I24: =+SUM(I25:I35) -> 0 | J24: =+SUM(J25:J35) -> 141818694 | K24: =+SUM(K25:K35) -> 0 | L24: =+SUM(L25:L35) -> 0 | M24: =+SUM(M25:M35) -> 0 | N24: =+SUM(N25:N35) -> 0 | O24: =+SUM(O25:O35) -> 2344428315 | R24: =+SUM(R25:R35) -> 2344428315 | U24: =+SUM(U25:U35) -> 2263583225 | V24: =SUMIF(지분법및기타!$D:$D,BS!G24,지분법및기타!$F:$F) -> 0 | W24: =SUMIF(지분법및기타!$G:$G,BS!G24,지분법및기타!$I:$I) -> 0 | X24: =+SUM(X25:X35) -> 2306724877
A25: 4 | E25: 상품 | G25: 14600 | H25: =SUMIF(별도정산표!$G:$G,BS!G25,별도정산표!$E:$E) -> 47852743 | I25: =SUMIF(울트라팜_FS!$A:$A,BS!G25,울트라팜_FS!$D:$D) -> 0 | J25: =SUMIF(HK_BS!$A:$A,BS!G25,HK_BS!$K:$K) -> 141818694 | K25: =SUMIF(DHK_BS!$A:$A,BS!G25,DHK_BS!$K:$K) -> 0 | L25: =SUMIF(상해_BS!$A:$A,BS!G25,상해_BS!$K:$K) -> 0 | M25: =SUMIF(SG_BS!$A:$A,BS!G25,SG_BS!$K:$K) -> 0 | N25: =SUMIF(ATGC_BS!$H:$H,BS!G25,ATGC_BS!$I:$I) -> 0 | O25: =SUM(H25:N25) -> 189671437 | P25: =SUMIF(RIC!D:D,BS!G25,RIC!F:F) -> 0 | Q25: =SUMIF(RIC!G:G,BS!G25,RIC!I:I) -> 0 | R25: =O25+P25-Q25 -> 189671437 | S25: =SUMIF(RIT!H:H,BS!G25,RIT!J:J) -> 1749501 | T25: =SUMIF(RIT!K:K,BS!G25,RIT!M:M) -> 141818694 | U25: =R25+S25-T25 -> 49602244 | V25: =SUMIF(지분법및기타!$D:$D,BS!G25,지분법및기타!$F:$F) -> 115769431 | W25: =SUMIF(지분법및기타!$G:$G,BS!G25,지분법및기타!$I:$I) -> 52288298 | X25: =U25+V25-W25 -> 113083377 | Y25: 상품 | AA25: =X25-O25 -> -76588060 | AB25: 전액 내부거래 차이
E26: 상품재고자산평가충당금 | G26: 16000 | H26: =SUMIF(별도정산표!$G:$G,BS!G26,별도정산표!$E:$E) -> 0 | I26: =SUMIF(울트라팜_FS!$A:$A,BS!G26,울트라팜_FS!$D:$D) -> 0 | J26: =SUMIF(HK_BS!$A:$A,BS!G26,HK_BS!$K:$K) -> 0 | K26: =SUMIF(DHK_BS!$A:$A,BS!G26,DHK_BS!$K:$K) -> 0 | L26: =SUMIF(상해_BS!$A:$A,BS!G26,상해_BS!$K:$K) -> 0 | M26: =SUMIF(SG_BS!$A:$A,BS!G26,SG_BS!$K:$K) -> 0 | N26: =SUMIF(ATGC_BS!$H:$H,BS!G26,ATGC_BS!$I:$I) -> 0 | O26: =SUM(H26:N26) -> 0 | P26: =SUMIF(RIC!D:D,BS!G26,RIC!F:F) -> 0 | Q26: =SUMIF(RIC!G:G,BS!G26,RIC!I:I) -> 0 | R26: =O26+P26-Q26 -> 0 | S26: =SUMIF(RIT!H:H,BS!G26,RIT!J:J) -> 0 | T26: =SUMIF(RIT!K:K,BS!G26,RIT!M:M) -> 0 | U26: =R26+S26-T26 -> 0 | V26: =SUMIF(지분법및기타!$D:$D,BS!G26,지분법및기타!$F:$F) -> 0 | W26: =SUMIF(지분법및기타!$G:$G,BS!G26,지분법및기타!$I:$I) -> 0 | X26: =U26+V26-W26 -> 0 | Y26: 상품평가충당금
A27: 4 | E27: 제품 | G27: 14700 | H27: =SUMIF(별도정산표!$G:$G,BS!G27,별도정산표!$E:$E) -> 2534717672 | I27: =SUMIF(울트라팜_FS!$A:$A,BS!G27,울트라팜_FS!$D:$D) -> 0 | J27: =SUMIF(HK_BS!$A:$A,BS!G27,HK_BS!$K:$K) -> 0 | K27: =SUMIF(DHK_BS!$A:$A,BS!G27,DHK_BS!$K:$K) -> 0 | L27: =SUMIF(상해_BS!$A:$A,BS!G27,상해_BS!$K:$K) -> 0 | M27: =SUMIF(SG_BS!$A:$A,BS!G27,SG_BS!$K:$K) -> 0 | N27: =SUMIF(ATGC_BS!$H:$H,BS!G27,ATGC_BS!$I:$I) -> 0 | O27: =SUM(H27:N27) -> 2534717672 | P27: =SUMIF(RIC!D:D,BS!G27,RIC!F:F) -> 0 | Q27: =SUMIF(RIC!G:G,BS!G27,RIC!I:I) -> 0 | R27: =O27+P27-Q27 -> 2534717672 | S27: =SUMIF(RIT!H:H,BS!G27,RIT!J:J) -> 59224103 | T27: =SUMIF(RIT!K:K,BS!G27,RIT!M:M) -> 0 | U27: =R27+S27-T27 -> 2593941775 | V27: =SUMIF(지분법및기타!$D:$D,BS!G27,지분법및기타!$F:$F) -> 98161994 | W27: =SUMIF(지분법및기타!$G:$G,BS!G27,지분법및기타!$I:$I) -> 118501475 | X27: =U27+V27-W27 -> 2573602294 | Y27: 제품 | AA27: =X27-O27 -> 38884622 | AB27: 전액 내부거래 차이
E28: 제품재고자산평가충당금 | G28: 16100 | H28: =SUMIF(별도정산표!$G:$G,BS!G28,별도정산표!$E:$E) -> -827921741 | I28: =SUMIF(울트라팜_FS!$A:$A,BS!G28,울트라팜_FS!$D:$D) -> 0 | J28: =SUMIF(HK_BS!$A:$A,BS!G28,HK_BS!$K:$K) -> 0 | K28: =SUMIF(DHK_BS!$A:$A,BS!G28,DHK_BS!$K:$K) -> 0 | L28: =SUMIF(상해_BS!$A:$A,BS!G28,상해_BS!$K:$K) -> 0 | M28: =SUMIF(SG_BS!$A:$A,BS!G28,SG_BS!$K:$K) -> 0 | N28: =SUMIF(ATGC_BS!$H:$H,BS!G28,ATGC_BS!$I:$I) -> 0 | O28: =SUM(H28:N28) -> -827921741 | P28: =SUMIF(RIC!D:D,BS!G28,RIC!F:F) -> 0 | Q28: =SUMIF(RIC!G:G,BS!G28,RIC!I:I) -> 0 | R28: =O28+P28-Q28 -> -827921741 | S28: =SUMIF(RIT!H:H,BS!G28,RIT!J:J) -> 0 | T28: =SUMIF(RIT!K:K,BS!G28,RIT!M:M) -> 0 | U28: =R28+S28-T28 -> -827921741 | V28: =SUMIF(지분법및기타!$D:$D,BS!G28,지분법및기타!$F:$F) -> 0 | W28: =SUMIF(지분법및기타!$G:$G,BS!G28,지분법및기타!$I:$I) -> 0 | X28: =U28+V28-W28 -> -827921741 | Y28: 제품평가충당금 | AA28: =X28-O28 -> 0
A29: 4 | E29: 원재료 | G29: 14900 | H29: =SUMIF(별도정산표!$G:$G,BS!G29,별도정산표!$E:$E) -> 464851515 | I29: =울트라팜_FS!C16+울트라팜_FS!C19 -> 0 | J29: =SUMIF(HK_BS!$A:$A,BS!G29,HK_BS!$K:$K) -> 0 | K29: =SUMIF(DHK_BS!$A:$A,BS!G29,DHK_BS!$K:$K) -> 0 | L29: =SUMIF(상해_BS!$A:$A,BS!G29,상해_BS!$K:$K) -> 0 | M29: =SUMIF(SG_BS!$A:$A,BS!G29,SG_BS!$K:$K) -> 0 | N29: =SUMIF(ATGC_BS!$H:$H,BS!G29,ATGC_BS!$I:$I) -> 22402866 | O29: =SUM(H29:N29) -> 487254381 | P29: =SUMIF(RIC!D:D,BS!G29,RIC!F:F) -> 0 | Q29: =SUMIF(RIC!G:G,BS!G29,RIC!I:I) -> 0 | R29: =O29+P29-Q29 -> 487254381 | S29: =SUMIF(RIT!H:H,BS!G29,RIT!J:J) -> 0 | T29: =SUMIF(RIT!K:K,BS!G29,RIT!M:M) -> 0 | U29: =R29+S29-T29 -> 487254381 | V29: =SUMIF(지분법및기타!$D:$D,BS!G29,지분법및기타!$F:$F) -> 0 | W29: =SUMIF(지분법및기타!$G:$G,BS!G29,지분법및기타!$I:$I) -> 0 | X29: =U29+V29-W29 -> 487254381 | Y29: 원재료 | AA29: =X29-O29 -> 0
A30: 4 | E30: 원재료재고자산평가충당금 | G30: 16200 | H30: =SUMIF(별도정산표!$G:$G,BS!G30,별도정산표!$E:$E) -> -44697318 | I30: =-울트라팜_FS!C17-울트라팜_FS!C20 -> 0 | J30: =SUMIF(HK_BS!$A:$A,BS!G30,HK_BS!$K:$K) -> 0 | K30: =SUMIF(DHK_BS!$A:$A,BS!G30,DHK_BS!$K:$K) -> 0 | L30: =SUMIF(상해_BS!$A:$A,BS!G30,상해_BS!$K:$K) -> 0 | M30: =SUMIF(SG_BS!$A:$A,BS!G30,SG_BS!$K:$K) -> 0 | N30: =SUMIF(ATGC_BS!$H:$H,BS!G30,ATGC_BS!$I:$I) -> -22402866 | O30: =SUM(H30:N30) -> -67100184 | P30: =SUMIF(RIC!D:D,BS!G30,RIC!F:F) -> 0 | Q30: =SUMIF(RIC!G:G,BS!G30,RIC!I:I) -> 0 | R30: =O30+P30-Q30 -> -67100184 | S30: =SUMIF(RIT!H:H,BS!G30,RIT!J:J) -> 0 | T30: =SUMIF(RIT!K:K,BS!G30,RIT!M:M) -> 0 | U30: =R30+S30-T30 -> -67100184 | V30: =SUMIF(지분법및기타!$D:$D,BS!G30,지분법및기타!$F:$F) -> 0 | W30: =SUMIF(지분법및기타!$G:$G,BS!G30,지분법및기타!$I:$I) -> 0 | X30: =U30+V30-W30 -> -67100184 | Y30: 원재료평가충당금 | AA30: =X30-O30 -> 0
E31: 부재료 | G31: 15000 | H31: =SUMIF(별도정산표!$G:$G,BS!G31,별도정산표!$E:$E) -> 48405072 | I31: 0 | J31: =SUMIF(HK_BS!$A:$A,BS!G31,HK_BS!$K:$K) -> 0 | K31: =SUMIF(DHK_BS!$A:$A,BS!G31,DHK_BS!$K:$K) -> 0 | L31: =SUMIF(상해_BS!$A:$A,BS!G31,상해_BS!$K:$K) -> 0 | M31: =SUMIF(SG_BS!$A:$A,BS!G31,SG_BS!$K:$K) -> 0 | N31: =SUMIF(ATGC_BS!$H:$H,BS!G31,ATGC_BS!$I:$I) -> 0 | O31: =SUM(H31:N31) -> 48405072 | P31: =SUMIF(RIC!D:D,BS!G31,RIC!F:F) -> 0 | Q31: =SUMIF(RIC!G:G,BS!G31,RIC!I:I) -> 0 | R31: =O31+P31-Q31 -> 48405072 | S31: =SUMIF(RIT!H:H,BS!G31,RIT!J:J) -> 0 | T31: =SUMIF(RIT!K:K,BS!G31,RIT!M:M) -> 0 | U31: =R31+S31-T31 -> 48405072 | V31: =SUMIF(지분법및기타!$D:$D,BS!G31,지분법및기타!$F:$F) -> 0 | W31: =SUMIF(지분법및기타!$G:$G,BS!G31,지분법및기타!$I:$I) -> 0 | X31: =U31+V31-W31 -> 48405072 | Y31: 부재료 | AA31: =X31-O31 -> 0
E32: 부재료재고자산평가충당금 | G32: 15100 | H32: =SUMIF(별도정산표!$G:$G,BS!G32,별도정산표!$E:$E) -> -20598322 | J32: =SUMIF(HK_BS!$A:$A,BS!G32,HK_BS!$K:$K) -> 0 | K32: =SUMIF(DHK_BS!$A:$A,BS!G32,DHK_BS!$K:$K) -> 0 | L32: =SUMIF(상해_BS!$A:$A,BS!G32,상해_BS!$K:$K) -> 0 | M32: =SUMIF(SG_BS!$A:$A,BS!G32,SG_BS!$K:$K) -> 0 | N32: =SUMIF(ATGC_BS!$H:$H,BS!G32,ATGC_BS!$I:$I) -> 0 | O32: =SUM(H32:N32) -> -20598322 | P32: =SUMIF(RIC!D:D,BS!G32,RIC!F:F) -> 0 | Q32: =SUMIF(RIC!G:G,BS!G32,RIC!I:I) -> 0 | R32: =O32+P32-Q32 -> -20598322 | S32: =SUMIF(RIT!H:H,BS!G32,RIT!J:J) -> 0 | T32: =SUMIF(RIT!K:K,BS!G32,RIT!M:M) -> 0 | U32: =R32+S32-T32 -> -20598322 | V32: =SUMIF(지분법및기타!$D:$D,BS!G32,지분법및기타!$F:$F) -> 0 | W32: =SUMIF(지분법및기타!$G:$G,BS!G32,지분법및기타!$I:$I) -> 0 | X32: =U32+V32-W32 -> -20598322 | Y32: 부재료평가충당금 | AA32: =X32-O32 -> 0
E33: 재공품 | G33: 15700 | H33: =SUMIF(별도정산표!$G:$G,BS!G33,별도정산표!$E:$E) -> 0 | I33: =SUMIF(울트라팜_FS!$A:$A,BS!G33,울트라팜_FS!$D:$D) -> 0 | J33: =SUMIF(HK_BS!$A:$A,BS!G33,HK_BS!$K:$K) -> 0 | K33: =SUMIF(DHK_BS!$A:$A,BS!G33,DHK_BS!$K:$K) -> 0 | L33: =SUMIF(상해_BS!$A:$A,BS!G33,상해_BS!$K:$K) -> 0 | M33: =SUMIF(SG_BS!$A:$A,BS!G33,SG_BS!$K:$K) -> 0 | N33: =SUMIF(ATGC_BS!$H:$H,BS!G33,ATGC_BS!$I:$I) -> 1451631047 | O33: =SUM(H33:N33) -> 1451631047 | P33: =SUMIF(RIC!D:D,BS!G33,RIC!F:F) -> 0 | Q33: =SUMIF(RIC!G:G,BS!G33,RIC!I:I) -> 0 | R33: =O33+P33-Q33 -> 1451631047 | S33: =SUMIF(RIT!H:H,BS!G33,RIT!J:J) -> 0 | T33: =SUMIF(RIT!K:K,BS!G33,RIT!M:M) -> 0 | U33: =R33+S33-T33 -> 1451631047 | V33: =SUMIF(지분법및기타!$D:$D,BS!G33,지분법및기타!$F:$F) -> 0 | W33: =SUMIF(지분법및기타!$G:$G,BS!G33,지분법및기타!$I:$I) -> 0 | X33: =U33+V33-W33 -> 1451631047 | Y33: 재공품
E34: 재공품재고자산평가충당금 | G34: 15800 | H34: =SUMIF(별도정산표!$G:$G,BS!G34,별도정산표!$E:$E) -> 0 | I34: =SUMIF(울트라팜_FS!$A:$A,BS!G34,울트라팜_FS!$D:$D) -> 0 | J34: =SUMIF(HK_BS!$A:$A,BS!G34,HK_BS!$K:$K) -> 0 | K34: =SUMIF(DHK_BS!$A:$A,BS!G34,DHK_BS!$K:$K) -> 0 | L34: =SUMIF(상해_BS!$A:$A,BS!G34,상해_BS!$K:$K) -> 0 | M34: =SUMIF(SG_BS!$A:$A,BS!G34,SG_BS!$K:$K) -> 0 | N34: =SUMIF(ATGC_BS!$H:$H,BS!G34,ATGC_BS!$I:$I) -> -1451631047 | O34: =SUM(H34:N34) -> -1451631047 | P34: =SUMIF(RIC!D:D,BS!G34,RIC!F:F) -> 0 | Q34: =SUMIF(RIC!G:G,BS!G34,RIC!I:I) -> 0 | R34: =O34+P34-Q34 -> -1451631047 | S34: =SUMIF(RIT!H:H,BS!G34,RIT!J:J) -> 0 | T34: =SUMIF(RIT!K:K,BS!G34,RIT!M:M) -> 0 | U34: =R34+S34-T34 -> -1451631047 | V34: =SUMIF(지분법및기타!$D:$D,BS!G34,지분법및기타!$F:$F) -> 0 | W34: =SUMIF(지분법및기타!$G:$G,BS!G34,지분법및기타!$I:$I) -> 0 | X34: =U34+V34-W34 -> -1451631047 | Y34: 재공품평가충당금
E35: 미사용 | H35: =SUMIF(별도정산표!$G:$G,BS!G35,별도정산표!$E:$E) -> 0 | I35: =SUMIF(울트라팜_FS!$A:$A,BS!G35,울트라팜_FS!$D:$D) -> 0 | J35: =SUMIF(HK_BS!$A:$A,BS!G35,HK_BS!$K:$K) -> 0 | K35: =SUMIF(DHK_BS!$A:$A,BS!G35,DHK_BS!$K:$K) -> 0 | L35: =SUMIF(상해_BS!$A:$A,BS!G35,상해_BS!$K:$K) -> 0 | M35: =SUMIF(SG_BS!$A:$A,BS!G35,SG_BS!$K:$K) -> 0 | N35: =SUMIF(ATGC_BS!$H:$H,BS!G35,ATGC_BS!$I:$I) -> 0 | O35: =SUM(H35:N35) -> 0 | P35: =SUMIF(RIC!D:D,BS!G35,RIC!F:F) -> 0 | Q35: =SUMIF(RIC!G:G,BS!G35,RIC!I:I) -> 0 | R35: =O35+P35-Q35 -> 0 | S35: =SUMIF(RIT!H:H,BS!G35,RIT!J:J) -> 0 | T35: =SUMIF(RIT!K:K,BS!G35,RIT!M:M) -> 0 | U35: =R35+S35-T35 -> 0 | V35: =SUMIF(지분법및기타!$D:$D,BS!G35,지분법및기타!$F:$F) -> 0 | W35: =SUMIF(지분법및기타!$G:$G,BS!G35,지분법및기타!$I:$I) -> 0 | X35: =U35+V35-W35 -> 0
A36: 3 | D36: 유동성 보증금 | H36: =SUM(H37:H38) -> 0 | I36: =SUM(I37:I38) -> 0 | J36: =SUM(J37:J38) -> 17988900 | K36: =SUM(K37:K38) -> 40443667 | L36: =SUM(L37:L38) -> 0 | M36: =SUM(M37:M38) -> 0 | N36: =SUM(N37:N38) -> 0 | O36: =SUM(O37:O38) -> 58432567 | R36: =R37+R38 -> 58432567 | U36: =U37+U38 -> 58432567 | V36: =SUMIF(지분법및기타!$D:$D,BS!G36,지분법및기타!$F:$F) -> 0 | W36: =SUMIF(지분법및기타!$G:$G,BS!G36,지분법및기타!$I:$I) -> 0 | X36: =X37+X38 -> 58432567
E37: 임차보증금(유동) | G37: 12400 | H37: =SUMIF(별도정산표!$G:$G,BS!G37,별도정산표!$E:$E) -> 0 | I37: =SUMIF(울트라팜_FS!$A:$A,BS!G37,울트라팜_FS!$D:$D) -> 0 | J37: =SUMIF(HK_BS!$A:$A,BS!G37,HK_BS!$K:$K) -> 17988900 | K37: =SUMIF(DHK_BS!$A:$A,BS!G37,DHK_BS!$K:$K) -> 40443667 | L37: =SUMIF(상해_BS!$A:$A,BS!G37,상해_BS!$K:$K) -> 0 | M37: =SUMIF(SG_BS!$A:$A,BS!G37,SG_BS!$K:$K) -> 0 | N37: =SUMIF(ATGC_BS!$H:$H,BS!G37,ATGC_BS!$I:$I) -> 0 | O37: =SUM(H37:N37) -> 58432567 | P37: =SUMIF(RIC!D:D,BS!G37,RIC!F:F) -> 0 | Q37: =SUMIF(RIC!G:G,BS!G37,RIC!I:I) -> 0 | R37: =O37+P37-Q37 -> 58432567 | S37: =SUMIF(RIT!H:H,BS!G37,RIT!J:J) -> 0 | T37: =SUMIF(RIT!K:K,BS!G37,RIT!M:M) -> 0 | U37: =R37+S37-T37 -> 58432567 | V37: =SUMIF(지분법및기타!$D:$D,BS!G37,지분법및기타!$F:$F) -> 0 | W37: =SUMIF(지분법및기타!$G:$G,BS!G37,지분법및기타!$I:$I) -> 0 | X37: =U37+V37-W37 -> 58432567 | Y37: 임차보증금(유동) | AA37: =X37-O37 -> 0
E38: 미사용 | H38: =SUMIF(별도정산표!$G:$G,BS!G38,별도정산표!$E:$E) -> 0 | I38: =SUMIF(울트라팜_FS!$A:$A,BS!G38,울트라팜_FS!$D:$D) -> 0 | J38: =SUMIF(HK_BS!$A:$A,BS!G38,HK_BS!$K:$K) -> 0 | K38: =SUMIF(DHK_BS!$A:$A,BS!G38,DHK_BS!$K:$K) -> 0 | L38: =SUMIF(상해_BS!$A:$A,BS!G38,상해_BS!$K:$K) -> 0 | M38: =SUMIF(SG_BS!$A:$A,BS!G38,SG_BS!$K:$K) -> 0 | N38: =SUMIF(ATGC_BS!$H:$H,BS!G38,ATGC_BS!$I:$I) -> 0 | O38: =SUM(H38:N38) -> 0 | P38: =SUMIF(RIC!D:D,BS!G38,RIC!F:F) -> 0 | Q38: =SUMIF(RIC!G:G,BS!G38,RIC!I:I) -> 0 | R38: =O38+P38-Q38 -> 0 | S38: =SUMIF(RIT!H:H,BS!G38,RIT!J:J) -> 0 | T38: =SUMIF(RIT!K:K,BS!G38,RIT!M:M) -> 0 | U38: =R38+S38-T38 -> 0 | V38: =SUMIF(지분법및기타!$D:$D,BS!G38,지분법및기타!$F:$F) -> 0 | W38: =SUMIF(지분법및기타!$G:$G,BS!G38,지분법및기타!$I:$I) -> 0 | X38: =U38+V38-W38 -> 0
A39: 2 | C39: 비유동자산 | H39: =H43+H48+H68+H77+H84+H40 -> 37605682655 | I39: =I43+I48+I68+I77+I84 -> 0 | J39: =J43+J48+J68+J77+J84 -> 225947074 | K39: =K43+K48+K68+K77+K84 -> 291758933 | L39: =L43+L48+L68+L77+L84 -> 0 | M39: =M43+M48+M68+M77+M84 -> 0 | N39: =N43+N48+N68+N77+N84 -> 8080134954 | O39: =O43+O48+O68+O77+O84+O40 -> 46203523616 | R39: =R43+R48+R68+R77+R84+R40 -> 49695805077 | U39: =U43+U48+U68+U77+U84+U40 -> 49694228886 | V39: =SUMIF(지분법및기타!$D:$D,BS!G39,지분법및기타!$F:$F) -> 0 | W39: =SUMIF(지분법및기타!$G:$G,BS!G39,지분법및기타!$I:$I) -> 0 | X39: =X43+X48+X68+X77+X84+X40 -> 47987765603
A40: 3 | D40: 장기매출채권 | H40: =SUM(H41:H42) -> 0 | I40: =SUM(I41:I42) -> 0 | J40: =SUM(J41:J42) -> 0 | K40: =SUM(K41:K42) -> 0 | L40: =SUM(L41:L42) -> 0 | M40: =SUM(M41:M42) -> 0 | N40: =SUM(N41:N42) -> 0 | O40: =SUM(O41:O42) -> 0 | R40: =SUM(R41:R42) -> 0 | U40: =SUM(U41:U42) -> 0 | V40: =SUMIF(지분법및기타!$D:$D,BS!G40,지분법및기타!$F:$F) -> 0 | W40: =SUMIF(지분법및기타!$G:$G,BS!G40,지분법및기타!$I:$I) -> 0 | X40: =SUM(X41:X42) -> 0
A41: 4 | E41: 미사용 | H41: =SUMIF(별도정산표!$G:$G,BS!G41,별도정산표!$E:$E) -> 0 | I41: =SUMIF(울트라팜_FS!$A:$A,BS!G41,울트라팜_FS!$D:$D) -> 0 | J41: =SUMIF(HK_BS!$A:$A,BS!G41,HK_BS!$K:$K) -> 0 | K41: =SUMIF(DHK_BS!$A:$A,BS!G41,DHK_BS!$K:$K) -> 0 | L41: =SUMIF(상해_BS!$A:$A,BS!G41,상해_BS!$K:$K) -> 0 | M41: =SUMIF(SG_BS!$A:$A,BS!G41,SG_BS!$K:$K) -> 0 | N41: =SUMIF(ATGC_BS!$H:$H,BS!G41,ATGC_BS!$I:$I) -> 0 | O41: =SUM(H41:N41) -> 0 | P41: =SUMIF(RIC!D:D,BS!G41,RIC!F:F) -> 0 | Q41: =SUMIF(RIC!G:G,BS!G41,RIC!I:I) -> 0 | R41: =O41+P41-Q41 -> 0 | S41: =SUMIF(RIT!H:H,BS!G41,RIT!J:J) -> 0 | T41: =SUMIF(RIT!K:K,BS!G41,RIT!M:M) -> 0 | U41: =R41+S41-T41 -> 0 | V41: =SUMIF(지분법및기타!$D:$D,BS!G41,지분법및기타!$F:$F) -> 0 | W41: =SUMIF(지분법및기타!$G:$G,BS!G41,지분법및기타!$I:$I) -> 0 | X41: =U41+V41-W41 -> 0
E42: 미사용 | H42: =SUMIF(별도정산표!$G:$G,BS!G42,별도정산표!$E:$E) -> 0 | I42: =SUMIF(울트라팜_FS!$A:$A,BS!G42,울트라팜_FS!$D:$D) -> 0 | J42: =SUMIF(HK_BS!$A:$A,BS!G42,HK_BS!$K:$K) -> 0 | K42: =SUMIF(DHK_BS!$A:$A,BS!G42,DHK_BS!$K:$K) -> 0 | L42: =SUMIF(상해_BS!$A:$A,BS!G42,상해_BS!$K:$K) -> 0 | M42: =SUMIF(SG_BS!$A:$A,BS!G42,SG_BS!$K:$K) -> 0 | N42: =SUMIF(ATGC_BS!$H:$H,BS!G42,ATGC_BS!$I:$I) -> 0 | O42: =SUM(H42:N42) -> 0 | P42: =SUMIF(RIC!D:D,BS!G42,RIC!F:F) -> 0 | Q42: =SUMIF(RIC!G:G,BS!G42,RIC!I:I) -> 0 | R42: =O42+P42-Q42 -> 0 | S42: =SUMIF(RIT!H:H,BS!G42,RIT!J:J) -> 0 | T42: =SUMIF(RIT!K:K,BS!G42,RIT!M:M) -> 0 | U42: =R42+S42-T42 -> 0 | V42: =SUMIF(지분법및기타!$D:$D,BS!G42,지분법및기타!$F:$F) -> 0 | W42: =SUMIF(지분법및기타!$G:$G,BS!G42,지분법및기타!$I:$I) -> 0 | X42: =U42+V42-W42 -> 0
A43: 3 | D43: 투자자산 | H43: =SUM(H44:H47) -> 25520890121 | I43: =SUM(I44:I47) -> 0 | J43: =SUM(J44:J47) -> 196600000 | K43: =SUM(K44:K47) -> 0 | L43: =SUM(L44:L47) -> 0 | M43: =SUM(M44:M47) -> 0 | N43: =SUM(N44:N47) -> 0 | O43: =SUM(O44:O47) -> 25717490121 | R43: =SUM(R44:R47) -> 1879128223 | U43: =SUM(U44:U47) -> 1879128223 | V43: =SUMIF(지분법및기타!$D:$D,BS!G43,지분법및기타!$F:$F) -> 0 | W43: =SUMIF(지분법및기타!$G:$G,BS!G43,지분법및기타!$I:$I) -> 0 | X43: =SUM(X44:X47) -> 172664940 | AA43: =X43-O43 -> -25544825181 | AB43: 전액 투자자본상계 제거액
A44: 4 | E44: 당기손익-공정가치금융자산 | G44: 19500 | H44: =SUMIF(별도정산표!$G:$G,BS!G44,별도정산표!$E:$E) -> 172664940 | I44: =SUMIF(울트라팜_FS!$A:$A,BS!G44,울트라팜_FS!$D:$D) -> 0 | J44: =SUMIF(HK_BS!$A:$A,BS!G44,HK_BS!$K:$K) -> 0 | K44: =SUMIF(DHK_BS!$A:$A,BS!G44,DHK_BS!$K:$K) -> 0 | L44: =SUMIF(상해_BS!$A:$A,BS!G44,상해_BS!$K:$K) -> 0 | M44: =SUMIF(SG_BS!$A:$A,BS!G44,SG_BS!$K:$K) -> 0 | N44: =SUMIF(ATGC_BS!$H:$H,BS!G44,ATGC_BS!$I:$I) -> 0 | O44: =SUM(H44:N44) -> 172664940 | P44: =SUMIF(RIC!D:D,BS!G44,RIC!F:F) -> 0 | Q44: =SUMIF(RIC!G:G,BS!G44,RIC!I:I) -> 0 | R44: =O44+P44-Q44 -> 172664940 | S44: =SUMIF(RIT!H:H,BS!G44,RIT!J:J) -> 0 | T44: =SUMIF(RIT!K:K,BS!G44,RIT!M:M) -> 0 | U44: =R44+S44-T44 -> 172664940 | V44: =SUMIF(지분법및기타!$D:$D,BS!G44,지분법및기타!$F:$F) -> 0 | W44: =SUMIF(지분법및기타!$G:$G,BS!G44,지분법및기타!$I:$I) -> 0 | X44: =U44+V44-W44 -> 172664940 | Y44: 당기손익-공정가치금융자산 | AA44: =X44-O44 -> 0
A45: 4 | E45: 종속기업투자 | G45: 17600 | H45: =SUMIF(별도정산표!$G:$G,BS!G45,별도정산표!$E:$E) -> 25348225181 | I45: =SUMIF(울트라팜_FS!$A:$A,BS!G45,울트라팜_FS!$D:$D) -> 0 | J45: =SUMIF(HK_BS!$A:$A,BS!G45,HK_BS!$K:$K) -> 196600000 | K45: =SUMIF(DHK_BS!$A:$A,BS!G45,DHK_BS!$K:$K) -> 0 | L45: =SUMIF(상해_BS!$A:$A,BS!G45,상해_BS!$K:$K) -> 0 | M45: =SUMIF(SG_BS!$A:$A,BS!G45,SG_BS!$K:$K) -> 0 | N45: =SUMIF(ATGC_BS!$H:$H,BS!G45,ATGC_BS!$I:$I) -> 0 | O45: =SUM(H45:N45) -> 25544825181 | P45: =SUMIF(RIC!D:D,BS!G45,RIC!F:F) -> 398237023 | Q45: =SUMIF(RIC!G:G,BS!G45,RIC!I:I) -> 26304544698 | R45: =O45+P45-Q45 -> -361482494 | S45: =SUMIF(RIT!H:H,BS!G45,RIT!J:J) -> 0 | T45: =SUMIF(RIT!K:K,BS!G45,RIT!M:M) -> 0 | U45: =R45+S45-T45 -> -361482494 | V45: =SUMIF(지분법및기타!$D:$D,BS!G45,지분법및기타!$F:$F) -> 361482494 | W45: =SUMIF(지분법및기타!$G:$G,BS!G45,지분법및기타!$I:$I) -> 0 | X45: =U45+V45-W45 -> 0 | Y45: 종속기업투자
E46: 관계기업투자 | G46: 17700 | H46: =SUMIF(별도정산표!$G:$G,BS!G46,별도정산표!$E:$E) -> 0 | I46: =SUMIF(울트라팜_FS!$A:$A,BS!G46,울트라팜_FS!$D:$D) -> 0 | J46: =SUMIF(HK_BS!$A:$A,BS!G46,HK_BS!$K:$K) -> 0 | K46: =SUMIF(DHK_BS!$A:$A,BS!G46,DHK_BS!$K:$K) -> 0 | L46: =SUMIF(상해_BS!$A:$A,BS!G46,상해_BS!$K:$K) -> 0 | M46: =SUMIF(SG_BS!$A:$A,BS!G46,SG_BS!$K:$K) -> 0 | N46: =SUMIF(ATGC_BS!$H:$H,BS!G46,ATGC_BS!$I:$I) -> 0 | O46: =SUM(H46:N46) -> 0 | P46: =SUMIF(RIC!D:D,BS!G46,RIC!F:F) -> 2067945777 | Q46: =SUMIF(RIC!G:G,BS!G46,RIC!I:I) -> 0 | R46: =O46+P46-Q46 -> 2067945777 | U46: =R46+S46-T46 -> 2067945777 | V46: =SUMIF(지분법및기타!$D:$D,BS!G46,지분법및기타!$F:$F) -> 78288846 | W46: =SUMIF(지분법및기타!$G:$G,BS!G46,지분법및기타!$I:$I) -> 2146234623 | X46: =U46+V46-W46 -> 0 | Y46: 관계기업투자
A47: 4 | E47: 미사용 | H47: =SUMIF(별도정산표!$G:$G,BS!G47,별도정산표!$E:$E) -> 0 | I47: =SUMIF(울트라팜_FS!$A:$A,BS!G47,울트라팜_FS!$D:$D) -> 0 | J47: =SUMIF(HK_BS!$A:$A,BS!G47,HK_BS!$K:$K) -> 0 | K47: =SUMIF(DHK_BS!$A:$A,BS!G47,DHK_BS!$K:$K) -> 0 | L47: =SUMIF(상해_BS!$A:$A,BS!G47,상해_BS!$K:$K) -> 0 | M47: =SUMIF(SG_BS!$A:$A,BS!G47,SG_BS!$K:$K) -> 0 | N47: =SUMIF(ATGC_BS!$H:$H,BS!G47,ATGC_BS!$I:$I) -> 0 | O47: =SUM(H47:N47) -> 0 | P47: =SUMIF(RIC!D:D,BS!G47,RIC!F:F) -> 0 | Q47: =SUMIF(RIC!G:G,BS!G47,RIC!I:I) -> 0 | R47: =O47+P47-Q47 -> 0 | S47: =SUMIF(RIT!H:H,BS!G47,RIT!J:J) -> 0 | T47: =SUMIF(RIT!K:K,BS!G47,RIT!M:M) -> 0 | U47: =R47+S47-T47 -> 0 | V47: =SUMIF(지분법및기타!$D:$D,BS!G47,지분법및기타!$F:$F) -> 0 | W47: =SUMIF(지분법및기타!$G:$G,BS!G47,지분법및기타!$I:$I) -> 0 | X47: =U47+V47-W47 -> 0
A48: 3 | D48: 유형자산 | H48: =SUM(H49:H67) -> 9018883065 | I48: =SUM(I49:I67) -> 0 | J48: =SUM(J49:J67) -> 29347074 | K48: =SUM(K49:K67) -> 291758933 | L48: =SUM(L49:L67) -> 0 | M48: =SUM(M49:M67) -> 0 | N48: =SUM(N49:N67) -> 1539612650 | O48: =SUM(O49:O67) -> 10879601722 | R48: =SUM(R49:R67) -> 10879601722 | U48: =SUM(U49:U67) -> 10878025531 | V48: =SUMIF(지분법및기타!$D:$D,BS!G48,지분법및기타!$F:$F) -> 0 | W48: =SUMIF(지분법및기타!$G:$G,BS!G48,지분법및기타!$I:$I) -> 0 | X48: =SUM(X49:X67) -> 10878025531 | AA48: =X48-O48 -> -1576191
A49: 4 | E49: 토지 | G49: 20100 | H49: =SUMIF(별도정산표!$G:$G,BS!G49,별도정산표!$E:$E) -> 1115280040 | I49: =울트라팜_FS!C24 -> 0 | J49: =SUMIF(HK_BS!$A:$A,BS!G49,HK_BS!$K:$K) -> 0 | K49: =SUMIF(DHK_BS!$A:$A,BS!G49,DHK_BS!$K:$K) -> 0 | L49: =SUMIF(상해_BS!$A:$A,BS!G49,상해_BS!$K:$K) -> 0 | M49: =SUMIF(SG_BS!$A:$A,BS!G49,SG_BS!$K:$K) -> 0 | N49: =SUMIF(ATGC_BS!$H:$H,BS!G49,ATGC_BS!$I:$I) -> 0 | O49: =SUM(H49:N49) -> 1115280040 | P49: =SUMIF(RIC!D:D,BS!G49,RIC!F:F) -> 0 | Q49: =SUMIF(RIC!G:G,BS!G49,RIC!I:I) -> 0 | R49: =O49+P49-Q49 -> 1115280040 | S49: =SUMIF(RIT!H:H,BS!G49,RIT!J:J) -> 0 | T49: =SUMIF(RIT!K:K,BS!G49,RIT!M:M) -> 0 | U49: =R49+S49-T49 -> 1115280040 | V49: =SUMIF(지분법및기타!$D:$D,BS!G49,지분법및기타!$F:$F) -> 0 | W49: =SUMIF(지분법및기타!$G:$G,BS!G49,지분법및기타!$I:$I) -> 0 | X49: =U49+V49-W49 -> 1115280040 | Y49: 토지 | AA49: =X49-O49 -> 0
E50: 건물 | G50: 20200 | H50: =SUMIF(별도정산표!$G:$G,BS!G50,별도정산표!$E:$E) -> 2832428420 | I50: =울트라팜_FS!C25 -> 0 | J50: =SUMIF(HK_BS!$A:$A,BS!G50,HK_BS!$K:$K) -> 0 | K50: =SUMIF(DHK_BS!$A:$A,BS!G50,DHK_BS!$K:$K) -> 0 | L50: =SUMIF(상해_BS!$A:$A,BS!G50,상해_BS!$K:$K) -> 0 | M50: =SUMIF(SG_BS!$A:$A,BS!G50,SG_BS!$K:$K) -> 0 | N50: =SUMIF(ATGC_BS!$H:$H,BS!G50,ATGC_BS!$I:$I) -> 0 | O50: =SUM(H50:N50) -> 2832428420 | P50: =SUMIF(RIC!D:D,BS!G50,RIC!F:F) -> 0 | Q50: =SUMIF(RIC!G:G,BS!G50,RIC!I:I) -> 0 | R50: =O50+P50-Q50 -> 2832428420 | S50: =SUMIF(RIT!H:H,BS!G50,RIT!J:J) -> 0 | T50: =SUMIF(RIT!K:K,BS!G50,RIT!M:M) -> 0 | U50: =R50+S50-T50 -> 2832428420 | V50: =SUMIF(지분법및기타!$D:$D,BS!G50,지분법및기타!$F:$F) -> 0 | W50: =SUMIF(지분법및기타!$G:$G,BS!G50,지분법및기타!$I:$I) -> 0 | X50: =U50+V50-W50 -> 2832428420 | Y50: 건물
E51: 감가상각누계액건물 | G51: 20300 | H51: =SUMIF(별도정산표!$G:$G,BS!G51,별도정산표!$E:$E) -> -61959374 | I51: =울트라팜_FS!C26 -> 0 | J51: =SUMIF(HK_BS!$A:$A,BS!G51,HK_BS!$K:$K) -> 0 | K51: =SUMIF(DHK_BS!$A:$A,BS!G51,DHK_BS!$K:$K) -> 0 | L51: =SUMIF(상해_BS!$A:$A,BS!G51,상해_BS!$K:$K) -> 0 | M51: =SUMIF(SG_BS!$A:$A,BS!G51,SG_BS!$K:$K) -> 0 | N51: =SUMIF(ATGC_BS!$H:$H,BS!G51,ATGC_BS!$I:$I) -> 0 | O51: =SUM(H51:N51) -> -61959374 | P51: =SUMIF(RIC!D:D,BS!G51,RIC!F:F) -> 0 | Q51: =SUMIF(RIC!G:G,BS!G51,RIC!I:I) -> 0 | R51: =O51+P51-Q51 -> -61959374 | S51: =SUMIF(RIT!H:H,BS!G51,RIT!J:J) -> 0 | T51: =SUMIF(RIT!K:K,BS!G51,RIT!M:M) -> 0 | U51: =R51+S51-T51 -> -61959374 | V51: =SUMIF(지분법및기타!$D:$D,BS!G51,지분법및기타!$F:$F) -> 0 | W51: =SUMIF(지분법및기타!$G:$G,BS!G51,지분법및기타!$I:$I) -> 0 | X51: =U51+V51-W51 -> -61959374 | Y51: 건물감가상각누계액
E52: 기계장치 | G52: 20600 | H52: =SUMIF(별도정산표!$G:$G,BS!G52,별도정산표!$E:$E) -> 2674264961 | I52: =울트라팜_FS!C25 -> 0 | J52: =SUMIF(HK_BS!$A:$A,BS!G52,HK_BS!$K:$K) -> 0 | K52: =SUMIF(DHK_BS!$A:$A,BS!G52,DHK_BS!$K:$K) -> 0 | L52: =SUMIF(상해_BS!$A:$A,BS!G52,상해_BS!$K:$K) -> 0 | M52: =SUMIF(SG_BS!$A:$A,BS!G52,SG_BS!$K:$K) -> 0 | N52: =SUMIF(ATGC_BS!$H:$H,BS!G52,ATGC_BS!$I:$I) -> 2205763514 | O52: =SUM(H52:N52) -> 4880028475 | R52: =O52+P52-Q52 -> 4880028475 | U52: =R52+S52-T52 -> 4880028475 | X52: =U52+V52-W52 -> 4880028475 | Y52: 기계장치 | AA52: =X52-O52 -> 0
E53: 감가상각누계액기계장치 | G53: 20700 | H53: =SUMIF(별도정산표!$G:$G,BS!G53,별도정산표!$E:$E) -> -1323604760 | I53: =울트라팜_FS!C26 -> 0 | J53: =SUMIF(HK_BS!$A:$A,BS!G53,HK_BS!$K:$K) -> 0 | K53: =SUMIF(DHK_BS!$A:$A,BS!G53,DHK_BS!$K:$K) -> 0 | L53: =SUMIF(상해_BS!$A:$A,BS!G53,상해_BS!$K:$K) -> 0 | M53: =SUMIF(SG_BS!$A:$A,BS!G53,SG_BS!$K:$K) -> 0 | N53: =SUMIF(ATGC_BS!$H:$H,BS!G53,ATGC_BS!$I:$I) -> -1673360452 | O53: =SUM(H53:N53) -> -2996965212 | R53: =O53+P53-Q53 -> -2996965212 | U53: =R53+S53-T53 -> -2996965212 | X53: =U53+V53-W53 -> -2996965212 | Y53: 기계감가상각누계액 | AA53: =X53-O53 -> 0
A54: 4 | E54: 차량운반구 | G54: 20800 | H54: =SUMIF(별도정산표!$G:$G,BS!G54,별도정산표!$E:$E) -> 7974819 | I54: =울트라팜_FS!C26 -> 0 | J54: =SUMIF(HK_BS!$A:$A,BS!G54,HK_BS!$K:$K) -> 0 | K54: =SUMIF(DHK_BS!$A:$A,BS!G54,DHK_BS!$K:$K) -> 0 | L54: =SUMIF(상해_BS!$A:$A,BS!G54,상해_BS!$K:$K) -> 0 | M54: =SUMIF(SG_BS!$A:$A,BS!G54,SG_BS!$K:$K) -> 0 | N54: =SUMIF(ATGC_BS!$H:$H,BS!G54,ATGC_BS!$I:$I) -> 0 | O54: =SUM(H54:N54) -> 7974819 | P54: =SUMIF(RIC!D:D,BS!G54,RIC!F:F) -> 0 | Q54: =SUMIF(RIC!G:G,BS!G54,RIC!I:I) -> 0 | R54: =O54+P54-Q54 -> 7974819 | S54: =SUMIF(RIT!H:H,BS!G54,RIT!J:J) -> 0 | T54: =SUMIF(RIT!K:K,BS!G54,RIT!M:M) -> 0 | U54: =R54+S54-T54 -> 7974819 | V54: =SUMIF(지분법및기타!$D:$D,BS!G54,지분법및기타!$F:$F) -> 0 | W54: =SUMIF(지분법및기타!$G:$G,BS!G54,지분법및기타!$I:$I) -> 0 | X54: =U54+V54-W54 -> 7974819 | Y54: 차량운반구 | AA54: =X54-O54 -> 0
A55: 4 | E55: 감가상각누계액차량운반구 | G55: 20900 | H55: =SUMIF(별도정산표!$G:$G,BS!G55,별도정산표!$E:$E) -> -7972819 | I55: =-울트라팜_FS!C27 -> 0 | J55: =SUMIF(HK_BS!$A:$A,BS!G55,HK_BS!$K:$K) -> 0 | K55: =SUMIF(DHK_BS!$A:$A,BS!G55,DHK_BS!$K:$K) -> 0 | L55: =SUMIF(상해_BS!$A:$A,BS!G55,상해_BS!$K:$K) -> 0 | M55: =SUMIF(SG_BS!$A:$A,BS!G55,SG_BS!$K:$K) -> 0 | N55: =SUMIF(ATGC_BS!$H:$H,BS!G55,ATGC_BS!$I:$I) -> 0 | O55: =SUM(H55:N55) -> -7972819 | P55: =SUMIF(RIC!D:D,BS!G55,RIC!F:F) -> 0 | Q55: =SUMIF(RIC!G:G,BS!G55,RIC!I:I) -> 0 | R55: =O55+P55-Q55 -> -7972819 | S55: =SUMIF(RIT!H:H,BS!G55,RIT!J:J) -> 0 | T55: =SUMIF(RIT!K:K,BS!G55,RIT!M:M) -> 0 | U55: =R55+S55-T55 -> -7972819 | V55: =SUMIF(지분법및기타!$D:$D,BS!G55,지분법및기타!$F:$F) -> 0 | W55: =SUMIF(지분법및기타!$G:$G,BS!G55,지분법및기타!$I:$I) -> 0 | X55: =U55+V55-W55 -> -7972819 | Y55: 차량감가상각누계액 | AA55: =X55-O55 -> 0
A56: 4 | E56: 공구와기구 | G56: 21000 | H56: =SUMIF(별도정산표!$G:$G,BS!G56,별도정산표!$E:$E) -> 131100000 | I56: 0 | J56: =SUMIF(HK_BS!$A:$A,BS!G56,HK_BS!$K:$K) -> 0 | K56: =SUMIF(DHK_BS!$A:$A,BS!G56,DHK_BS!$K:$K) -> 0 | L56: =SUMIF(상해_BS!$A:$A,BS!G56,상해_BS!$K:$K) -> 0 | M56: =SUMIF(SG_BS!$A:$A,BS!G56,SG_BS!$K:$K) -> 0 | N56: =SUMIF(ATGC_BS!$H:$H,BS!G56,ATGC_BS!$I:$I) -> 0 | O56: =SUM(H56:N56) -> 131100000 | P56: =SUMIF(RIC!D:D,BS!G56,RIC!F:F) -> 0 | Q56: =SUMIF(RIC!G:G,BS!G56,RIC!I:I) -> 0 | R56: =O56+P56-Q56 -> 131100000 | S56: =SUMIF(RIT!H:H,BS!G56,RIT!J:J) -> 0 | T56: =SUMIF(RIT!K:K,BS!G56,RIT!M:M) -> 0 | U56: =R56+S56-T56 -> 131100000 | V56: =SUMIF(지분법및기타!$D:$D,BS!G56,지분법및기타!$F:$F) -> 0 | W56: =SUMIF(지분법및기타!$G:$G,BS!G56,지분법및기타!$I:$I) -> 0 | X56: =U56+V56-W56 -> 131100000 | Y56: 공구와기구 | AA56: =X56-O56 -> 0
A57: 4 | E57: 감가상각누계액공구와기구 | G57: 21100 | H57: =SUMIF(별도정산표!$G:$G,BS!G57,별도정산표!$E:$E) -> -67838194 | I57: 0 | J57: =SUMIF(HK_BS!$A:$A,BS!G57,HK_BS!$K:$K) -> 0 | K57: =SUMIF(DHK_BS!$A:$A,BS!G57,DHK_BS!$K:$K) -> 0 | L57: =SUMIF(상해_BS!$A:$A,BS!G57,상해_BS!$K:$K) -> 0 | M57: =SUMIF(SG_BS!$A:$A,BS!G57,SG_BS!$K:$K) -> 0 | N57: =SUMIF(ATGC_BS!$H:$H,BS!G57,ATGC_BS!$I:$I) -> 0 | O57: =SUM(H57:N57) -> -67838194 | P57: =SUMIF(RIC!D:D,BS!G57,RIC!F:F) -> 0 | Q57: =SUMIF(RIC!G:G,BS!G57,RIC!I:I) -> 0 | R57: =O57+P57-Q57 -> -67838194 | S57: =SUMIF(RIT!H:H,BS!G57,RIT!J:J) -> 0 | T57: =SUMIF(RIT!K:K,BS!G57,RIT!M:M) -> 0 | U57: =R57+S57-T57 -> -67838194 | V57: =SUMIF(지분법및기타!$D:$D,BS!G57,지분법및기타!$F:$F) -> 0 | W57: =SUMIF(지분법및기타!$G:$G,BS!G57,지분법및기타!$I:$I) -> 0 | X57: =U57+V57-W57 -> -67838194 | Y57: 공구와기구감가상각누계액 | AA57: =X57-O57 -> 0
A58: 4 | E58: 비품 | G58: 21200 | H58: =SUMIF(별도정산표!$G:$G,BS!G58,별도정산표!$E:$E) -> 368187065 | I58: =울트라팜_FS!C28 -> 0 | J58: =SUMIF(HK_BS!$A:$A,BS!G58,HK_BS!$K:$K) -> 54274031 | K58: =SUMIF(DHK_BS!$A:$A,BS!G58,DHK_BS!$K:$K) -> 174153610 | L58: =SUMIF(상해_BS!$A:$A,BS!G58,상해_BS!$K:$K) -> 0 | M58: =SUMIF(SG_BS!$A:$A,BS!G58,SG_BS!$K:$K) -> 0 | N58: =SUMIF(ATGC_BS!$H:$H,BS!G58,ATGC_BS!$I:$I) -> 927664055 | O58: =SUM(H58:N58) -> 1524278761 | P58: =SUMIF(RIC!D:D,BS!G58,RIC!F:F) -> 0 | Q58: =SUMIF(RIC!G:G,BS!G58,RIC!I:I) -> 0 | R58: =O58+P58-Q58 -> 1524278761 | S58: =SUMIF(RIT!H:H,BS!G58,RIT!J:J) -> 10761784 | T58: =SUMIF(RIT!K:K,BS!G58,RIT!M:M) -> 0 | U58: =R58+S58-T58 -> 1535040545 | V58: =SUMIF(지분법및기타!$D:$D,BS!G58,지분법및기타!$F:$F) -> 0 | W58: =SUMIF(지분법및기타!$G:$G,BS!G58,지분법및기타!$I:$I) -> 0 | X58: =U58+V58-W58 -> 1535040545 | Y58: 집기비품 | AA58: =X58-O58 -> 10761784
A59: 4 | E59: 감가상각누계액비품 | G59: 21300 | H59: =SUMIF(별도정산표!$G:$G,BS!G59,별도정산표!$E:$E) -> -189699106 | I59: =-울트라팜_FS!C29 -> 0 | J59: =SUMIF(HK_BS!$A:$A,BS!G59,HK_BS!$K:$K) -> -29069140 | K59: =SUMIF(DHK_BS!$A:$A,BS!G59,DHK_BS!$K:$K) -> -79783760 | L59: =SUMIF(상해_BS!$A:$A,BS!G59,상해_BS!$K:$K) -> 0 | M59: =SUMIF(SG_BS!$A:$A,BS!G59,SG_BS!$K:$K) -> 0 | N59: =SUMIF(ATGC_BS!$H:$H,BS!G59,ATGC_BS!$I:$I) -> -910698842 | O59: =SUM(H59:N59) -> -1209250848 | P59: =SUMIF(RIC!D:D,BS!G59,RIC!F:F) -> 0 | Q59: =SUMIF(RIC!G:G,BS!G59,RIC!I:I) -> 0 | R59: =O59+P59-Q59 -> -1209250848 | S59: =SUMIF(RIT!H:H,BS!G59,RIT!J:J) -> 0 | T59: =SUMIF(RIT!K:K,BS!G59,RIT!M:M) -> 12337975 | U59: =R59+S59-T59 -> -1221588823 | V59: =SUMIF(지분법및기타!$D:$D,BS!G59,지분법및기타!$F:$F) -> 0 | W59: =SUMIF(지분법및기타!$G:$G,BS!G59,지분법및기타!$I:$I) -> 0 | X59: =U59+V59-W59 -> -1221588823 | Y59: 집기비품감가상각누계액 | AA59: =X59-O59 -> -12337975
A60: 4 | E60: 인테리어 | G60: 21900 | H60: =SUMIF(별도정산표!$G:$G,BS!G60,별도정산표!$E:$E) -> 131819200 | I60: =울트라팜_FS!C30+울트라팜_FS!C34 -> 0 | J60: =SUMIF(HK_BS!$A:$A,BS!G60,HK_BS!$K:$K) -> 9910105 | K60: =SUMIF(DHK_BS!$A:$A,BS!G60,DHK_BS!$K:$K) -> 409212118 | L60: =SUMIF(상해_BS!$A:$A,BS!G60,상해_BS!$K:$K) -> 0 | M60: =SUMIF(SG_BS!$A:$A,BS!G60,SG_BS!$K:$K) -> 0 | N60: =SUMIF(ATGC_BS!$H:$H,BS!G60,ATGC_BS!$I:$I) -> 0 | O60: =SUM(H60:N60) -> 550941423 | P60: =SUMIF(RIC!D:D,BS!G60,RIC!F:F) -> 0 | Q60: =SUMIF(RIC!G:G,BS!G60,RIC!I:I) -> 0 | R60: =O60+P60-Q60 -> 550941423 | S60: =SUMIF(RIT!H:H,BS!G60,RIT!J:J) -> 0 | T60: =SUMIF(RIT!K:K,BS!G60,RIT!M:M) -> 0 | U60: =R60+S60-T60 -> 550941423 | V60: =SUMIF(지분법및기타!$D:$D,BS!G60,지분법및기타!$F:$F) -> 0 | W60: =SUMIF(지분법및기타!$G:$G,BS!G60,지분법및기타!$I:$I) -> 0 | X60: =U60+V60-W60 -> 550941423 | Y60: 인테리어 | AA60: =X60-O60 -> 0
A61: 4 | E61: 감가상각누계액인테리어 | G61: 22000 | H61: =SUMIF(별도정산표!$G:$G,BS!G61,별도정산표!$E:$E) -> -131811200 | I61: =-(울트라팜_FS!C31+울트라팜_FS!C35) -> 0 | J61: =SUMIF(HK_BS!$A:$A,BS!G61,HK_BS!$K:$K) -> -5767922 | K61: =SUMIF(DHK_BS!$A:$A,BS!G61,DHK_BS!$K:$K) -> -211823035 | L61: =SUMIF(상해_BS!$A:$A,BS!G61,상해_BS!$K:$K) -> 0 | M61: =SUMIF(SG_BS!$A:$A,BS!G61,SG_BS!$K:$K) -> 0 | N61: =SUMIF(ATGC_BS!$H:$H,BS!G61,ATGC_BS!$I:$I) -> 0 | O61: =SUM(H61:N61) -> -349402157 | P61: =SUMIF(RIC!D:D,BS!G61,RIC!F:F) -> 0 | Q61: =SUMIF(RIC!G:G,BS!G61,RIC!I:I) -> 0 | R61: =O61+P61-Q61 -> -349402157 | S61: =SUMIF(RIT!H:H,BS!G61,RIT!J:J) -> 0 | T61: =SUMIF(RIT!K:K,BS!G61,RIT!M:M) -> 0 | U61: =R61+S61-T61 -> -349402157 | V61: =SUMIF(지분법및기타!$D:$D,BS!G61,지분법및기타!$F:$F) -> 0 | W61: =SUMIF(지분법및기타!$G:$G,BS!G61,지분법및기타!$I:$I) -> 0 | X61: =U61+V61-W61 -> -349402157 | Y61: 인테리어감가상각누계액 | AA61: =X61-O61 -> 0
E62: 시설장치 | G62: 22100 | H62: =SUMIF(별도정산표!$G:$G,BS!G62,별도정산표!$E:$E) -> 972487904 | J62: =SUMIF(HK_BS!$A:$A,BS!G62,HK_BS!$K:$K) -> 0 | K62: =SUMIF(DHK_BS!$A:$A,BS!G62,DHK_BS!$K:$K) -> 0 | L62: =SUMIF(상해_BS!$A:$A,BS!G62,상해_BS!$K:$K) -> 0 | M62: =SUMIF(SG_BS!$A:$A,BS!G62,SG_BS!$K:$K) -> 0 | N62: =SUMIF(ATGC_BS!$H:$H,BS!G62,ATGC_BS!$I:$I) -> 661480300 | O62: =SUM(H62:N62) -> 1633968204 | R62: =O62+P62-Q62 -> 1633968204 | S62: =SUMIF(RIT!H:H,BS!G62,RIT!J:J) -> 0 | T62: =SUMIF(RIT!K:K,BS!G62,RIT!M:M) -> 0 | U62: =R62+S62-T62 -> 1633968204 | V62: =SUMIF(지분법및기타!$D:$D,BS!G62,지분법및기타!$F:$F) -> 0 | W62: =SUMIF(지분법및기타!$G:$G,BS!G62,지분법및기타!$I:$I) -> 0 | X62: =U62+V62-W62 -> 1633968204 | Y62: 시설장치
E63: 감가상각누계액 | G63: 22200 | H63: =SUMIF(별도정산표!$G:$G,BS!G63,별도정산표!$E:$E) -> -169400862 | J63: =SUMIF(HK_BS!$A:$A,BS!G63,HK_BS!$K:$K) -> 0 | K63: =SUMIF(DHK_BS!$A:$A,BS!G63,DHK_BS!$K:$K) -> 0 | L63: =SUMIF(상해_BS!$A:$A,BS!G63,상해_BS!$K:$K) -> 0 | M63: =SUMIF(SG_BS!$A:$A,BS!G63,SG_BS!$K:$K) -> 0 | N63: =SUMIF(ATGC_BS!$H:$H,BS!G63,ATGC_BS!$I:$I) -> -628405785 | O63: =SUM(H63:N63) -> -797806647 | R63: =O63+P63-Q63 -> -797806647 | S63: =SUMIF(RIT!H:H,BS!G63,RIT!J:J) -> 0 | T63: =SUMIF(RIT!K:K,BS!G63,RIT!M:M) -> 0 | U63: =R63+S63-T63 -> -797806647 | V63: =SUMIF(지분법및기타!$D:$D,BS!G63,지분법및기타!$F:$F) -> 0 | W63: =SUMIF(지분법및기타!$G:$G,BS!G63,지분법및기타!$I:$I) -> 0 | X63: =U63+V63-W63 -> -797806647 | Y63: 시설장치감가상각누계액
A64: 4 | E64: 사용권자산 | G64: 22300 | H64: =SUMIF(별도정산표!$G:$G,BS!G64,별도정산표!$E:$E) -> 1731999794 | I64: =울트라팜_FS!C32 -> 0 | J64: =SUMIF(HK_BS!$A:$A,BS!G64,HK_BS!$K:$K) -> 0 | K64: =SUMIF(DHK_BS!$A:$A,BS!G64,DHK_BS!$K:$K) -> 0 | L64: =SUMIF(상해_BS!$A:$A,BS!G64,상해_BS!$K:$K) -> 0 | M64: =SUMIF(SG_BS!$A:$A,BS!G64,SG_BS!$K:$K) -> 0 | N64: =SUMIF(ATGC_BS!$H:$H,BS!G64,ATGC_BS!$I:$I) -> 3117259299 | O64: =SUM(H64:N64) -> 4849259093 | P64: =SUMIF(RIC!D:D,BS!G64,RIC!F:F) -> 0 | Q64: =SUMIF(RIC!G:G,BS!G64,RIC!I:I) -> 0 | R64: =O64+P64-Q64 -> 4849259093 | S64: =SUMIF(RIT!H:H,BS!G64,RIT!J:J) -> 0 | T64: =SUMIF(RIT!K:K,BS!G64,RIT!M:M) -> 0 | U64: =R64+S64-T64 -> 4849259093 | V64: =SUMIF(지분법및기타!$D:$D,BS!G64,지분법및기타!$F:$F) -> 0 | W64: =SUMIF(지분법및기타!$G:$G,BS!G64,지분법및기타!$I:$I) -> 0 | X64: =U64+V64-W64 -> 4849259093 | Y64: 사용권자산 | AA64: =X64-O64 -> 0
A65: 4 | E65: 감가상각누계액사용권자산 | G65: 22400 | H65: =SUMIF(별도정산표!$G:$G,BS!G65,별도정산표!$E:$E) -> -370585998 | I65: =-울트라팜_FS!C33 -> 0 | J65: =SUMIF(HK_BS!$A:$A,BS!G65,HK_BS!$K:$K) -> 0 | K65: =SUMIF(DHK_BS!$A:$A,BS!G65,DHK_BS!$K:$K) -> 0 | L65: =SUMIF(상해_BS!$A:$A,BS!G65,상해_BS!$K:$K) -> 0 | M65: =SUMIF(SG_BS!$A:$A,BS!G65,SG_BS!$K:$K) -> 0 | N65: =SUMIF(ATGC_BS!$H:$H,BS!G65,ATGC_BS!$I:$I) -> -2160089439 | O65: =SUM(H65:N65) -> -2530675437 | P65: =SUMIF(RIC!D:D,BS!G65,RIC!F:F) -> 0 | Q65: =SUMIF(RIC!G:G,BS!G65,RIC!I:I) -> 0 | R65: =O65+P65-Q65 -> -2530675437 | S65: =SUMIF(RIT!H:H,BS!G65,RIT!J:J) -> 0 | T65: =SUMIF(RIT!K:K,BS!G65,RIT!M:M) -> 0 | U65: =R65+S65-T65 -> -2530675437 | V65: =SUMIF(지분법및기타!$D:$D,BS!G65,지분법및기타!$F:$F) -> 0 | W65: =SUMIF(지분법및기타!$G:$G,BS!G65,지분법및기타!$I:$I) -> 0 | X65: =U65+V65-W65 -> -2530675437 | Y65: 사용권자산상각누계액 | AA65: =X65-O65 -> 0
A66: 4 | E66: 건설중인자산 | G66: 21400 | H66: =SUMIF(별도정산표!$G:$G,BS!G66,별도정산표!$E:$E) -> 1376213175 | I66: =SUMIF(울트라팜_FS!$A:$A,BS!G66,울트라팜_FS!$D:$D) -> 0 | J66: =SUMIF(HK_BS!$A:$A,BS!G66,HK_BS!$K:$K) -> 0 | K66: =SUMIF(DHK_BS!$A:$A,BS!G66,DHK_BS!$K:$K) -> 0 | L66: =SUMIF(상해_BS!$A:$A,BS!G66,상해_BS!$K:$K) -> 0 | M66: =SUMIF(SG_BS!$A:$A,BS!G66,SG_BS!$K:$K) -> 0 | N66: =SUMIF(ATGC_BS!$H:$H,BS!G66,ATGC_BS!$I:$I) -> 0 | O66: =SUM(H66:N66) -> 1376213175 | P66: =SUMIF(RIC!D:D,BS!G66,RIC!F:F) -> 0 | Q66: =SUMIF(RIC!G:G,BS!G66,RIC!I:I) -> 0 | R66: =O66+P66-Q66 -> 1376213175 | S66: =SUMIF(RIT!H:H,BS!G66,RIT!J:J) -> 0 | T66: =SUMIF(RIT!K:K,BS!G66,RIT!M:M) -> 0 | U66: =R66+S66-T66 -> 1376213175 | V66: =SUMIF(지분법및기타!$D:$D,BS!G66,지분법및기타!$F:$F) -> 0 | W66: =SUMIF(지분법및기타!$G:$G,BS!G66,지분법및기타!$I:$I) -> 0 | X66: =U66+V66-W66 -> 1376213175 | Y66: 건설중인자산 | AA66: =X66-O66 -> 0
A67: 4 | E67: 미사용 | H67: =SUMIF(별도정산표!$G:$G,BS!G67,별도정산표!$E:$E) -> 0 | I67: =SUMIF(울트라팜_FS!$A:$A,BS!G67,울트라팜_FS!$D:$D) -> 0 | J67: =SUMIF(HK_BS!$A:$A,BS!G67,HK_BS!$K:$K) -> 0 | K67: =SUMIF(DHK_BS!$A:$A,BS!G67,DHK_BS!$K:$K) -> 0 | L67: =SUMIF(상해_BS!$A:$A,BS!G67,상해_BS!$K:$K) -> 0 | M67: =SUMIF(SG_BS!$A:$A,BS!G67,SG_BS!$K:$K) -> 0 | N67: =SUMIF(ATGC_BS!$H:$H,BS!G67,ATGC_BS!$I:$I) -> 0 | O67: =SUM(H67:N67) -> 0 | P67: =SUMIF(RIC!D:D,BS!G67,RIC!F:F) -> 0 | Q67: =SUMIF(RIC!G:G,BS!G67,RIC!I:I) -> 0 | R67: =O67+P67-Q67 -> 0 | S67: =SUMIF(RIT!H:H,BS!G67,RIT!J:J) -> 0 | T67: =SUMIF(RIT!K:K,BS!G67,RIT!M:M) -> 0 | U67: =R67+S67-T67 -> 0 | V67: =SUMIF(지분법및기타!$D:$D,BS!G67,지분법및기타!$F:$F) -> 0 | W67: =SUMIF(지분법및기타!$G:$G,BS!G67,지분법및기타!$I:$I) -> 0 | X67: =U67+V67-W67 -> 0
A68: 3 | D68: 무형자산 | H68: =SUM(H69:H76) -> 124722122 | I68: =SUM(I69:I76) -> 0 | J68: =SUM(J69:J76) -> 0 | K68: =SUM(K69:K76) -> 0 | L68: =SUM(L69:L76) -> 0 | M68: =SUM(M69:M76) -> 0 | N68: =SUM(N69:N76) -> 5744689888 | O68: =SUM(O69:O76) -> 5869412010 | R68: =SUM(R69:R76) -> 33200055369 | U68: =SUM(U69:U76) -> 33200055369 | V68: =SUMIF(지분법및기타!$D:$D,BS!G68,지분법및기타!$F:$F) -> 0 | W68: =SUMIF(지분법및기타!$G:$G,BS!G68,지분법및기타!$I:$I) -> 0 | X68: =SUM(X69:X76) -> 33200055369 | AA68: =X68-O68 -> 27330643359
A69: 4 | E69: 특허권 | G69: 23200 | H69: =SUMIF(별도정산표!$G:$G,BS!G69,별도정산표!$E:$E) -> 49108768 | I69: =SUMIF(울트라팜_FS!$A:$A,BS!G69,울트라팜_FS!$D:$D) -> 0 | J69: =SUMIF(HK_BS!$A:$A,BS!G69,HK_BS!$K:$K) -> 0 | K69: =SUMIF(DHK_BS!$A:$A,BS!G69,DHK_BS!$K:$K) -> 0 | L69: =SUMIF(상해_BS!$A:$A,BS!G69,상해_BS!$K:$K) -> 0 | M69: =SUMIF(SG_BS!$A:$A,BS!G69,SG_BS!$K:$K) -> 0 | N69: =SUMIF(ATGC_BS!$H:$H,BS!G69,ATGC_BS!$I:$I) -> 10409738 | O69: =SUM(H69:N69) -> 59518506 | P69: =SUMIF(RIC!D:D,BS!G69,RIC!F:F) -> 4653260562 | Q69: =SUMIF(RIC!G:G,BS!G69,RIC!I:I) -> 0 | R69: =O69+P69-Q69 -> 4712779068 | S69: =SUMIF(RIT!H:H,BS!G69,RIT!J:J) -> 0 | T69: =SUMIF(RIT!K:K,BS!G69,RIT!M:M) -> 0 | U69: =R69+S69-T69 -> 4712779068 | V69: =SUMIF(지분법및기타!$D:$D,BS!G69,지분법및기타!$F:$F) -> 0 | W69: =SUMIF(지분법및기타!$G:$G,BS!G69,지분법및기타!$I:$I) -> 0 | X69: =U69+V69-W69 -> 4712779068 | Y69: 특허권 | AA69: =X69-O69 -> 4653260562
A70: 4 | E70: 상표권 | G70: 23300 | H70: =SUMIF(별도정산표!$G:$G,BS!G70,별도정산표!$E:$E) -> 23719703 | I70: =SUMIF(울트라팜_FS!$A:$A,BS!G70,울트라팜_FS!$D:$D) -> 0 | J70: =SUMIF(HK_BS!$A:$A,BS!G70,HK_BS!$K:$K) -> 0 | K70: =SUMIF(DHK_BS!$A:$A,BS!G70,DHK_BS!$K:$K) -> 0 | L70: =SUMIF(상해_BS!$A:$A,BS!G70,상해_BS!$K:$K) -> 0 | M70: =SUMIF(SG_BS!$A:$A,BS!G70,SG_BS!$K:$K) -> 0 | N70: =SUMIF(ATGC_BS!$H:$H,BS!G70,ATGC_BS!$I:$I) -> 0 | O70: =SUM(H70:N70) -> 23719703 | P70: =SUMIF(RIC!D:D,BS!G70,RIC!F:F) -> 384243995 | Q70: =SUMIF(RIC!G:G,BS!G70,RIC!I:I) -> 0 | R70: =O70+P70-Q70 -> 407963698 | S70: =SUMIF(RIT!H:H,BS!G70,RIT!J:J) -> 0 | T70: =SUMIF(RIT!K:K,BS!G70,RIT!M:M) -> 0 | U70: =R70+S70-T70 -> 407963698 | V70: =SUMIF(지분법및기타!$D:$D,BS!G70,지분법및기타!$F:$F) -> 0 | W70: =SUMIF(지분법및기타!$G:$G,BS!G70,지분법및기타!$I:$I) -> 0 | X70: =U70+V70-W70 -> 407963698 | Y70: 상표권 | AA70: =X70-O70 -> 384243995
A71: 4 | E71: 개발비 | G71: 23900 | H71: =SUMIF(별도정산표!$G:$G,BS!G71,별도정산표!$E:$E) -> 0 | I71: =SUMIF(울트라팜_FS!$A:$A,BS!G71,울트라팜_FS!$D:$D) -> 0 | J71: =SUMIF(HK_BS!$A:$A,BS!G71,HK_BS!$K:$K) -> 0 | K71: =SUMIF(DHK_BS!$A:$A,BS!G71,DHK_BS!$K:$K) -> 0 | L71: =SUMIF(상해_BS!$A:$A,BS!G71,상해_BS!$K:$K) -> 0 | M71: =SUMIF(SG_BS!$A:$A,BS!G71,SG_BS!$K:$K) -> 0 | N71: =SUMIF(ATGC_BS!$H:$H,BS!G71,ATGC_BS!$I:$I) -> 5628405039 | O71: =SUM(H71:N71) -> 5628405039 | P71: =SUMIF(RIC!D:D,BS!G71,RIC!F:F) -> 0 | Q71: =SUMIF(RIC!G:G,BS!G71,RIC!I:I) -> 0 | R71: =O71+P71-Q71 -> 5628405039 | S71: =SUMIF(RIT!H:H,BS!G71,RIT!J:J) -> 0 | T71: =SUMIF(RIT!K:K,BS!G71,RIT!M:M) -> 0 | U71: =R71+S71-T71 -> 5628405039 | V71: =SUMIF(지분법및기타!$D:$D,BS!G71,지분법및기타!$F:$F) -> 0 | W71: =SUMIF(지분법및기타!$G:$G,BS!G71,지분법및기타!$I:$I) -> 0 | X71: =U71+V71-W71 -> 5628405039 | Y71: 개발비 | AA71: =X71-O71 -> 0
A72: 4 | E72: 소프트웨어 | G72: 24000 | H72: =SUMIF(별도정산표!$G:$G,BS!G72,별도정산표!$E:$E) -> 51893651 | I72: =SUMIF(울트라팜_FS!$A:$A,BS!G72,울트라팜_FS!$D:$D) -> 0 | J72: =SUMIF(HK_BS!$A:$A,BS!G72,HK_BS!$K:$K) -> 0 | K72: =SUMIF(DHK_BS!$A:$A,BS!G72,DHK_BS!$K:$K) -> 0 | L72: =SUMIF(상해_BS!$A:$A,BS!G72,상해_BS!$K:$K) -> 0 | M72: =SUMIF(SG_BS!$A:$A,BS!G72,SG_BS!$K:$K) -> 0 | N72: =SUMIF(ATGC_BS!$H:$H,BS!G72,ATGC_BS!$I:$I) -> 21223133 | O72: =SUM(H72:N72) -> 73116784 | P72: =SUMIF(RIC!D:D,BS!G72,RIC!F:F) -> 0 | Q72: =SUMIF(RIC!G:G,BS!G72,RIC!I:I) -> 0 | R72: =O72+P72-Q72 -> 73116784 | S72: =SUMIF(RIT!H:H,BS!G72,RIT!J:J) -> 0 | T72: =SUMIF(RIT!K:K,BS!G72,RIT!M:M) -> 0 | U72: =R72+S72-T72 -> 73116784 | V72: =SUMIF(지분법및기타!$D:$D,BS!G72,지분법및기타!$F:$F) -> 0 | W72: =SUMIF(지분법및기타!$G:$G,BS!G72,지분법및기타!$I:$I) -> 0 | X72: =U72+V72-W72 -> 73116784 | Y72: 소프트웨어 | AA72: =X72-O72 -> 0
A73: 4 | E73: 영업권 | G73: 23400 | H73: =SUMIF(별도정산표!$G:$G,BS!G73,별도정산표!$E:$E) -> 0 | I73: =SUMIF(울트라팜_FS!$A:$A,BS!G73,울트라팜_FS!$D:$D) -> 0 | J73: =SUMIF(HK_BS!$A:$A,BS!G73,HK_BS!$K:$K) -> 0 | K73: =SUMIF(DHK_BS!$A:$A,BS!G73,DHK_BS!$K:$K) -> 0 | L73: =SUMIF(상해_BS!$A:$A,BS!G73,상해_BS!$K:$K) -> 0 | M73: =SUMIF(SG_BS!$A:$A,BS!G73,SG_BS!$K:$K) -> 0 | N73: =SUMIF(ATGC_BS!$H:$H,BS!G73,ATGC_BS!$I:$I) -> 0 | O73: =SUM(H73:N73) -> 0 | P73: =SUMIF(RIC!D:D,BS!G73,RIC!F:F) -> 16195983360 | Q73: =SUMIF(RIC!G:G,BS!G73,RIC!I:I) -> 0 | R73: =O73+P73-Q73 -> 16195983360 | S73: =SUMIF(RIT!H:H,BS!G73,RIT!J:J) -> 0 | T73: =SUMIF(RIT!K:K,BS!G73,RIT!M:M) -> 0 | U73: =R73+S73-T73 -> 16195983360 | V73: =SUMIF(지분법및기타!$D:$D,BS!G73,지분법및기타!$F:$F) -> 0 | W73: =SUMIF(지분법및기타!$G:$G,BS!G73,지분법및기타!$I:$I) -> 0 | X73: =U73+V73-W73 -> 16195983360 | Y73: 영업권
E74: 시설이용권 | G74: 23500 | H74: =SUMIF(별도정산표!$G:$G,BS!G74,별도정산표!$E:$E) -> 0 | I74: =SUMIF(울트라팜_FS!$A:$A,BS!G74,울트라팜_FS!$D:$D) -> 0 | J74: =SUMIF(HK_BS!$A:$A,BS!G74,HK_BS!$K:$K) -> 0 | K74: =SUMIF(DHK_BS!$A:$A,BS!G74,DHK_BS!$K:$K) -> 0 | L74: =SUMIF(상해_BS!$A:$A,BS!G74,상해_BS!$K:$K) -> 0 | M74: =SUMIF(SG_BS!$A:$A,BS!G74,SG_BS!$K:$K) -> 0 | N74: =SUMIF(ATGC_BS!$H:$H,BS!G74,ATGC_BS!$I:$I) -> 46357920 | O74: =SUM(H74:N74) -> 46357920 | P74: =SUMIF(RIC!D:D,BS!G74,RIC!F:F) -> 0 | Q74: =SUMIF(RIC!G:G,BS!G74,RIC!I:I) -> 0 | R74: =O74+P74-Q74 -> 46357920 | S74: =SUMIF(RIT!H:H,BS!G74,RIT!J:J) -> 0 | T74: =SUMIF(RIT!K:K,BS!G74,RIT!M:M) -> 0 | U74: =R74+S74-T74 -> 46357920 | V74: =SUMIF(지분법및기타!$D:$D,BS!G74,지분법및기타!$F:$F) -> 0 | W74: =SUMIF(지분법및기타!$G:$G,BS!G74,지분법및기타!$I:$I) -> 0 | X74: =U74+V74-W74 -> 46357920 | Y74: 시설이용권
E75: 건설중인자산(무형) | G75: 23600 | H75: =SUMIF(별도정산표!$G:$G,BS!G75,별도정산표!$E:$E) -> 0 | I75: =SUMIF(울트라팜_FS!$A:$A,BS!G75,울트라팜_FS!$D:$D) -> 0 | J75: =SUMIF(HK_BS!$A:$A,BS!G75,HK_BS!$K:$K) -> 0 | K75: =SUMIF(DHK_BS!$A:$A,BS!G75,DHK_BS!$K:$K) -> 0 | L75: =SUMIF(상해_BS!$A:$A,BS!G75,상해_BS!$K:$K) -> 0 | M75: =SUMIF(SG_BS!$A:$A,BS!G75,SG_BS!$K:$K) -> 0 | N75: =SUMIF(ATGC_BS!$H:$H,BS!G75,ATGC_BS!$I:$I) -> 38294058 | O75: =SUM(H75:N75) -> 38294058 | P75: =SUMIF(RIC!D:D,BS!G75,RIC!F:F) -> 0 | Q75: =SUMIF(RIC!G:G,BS!G75,RIC!I:I) -> 0 | R75: =O75+P75-Q75 -> 38294058 | S75: =SUMIF(RIT!H:H,BS!G75,RIT!J:J) -> 0 | T75: =SUMIF(RIT!K:K,BS!G75,RIT!M:M) -> 0 | U75: =R75+S75-T75 -> 38294058 | V75: =SUMIF(지분법및기타!$D:$D,BS!G75,지분법및기타!$F:$F) -> 0 | W75: =SUMIF(지분법및기타!$G:$G,BS!G75,지분법및기타!$I:$I) -> 0 | X75: =U75+V75-W75 -> 38294058 | Y75: 건설중인자산(무형)
E76: 기타의무형자산 | G76: 23700 | H76: =SUMIF(별도정산표!$G:$G,BS!G76,별도정산표!$E:$E) -> 0 | I76: =SUMIF(울트라팜_FS!$A:$A,BS!G76,울트라팜_FS!$D:$D) -> 0 | J76: =SUMIF(HK_BS!$A:$A,BS!G76,HK_BS!$K:$K) -> 0 | K76: =SUMIF(DHK_BS!$A:$A,BS!G76,DHK_BS!$K:$K) -> 0 | L76: =SUMIF(상해_BS!$A:$A,BS!G76,상해_BS!$K:$K) -> 0 | M76: =SUMIF(SG_BS!$A:$A,BS!G76,SG_BS!$K:$K) -> 0 | N76: =SUMIF(ATGC_BS!$H:$H,BS!G76,ATGC_BS!$I:$I) -> 0 | O76: =SUM(H76:N76) -> 0 | P76: =SUMIF(RIC!D:D,BS!G76,RIC!F:F) -> 6097155442 | Q76: =SUMIF(RIC!G:G,BS!G76,RIC!I:I) -> 0 | R76: =O76+P76-Q76 -> 6097155442 | S76: =SUMIF(RIT!H:H,BS!G76,RIT!J:J) -> 0 | T76: =SUMIF(RIT!K:K,BS!G76,RIT!M:M) -> 0 | U76: =R76+S76-T76 -> 6097155442 | V76: =SUMIF(지분법및기타!$D:$D,BS!G76,지분법및기타!$F:$F) -> 0 | W76: =SUMIF(지분법및기타!$G:$G,BS!G76,지분법및기타!$I:$I) -> 0 | X76: =U76+V76-W76 -> 6097155442 | Y76: 기타의무형자산
A77: 3 | D77: 기타의비유동자산 | H77: =+SUM(H78:H83) -> 2941187347 | I77: =+SUM(I78:I83) -> 0 | J77: =+SUM(J78:J83) -> 0 | K77: =+SUM(K78:K83) -> 0 | L77: =+SUM(L78:L83) -> 0 | M77: =+SUM(M78:M83) -> 0 | N77: =+SUM(N78:N83) -> 795832416 | O77: =+SUM(O78:O83) -> 3737019763 | R77: =+SUM(R78:R83) -> 3737019763 | U77: =+SUM(U78:U83) -> 3737019763 | V77: =SUMIF(지분법및기타!$D:$D,BS!G77,지분법및기타!$F:$F) -> 0 | W77: =SUMIF(지분법및기타!$G:$G,BS!G77,지분법및기타!$I:$I) -> 0 | X77: =+SUM(X78:X83) -> 3737019763 | AA77: =X77-O77 -> 0
A78: 4 | E78: 임차보증금 | G78: 18800 | H78: =SUMIF(별도정산표!$G:$G,BS!G78,별도정산표!$E:$E) -> 403800000 | I78: =SUMIF(울트라팜_FS!$A:$A,BS!G78,울트라팜_FS!$D:$D) -> 0 | J78: =SUMIF(HK_BS!$A:$A,BS!G78,HK_BS!$K:$K) -> 0 | K78: =SUMIF(DHK_BS!$A:$A,BS!G78,DHK_BS!$K:$K) -> 0 | L78: =SUMIF(상해_BS!$A:$A,BS!G78,상해_BS!$K:$K) -> 0 | M78: =SUMIF(SG_BS!$A:$A,BS!G78,SG_BS!$K:$K) -> 0 | N78: =SUMIF(ATGC_BS!$H:$H,BS!G78,ATGC_BS!$I:$I) -> 400000000 | O78: =SUM(H78:N78) -> 803800000 | P78: =SUMIF(RIC!D:D,BS!G78,RIC!F:F) -> 0 | Q78: =SUMIF(RIC!G:G,BS!G78,RIC!I:I) -> 0 | R78: =O78+P78-Q78 -> 803800000 | S78: =SUMIF(RIT!H:H,BS!G78,RIT!J:J) -> 0 | T78: =SUMIF(RIT!K:K,BS!G78,RIT!M:M) -> 0 | U78: =R78+S78-T78 -> 803800000 | V78: =SUMIF(지분법및기타!$D:$D,BS!G78,지분법및기타!$F:$F) -> 0 | W78: =SUMIF(지분법및기타!$G:$G,BS!G78,지분법및기타!$I:$I) -> 0 | X78: =U78+V78-W78 -> 803800000 | Y78: 임차보증금 | AA78: =X78-O78 -> 0
A79: 4 | E79: 기타보증금 | G79: 19000 | H79: =SUMIF(별도정산표!$G:$G,BS!G79,별도정산표!$E:$E) -> 10135870 | I79: =SUMIF(울트라팜_FS!$A:$A,BS!G79,울트라팜_FS!$D:$D) -> 0 | J79: =SUMIF(HK_BS!$A:$A,BS!G79,HK_BS!$K:$K) -> 0 | K79: =SUMIF(DHK_BS!$A:$A,BS!G79,DHK_BS!$K:$K) -> 0 | L79: =SUMIF(상해_BS!$A:$A,BS!G79,상해_BS!$K:$K) -> 0 | M79: =SUMIF(SG_BS!$A:$A,BS!G79,SG_BS!$K:$K) -> 0 | N79: =SUMIF(ATGC_BS!$H:$H,BS!G79,ATGC_BS!$I:$I) -> 9725000 | O79: =SUM(H79:N79) -> 19860870 | P79: =SUMIF(RIC!D:D,BS!G79,RIC!F:F) -> 0 | Q79: =SUMIF(RIC!G:G,BS!G79,RIC!I:I) -> 0 | R79: =O79+P79-Q79 -> 19860870 | S79: =SUMIF(RIT!H:H,BS!G79,RIT!J:J) -> 0 | T79: =SUMIF(RIT!K:K,BS!G79,RIT!M:M) -> 0 | U79: =R79+S79-T79 -> 19860870 | V79: =SUMIF(지분법및기타!$D:$D,BS!G79,지분법및기타!$F:$F) -> 0 | W79: =SUMIF(지분법및기타!$G:$G,BS!G79,지분법및기타!$I:$I) -> 0 | X79: =U79+V79-W79 -> 19860870 | Y79: 기타보증금 | AA79: =X79-O79 -> 0
E80: 기타보증금_현재가치할인차금 | G80: 19100 | H80: =SUMIF(별도정산표!$G:$G,BS!G80,별도정산표!$E:$E) -> 0 | I80: =SUMIF(울트라팜_FS!$A:$A,BS!G80,울트라팜_FS!$D:$D) -> 0 | J80: =SUMIF(HK_BS!$A:$A,BS!G80,HK_BS!$K:$K) -> 0 | K80: =SUMIF(DHK_BS!$A:$A,BS!G80,DHK_BS!$K:$K) -> 0 | L80: =SUMIF(상해_BS!$A:$A,BS!G80,상해_BS!$K:$K) -> 0 | M80: =SUMIF(SG_BS!$A:$A,BS!G80,SG_BS!$K:$K) -> 0 | N80: =SUMIF(ATGC_BS!$H:$H,BS!G80,ATGC_BS!$I:$I) -> -1736084 | O80: =SUM(H80:N80) -> -1736084 | P80: =SUMIF(RIC!D:D,BS!G80,RIC!F:F) -> 0 | Q80: =SUMIF(RIC!G:G,BS!G80,RIC!I:I) -> 0 | R80: =O80+P80-Q80 -> -1736084 | S80: =SUMIF(RIT!H:H,BS!G80,RIT!J:J) -> 0 | T80: =SUMIF(RIT!K:K,BS!G80,RIT!M:M) -> 0 | U80: =R80+S80-T80 -> -1736084 | V80: =SUMIF(지분법및기타!$D:$D,BS!G80,지분법및기타!$F:$F) -> 0 | W80: =SUMIF(지분법및기타!$G:$G,BS!G80,지분법및기타!$I:$I) -> 0 | X80: =U80+V80-W80 -> -1736084 | Y80: 기타보증금
E81: 장기선급비용 | G81: 19200 | H81: =SUMIF(별도정산표!$G:$G,BS!G81,별도정산표!$E:$E) -> 0 | I81: =SUMIF(울트라팜_FS!$A:$A,BS!G81,울트라팜_FS!$D:$D) -> 0 | J81: =SUMIF(HK_BS!$A:$A,BS!G81,HK_BS!$K:$K) -> 0 | K81: =SUMIF(DHK_BS!$A:$A,BS!G81,DHK_BS!$K:$K) -> 0 | L81: =SUMIF(상해_BS!$A:$A,BS!G81,상해_BS!$K:$K) -> 0 | M81: =SUMIF(SG_BS!$A:$A,BS!G81,SG_BS!$K:$K) -> 0 | N81: =SUMIF(ATGC_BS!$H:$H,BS!G81,ATGC_BS!$I:$I) -> 466873197 | O81: =SUM(H81:N81) -> 466873197 | P81: =SUMIF(RIC!D:D,BS!G81,RIC!F:F) -> 0 | Q81: =SUMIF(RIC!G:G,BS!G81,RIC!I:I) -> 0 | R81: =O81+P81-Q81 -> 466873197 | S81: =SUMIF(RIT!H:H,BS!G81,RIT!J:J) -> 0 | T81: =SUMIF(RIT!K:K,BS!G81,RIT!M:M) -> 0 | U81: =R81+S81-T81 -> 466873197 | V81: =SUMIF(지분법및기타!$D:$D,BS!G81,지분법및기타!$F:$F) -> 0 | W81: =SUMIF(지분법및기타!$G:$G,BS!G81,지분법및기타!$I:$I) -> 0 | X81: =U81+V81-W81 -> 466873197 | Y81: 장기선급비용
A82: 4 | E82: 이연법인세자산 | G82: 19600 | H82: =SUMIF(별도정산표!$G:$G,BS!G82,별도정산표!$E:$E) -> 2555104971 | I82: =SUMIF(울트라팜_FS!$A:$A,BS!G82,울트라팜_FS!$D:$D) -> 0 | J82: =SUMIF(HK_BS!$A:$A,BS!G82,HK_BS!$K:$K) -> 0 | K82: =SUMIF(DHK_BS!$A:$A,BS!G82,DHK_BS!$K:$K) -> 0 | L82: =SUMIF(상해_BS!$A:$A,BS!G82,상해_BS!$K:$K) -> 0 | M82: =SUMIF(SG_BS!$A:$A,BS!G82,SG_BS!$K:$K) -> 0 | N82: =SUMIF(ATGC_BS!$H:$H,BS!G82,ATGC_BS!$I:$I) -> 0 | O82: =SUM(H82:N82) -> 2555104971 | P82: =SUMIF(RIC!D:D,BS!G82,RIC!F:F) -> 0 | Q82: =SUMIF(RIC!G:G,BS!G82,RIC!I:I) -> 0 | R82: =O82+P82-Q82 -> 2555104971 | S82: =SUMIF(RIT!H:H,BS!G82,RIT!J:J) -> 0 | T82: =SUMIF(RIT!K:K,BS!G82,RIT!M:M) -> 0 | U82: =R82+S82-T82 -> 2555104971 | V82: =SUMIF(지분법및기타!$D:$D,BS!G82,지분법및기타!$F:$F) -> 0 | W82: =SUMIF(지분법및기타!$G:$G,BS!G82,지분법및기타!$I:$I) -> 0 | X82: =U82+V82-W82 -> 2555104971 | Y82: 이연법인세자산 | AA82: =X82-O82 -> 0
A83: 4 | E83: 임차보증금_현재가치할인차금 | G83: 18900 | H83: =SUMIF(별도정산표!$G:$G,BS!G83,별도정산표!$E:$E) -> -27853494 | I83: =SUMIF(울트라팜_FS!$A:$A,BS!G83,울트라팜_FS!$D:$D) -> 0 | J83: =SUMIF(HK_BS!$A:$A,BS!G83,HK_BS!$K:$K) -> 0 | K83: =SUMIF(DHK_BS!$A:$A,BS!G83,DHK_BS!$K:$K) -> 0 | L83: =SUMIF(상해_BS!$A:$A,BS!G83,상해_BS!$K:$K) -> 0 | M83: =SUMIF(SG_BS!$A:$A,BS!G83,SG_BS!$K:$K) -> 0 | N83: =SUMIF(ATGC_BS!$H:$H,BS!G83,ATGC_BS!$I:$I) -> -79029697 | O83: =SUM(H83:N83) -> -106883191 | P83: =SUMIF(RIC!D:D,BS!G83,RIC!F:F) -> 0 | Q83: =SUMIF(RIC!G:G,BS!G83,RIC!I:I) -> 0 | R83: =O83+P83-Q83 -> -106883191 | S83: =SUMIF(RIT!H:H,BS!G83,RIT!J:J) -> 0 | T83: =SUMIF(RIT!K:K,BS!G83,RIT!M:M) -> 0 | U83: =R83+S83-T83 -> -106883191 | V83: =SUMIF(지분법및기타!$D:$D,BS!G83,지분법및기타!$F:$F) -> 0 | W83: =SUMIF(지분법및기타!$G:$G,BS!G83,지분법및기타!$I:$I) -> 0 | X83: =U83+V83-W83 -> -106883191 | Y83: 임차보증금 | AA83: =X83-O83 -> 0
A84: 3 | D84: 투자부동산 | H84: =H85+H86+H87 -> 0 | I84: =I85+I86+I87 -> 0 | J84: =J85+J86+J87 -> 0 | K84: =K85+K86+K87 -> 0 | L84: =L85+L86+L87 -> 0 | M84: =M85+M86+M87 -> 0 | N84: =N85+N86+N87 -> 0 | O84: =O85+O86+O87 -> 0 | R84: =R85+R86+R87 -> 0 | U84: =U85+U86+U87 -> 0 | V84: =SUMIF(지분법및기타!$D:$D,BS!G84,지분법및기타!$F:$F) -> 0 | W84: =SUMIF(지분법및기타!$G:$G,BS!G84,지분법및기타!$I:$I) -> 0 | X84: =X85+X86+X87 -> 0
A85: 4 | E85: 토지 | H85: =SUMIF(별도정산표!$G:$G,BS!G85,별도정산표!$E:$E) -> 0 | I85: =SUMIF(울트라팜_FS!$A:$A,BS!G85,울트라팜_FS!$D:$D) -> 0 | J85: =SUMIF(HK_BS!$A:$A,BS!G85,HK_BS!$K:$K) -> 0 | K85: =SUMIF(DHK_BS!$A:$A,BS!G85,DHK_BS!$K:$K) -> 0 | L85: =SUMIF(상해_BS!$A:$A,BS!G85,상해_BS!$K:$K) -> 0 | M85: =SUMIF(SG_BS!$A:$A,BS!G85,SG_BS!$K:$K) -> 0 | N85: =SUMIF(ATGC_BS!$H:$H,BS!G85,ATGC_BS!$I:$I) -> 0 | O85: =SUM(H85:N85) -> 0 | P85: =SUMIF(RIC!D:D,BS!G85,RIC!F:F) -> 0 | Q85: =SUMIF(RIC!G:G,BS!G85,RIC!I:I) -> 0 | R85: =O85+P85-Q85 -> 0 | S85: =SUMIF(RIT!H:H,BS!G85,RIT!J:J) -> 0 | T85: =SUMIF(RIT!K:K,BS!G85,RIT!M:M) -> 0 | U85: =R85+S85-T85 -> 0 | V85: =SUMIF(지분법및기타!$D:$D,BS!G85,지분법및기타!$F:$F) -> 0 | W85: =SUMIF(지분법및기타!$G:$G,BS!G85,지분법및기타!$I:$I) -> 0 | X85: =U85+V85-W85 -> 0 | Y85: 투자부동산_토지
A86: 4 | E86: 건물 | H86: =SUMIF(별도정산표!$G:$G,BS!G86,별도정산표!$E:$E) -> 0 | I86: =SUMIF(울트라팜_FS!$A:$A,BS!G86,울트라팜_FS!$D:$D) -> 0 | J86: =SUMIF(HK_BS!$A:$A,BS!G86,HK_BS!$K:$K) -> 0 | K86: =SUMIF(DHK_BS!$A:$A,BS!G86,DHK_BS!$K:$K) -> 0 | L86: =SUMIF(상해_BS!$A:$A,BS!G86,상해_BS!$K:$K) -> 0 | M86: =SUMIF(SG_BS!$A:$A,BS!G86,SG_BS!$K:$K) -> 0 | N86: =SUMIF(ATGC_BS!$H:$H,BS!G86,ATGC_BS!$I:$I) -> 0 | O86: =SUM(H86:N86) -> 0 | P86: =SUMIF(RIC!D:D,BS!G86,RIC!F:F) -> 0 | Q86: =SUMIF(RIC!G:G,BS!G86,RIC!I:I) -> 0 | R86: =O86+P86-Q86 -> 0 | S86: =SUMIF(RIT!H:H,BS!G86,RIT!J:J) -> 0 | T86: =SUMIF(RIT!K:K,BS!G86,RIT!M:M) -> 0 | U86: =R86+S86-T86 -> 0 | V86: =SUMIF(지분법및기타!$D:$D,BS!G86,지분법및기타!$F:$F) -> 0 | W86: =SUMIF(지분법및기타!$G:$G,BS!G86,지분법및기타!$I:$I) -> 0 | X86: =U86+V86-W86 -> 0 | Y86: 투자부동산_건물
A87: 4 | E87: 건물감가상각누계액 | H87: =SUMIF(별도정산표!$G:$G,BS!G87,별도정산표!$E:$E) -> 0 | I87: =SUMIF(울트라팜_FS!$A:$A,BS!G87,울트라팜_FS!$D:$D) -> 0 | J87: =SUMIF(HK_BS!$A:$A,BS!G87,HK_BS!$K:$K) -> 0 | K87: =SUMIF(DHK_BS!$A:$A,BS!G87,DHK_BS!$K:$K) -> 0 | L87: =SUMIF(상해_BS!$A:$A,BS!G87,상해_BS!$K:$K) -> 0 | M87: =SUMIF(SG_BS!$A:$A,BS!G87,SG_BS!$K:$K) -> 0 | N87: =SUMIF(ATGC_BS!$H:$H,BS!G87,ATGC_BS!$I:$I) -> 0 | O87: =SUM(H87:N87) -> 0 | P87: =SUMIF(RIC!D:D,BS!G87,RIC!F:F) -> 0 | Q87: =SUMIF(RIC!G:G,BS!G87,RIC!I:I) -> 0 | R87: =O87+P87-Q87 -> 0 | S87: =SUMIF(RIT!H:H,BS!G87,RIT!J:J) -> 0 | T87: =SUMIF(RIT!K:K,BS!G87,RIT!M:M) -> 0 | U87: =R87+S87-T87 -> 0 | V87: =SUMIF(지분법및기타!$D:$D,BS!G87,지분법및기타!$F:$F) -> 0 | W87: =SUMIF(지분법및기타!$G:$G,BS!G87,지분법및기타!$I:$I) -> 0 | X87: =U87+V87-W87 -> 0 | Y87: 투자부동산_건물상각누계액
A88: 1 | B88: 부채 | H88: =H89+H106 -> 12842260610 | I88: =I89+I106 -> 0 | J88: =J89+J106 -> 516057216 | K88: =K89+K106 -> 1649671107 | L88: =L89+L106 -> 0 | M88: =M89+M106 -> 0 | N88: =N89+N106 -> 10501946093 | O88: =O89+O106 -> 25509935026 | R88: =R89+R106 -> 27959560214 | U88: =U89+U106 -> 25935945638 | V88: =SUMIF(지분법및기타!$D:$D,BS!G88,지분법및기타!$F:$F) -> 0 | W88: =SUMIF(지분법및기타!$G:$G,BS!G88,지분법및기타!$I:$I) -> 0 | X88: =X89+X106 -> 25936495008
A89: 2 | C89: 유동부채 | H89: =H90 -> 7026815912 | I89: =I90 -> 0 | J89: =J90 -> 516057216 | K89: =K90 -> 1649671107 | L89: =L90 -> 0 | M89: =M90 -> 0 | N89: =N90 -> 9388591014 | O89: =O90 -> 18581135249 | R89: =R90 -> 18581135249 | U89: =U90 -> 16544181233 | V89: =SUMIF(지분법및기타!$D:$D,BS!G89,지분법및기타!$F:$F) -> 0 | W89: =SUMIF(지분법및기타!$G:$G,BS!G89,지분법및기타!$I:$I) -> 0 | X89: =X90 -> 16544730603
A90: 3 | D90: 유동부채 | H90: =SUM(H91:H105) -> 7026815912 | I90: =SUM(I91:I105) -> 0 | J90: =SUM(J91:J105) -> 516057216 | K90: =SUM(K91:K105) -> 1649671107 | L90: =SUM(L91:L105) -> 0 | M90: =SUM(M91:M105) -> 0 | N90: =SUM(N91:N105) -> 9388591014 | O90: =SUM(O91:O105) -> 18581135249 | R90: =SUM(R91:R105) -> 18581135249 | U90: =SUM(U91:U105) -> 16544181233 | V90: =SUMIF(지분법및기타!$D:$D,BS!G90,지분법및기타!$F:$F) -> 0 | W90: =SUMIF(지분법및기타!$G:$G,BS!G90,지분법및기타!$I:$I) -> 0 | X90: =X91+X92+X93+X94+X95+X97+X98+X99+X100+X101+X102+X103+X105+X104+X96 -> 16544730603
A91: 4 | E91: 외상매입금 | G91: 25100 | H91: =SUMIF(별도정산표!$G:$G,BS!G91,별도정산표!$E:$E) -> 299203820 | I91: =SUMIF(울트라팜_FS!$A:$A,BS!G91,울트라팜_FS!$D:$D) -> 0 | J91: =SUMIF(HK_BS!$A:$A,BS!G91,HK_BS!$K:$K) -> 396013554 | K91: =SUMIF(DHK_BS!$A:$A,BS!G91,DHK_BS!$K:$K) -> 1640356199 | L91: =SUMIF(상해_BS!$A:$A,BS!G91,상해_BS!$K:$K) -> 0 | M91: =SUMIF(SG_BS!$A:$A,BS!G91,SG_BS!$K:$K) -> 0 | N91: =SUMIF(ATGC_BS!$H:$H,BS!G91,ATGC_BS!$I:$I) -> 0 | O91: =SUM(H91:N91) -> 2335573573 | P91: =SUMIF(RIC!D:D,BS!G91,RIC!F:F) -> 0 | Q91: =SUMIF(RIC!G:G,BS!G91,RIC!I:I) -> 0 | R91: =O91+Q91-P91 -> 2335573573 | S91: =SUMIF(RIT!H:H,BS!G91,RIT!J:J) -> 2036954016 | T91: =SUMIF(RIT!K:K,BS!G91,RIT!M:M) -> 0 | U91: =R91+T91-S91 -> 298619557 | V91: =SUMIF(지분법및기타!$D:$D,BS!G91,지분법및기타!$F:$F) -> 0 | W91: =SUMIF(지분법및기타!$G:$G,BS!G91,지분법및기타!$I:$I) -> 549370 | X91: =U91+W91-V91 -> 299168927 | Y91: 매입채무 | AA91: =X91-O91 -> -2036404646 | AB91: 전액 내부거래 차이
A92: 4 | E92: 미지급금 | G92: 25300 | H92: =SUMIF(별도정산표!$G:$G,BS!G92,별도정산표!$E:$E) -> 207639910 | I92: =SUMIF(울트라팜_FS!$A:$A,BS!G92,울트라팜_FS!$D:$D) -> 0 | J92: =SUMIF(HK_BS!$A:$A,BS!G92,HK_BS!$K:$K) -> 0 | K92: =SUMIF(DHK_BS!$A:$A,BS!G92,DHK_BS!$K:$K) -> 0 | L92: =SUMIF(상해_BS!$A:$A,BS!G92,상해_BS!$K:$K) -> 0 | M92: =SUMIF(SG_BS!$A:$A,BS!G92,SG_BS!$K:$K) -> 0 | N92: =SUMIF(ATGC_BS!$H:$H,BS!G92,ATGC_BS!$I:$I) -> 4135910170 | O92: =SUM(H92:N92) -> 4343550080 | P92: =SUMIF(RIC!D:D,BS!G92,RIC!F:F) -> 0 | Q92: =SUMIF(RIC!G:G,BS!G92,RIC!I:I) -> 0 | R92: =O92+Q92-P92 -> 4343550080 | S92: =SUMIF(RIT!H:H,BS!G92,RIT!J:J) -> 0 | T92: =SUMIF(RIT!K:K,BS!G92,RIT!M:M) -> 0 | U92: =R92+T92-S92 -> 4343550080 | V92: =SUMIF(지분법및기타!$D:$D,BS!G92,지분법및기타!$F:$F) -> 0 | W92: =SUMIF(지분법및기타!$G:$G,BS!G92,지분법및기타!$I:$I) -> 0 | X92: =U92+W92-V92 -> 4343550080 | Y92: 미지급금 | AA92: =X92-O92 -> 0
A93: 4 | E93: 예수금 | G93: 25400 | H93: =SUMIF(별도정산표!$G:$G,BS!G93,별도정산표!$E:$E) -> 85200680 | I93: =SUMIF(울트라팜_FS!$A:$A,BS!G93,울트라팜_FS!$D:$D) -> 0 | J93: =SUMIF(HK_BS!$A:$A,BS!G93,HK_BS!$K:$K) -> 0 | K93: =SUMIF(DHK_BS!$A:$A,BS!G93,DHK_BS!$K:$K) -> 0 | L93: =SUMIF(상해_BS!$A:$A,BS!G93,상해_BS!$K:$K) -> 0 | M93: =SUMIF(SG_BS!$A:$A,BS!G93,SG_BS!$K:$K) -> 0 | N93: =SUMIF(ATGC_BS!$H:$H,BS!G93,ATGC_BS!$I:$I) -> 0 | O93: =SUM(H93:N93) -> 85200680 | P93: =SUMIF(RIC!D:D,BS!G93,RIC!F:F) -> 0 | Q93: =SUMIF(RIC!G:G,BS!G93,RIC!I:I) -> 0 | R93: =O93+Q93-P93 -> 85200680 | S93: =SUMIF(RIT!H:H,BS!G93,RIT!J:J) -> 0 | T93: =SUMIF(RIT!K:K,BS!G93,RIT!M:M) -> 0 | U93: =R93+T93-S93 -> 85200680 | V93: =SUMIF(지분법및기타!$D:$D,BS!G93,지분법및기타!$F:$F) -> 0 | W93: =SUMIF(지분법및기타!$G:$G,BS!G93,지분법및기타!$I:$I) -> 0 | X93: =U93+W93-V93 -> 85200680 | Y93: 예수금 | AA93: =X93-O93 -> 0
A94: 4 | E94: 부가세예수금 | G94: 25500 | H94: =SUMIF(별도정산표!$G:$G,BS!G94,별도정산표!$E:$E) -> 0 | I94: =SUMIF(울트라팜_FS!$A:$A,BS!G94,울트라팜_FS!$D:$D) -> 0 | J94: =SUMIF(HK_BS!$A:$A,BS!G94,HK_BS!$K:$K) -> 0 | K94: =SUMIF(DHK_BS!$A:$A,BS!G94,DHK_BS!$K:$K) -> 0 | L94: =SUMIF(상해_BS!$A:$A,BS!G94,상해_BS!$K:$K) -> 0 | M94: =SUMIF(SG_BS!$A:$A,BS!G94,SG_BS!$K:$K) -> 0 | N94: =SUMIF(ATGC_BS!$H:$H,BS!G94,ATGC_BS!$I:$I) -> 0 | O94: =SUM(H94:N94) -> 0 | P94: =SUMIF(RIC!D:D,BS!G94,RIC!F:F) -> 0 | Q94: =SUMIF(RIC!G:G,BS!G94,RIC!I:I) -> 0 | R94: =O94+Q94-P94 -> 0 | S94: =SUMIF(RIT!H:H,BS!G94,RIT!J:J) -> 0 | T94: =SUMIF(RIT!K:K,BS!G94,RIT!M:M) -> 0 | U94: =R94+T94-S94 -> 0 | V94: =SUMIF(지분법및기타!$D:$D,BS!G94,지분법및기타!$F:$F) -> 0 | W94: =SUMIF(지분법및기타!$G:$G,BS!G94,지분법및기타!$I:$I) -> 0 | X94: =U94+W94-V94 -> 0 | Y94: 부가세예수금
A95: 4 | E95: 선수금 | G95: 25900 | H95: =SUMIF(별도정산표!$G:$G,BS!G95,별도정산표!$E:$E) -> 2215528322 | I95: =SUMIF(울트라팜_FS!$A:$A,BS!G95,울트라팜_FS!$D:$D) -> 0 | J95: =SUMIF(HK_BS!$A:$A,BS!G95,HK_BS!$K:$K) -> 65471929 | K95: =SUMIF(DHK_BS!$A:$A,BS!G95,DHK_BS!$K:$K) -> 173008 | L95: =SUMIF(상해_BS!$A:$A,BS!G95,상해_BS!$K:$K) -> 0 | M95: =SUMIF(SG_BS!$A:$A,BS!G95,SG_BS!$K:$K) -> 0 | N95: =SUMIF(ATGC_BS!$H:$H,BS!G95,ATGC_BS!$I:$I) -> 4747430895 | O95: =SUM(H95:N95) -> 7028604154 | P95: =SUMIF(RIC!D:D,BS!G95,RIC!F:F) -> 0 | Q95: =SUMIF(RIC!G:G,BS!G95,RIC!I:I) -> 0 | R95: =O95+Q95-P95 -> 7028604154 | S95: =SUMIF(RIT!H:H,BS!G95,RIT!J:J) -> 0 | T95: =SUMIF(RIT!K:K,BS!G95,RIT!M:M) -> 0 | U95: =R95+T95-S95 -> 7028604154 | V95: =SUMIF(지분법및기타!$D:$D,BS!G95,지분법및기타!$F:$F) -> 104971922 | W95: =SUMIF(지분법및기타!$G:$G,BS!G95,지분법및기타!$I:$I) -> 104971922 | X95: =U95+W95-V95 -> 7028604154 | Y95: 선수금 | AA95: =X95-O95 -> 0
E96: 환불부채 | G96: 25800 | H96: =SUMIF(별도정산표!$G:$G,BS!G96,별도정산표!$E:$E) -> 9395003 | I96: =SUMIF(울트라팜_FS!$A:$A,BS!G96,울트라팜_FS!$D:$D) -> 0 | J96: =SUMIF(HK_BS!$A:$A,BS!G96,HK_BS!$K:$K) -> 0 | K96: =SUMIF(DHK_BS!$A:$A,BS!G96,DHK_BS!$K:$K) -> 0 | L96: =SUMIF(상해_BS!$A:$A,BS!G96,상해_BS!$K:$K) -> 0 | M96: =SUMIF(SG_BS!$A:$A,BS!G96,SG_BS!$K:$K) -> 0 | N96: =SUMIF(ATGC_BS!$H:$H,BS!G96,ATGC_BS!$I:$I) -> 0 | O96: =SUM(H96:N96) -> 9395003 | P96: =SUMIF(RIC!D:D,BS!G96,RIC!F:F) -> 0 | Q96: =SUMIF(RIC!G:G,BS!G96,RIC!I:I) -> 0 | R96: =O96+Q96-P96 -> 9395003 | S96: =SUMIF(RIT!H:H,BS!G96,RIT!J:J) -> 0 | T96: =SUMIF(RIT!K:K,BS!G96,RIT!M:M) -> 0 | U96: =R96+T96-S96 -> 9395003 | V96: =SUMIF(지분법및기타!$D:$D,BS!G96,지분법및기타!$F:$F) -> 0 | W96: =SUMIF(지분법및기타!$G:$G,BS!G96,지분법및기타!$I:$I) -> 0 | X96: =U96+W96-V96 -> 9395003 | Y96: 환불부채 | AA96: =X96-O96 -> 0
A97: 4 | E97: 단기차입금 | G97: 26000 | H97: =SUMIF(별도정산표!$G:$G,BS!G97,별도정산표!$E:$E) -> 1120000000 | I97: =SUMIF(울트라팜_FS!$A:$A,BS!G97,울트라팜_FS!$D:$D) -> 0 | J97: =SUMIF(HK_BS!$A:$A,BS!G97,HK_BS!$K:$K) -> 0 | K97: =SUMIF(DHK_BS!$A:$A,BS!G97,DHK_BS!$K:$K) -> 0 | L97: =SUMIF(상해_BS!$A:$A,BS!G97,상해_BS!$K:$K) -> 0 | M97: =SUMIF(SG_BS!$A:$A,BS!G97,SG_BS!$K:$K) -> 0 | N97: =SUMIF(ATGC_BS!$H:$H,BS!G97,ATGC_BS!$I:$I) -> 0 | O97: =SUM(H97:N97) -> 1120000000 | P97: =SUMIF(RIC!D:D,BS!G97,RIC!F:F) -> 0 | Q97: =SUMIF(RIC!G:G,BS!G97,RIC!I:I) -> 0 | R97: =O97+Q97-P97 -> 1120000000 | S97: =SUMIF(RIT!H:H,BS!G97,RIT!J:J) -> 0 | T97: =SUMIF(RIT!K:K,BS!G97,RIT!M:M) -> 0 | U97: =R97+T97-S97 -> 1120000000 | V97: =SUMIF(지분법및기타!$D:$D,BS!G97,지분법및기타!$F:$F) -> 0 | W97: =SUMIF(지분법및기타!$G:$G,BS!G97,지분법및기타!$I:$I) -> 0 | X97: =U97+W97-V97 -> 1120000000 | Y97: 단기차입금 | AA97: =X97-O97 -> 0
A98: 4 | E98: 미지급비용 | G98: 26200 | H98: =SUMIF(별도정산표!$G:$G,BS!G98,별도정산표!$E:$E) -> 2552781060 | I98: =SUMIF(울트라팜_FS!$A:$A,BS!G98,울트라팜_FS!$D:$D) -> 0 | J98: =SUMIF(HK_BS!$A:$A,BS!G98,HK_BS!$K:$K) -> 54571733 | K98: =SUMIF(DHK_BS!$A:$A,BS!G98,DHK_BS!$K:$K) -> 9141900 | L98: =SUMIF(상해_BS!$A:$A,BS!G98,상해_BS!$K:$K) -> 0 | M98: =SUMIF(SG_BS!$A:$A,BS!G98,SG_BS!$K:$K) -> 0 | N98: =SUMIF(ATGC_BS!$H:$H,BS!G98,ATGC_BS!$I:$I) -> 143171601 | O98: =SUM(H98:N98) -> 2759666294 | P98: =SUMIF(RIC!D:D,BS!G98,RIC!F:F) -> 0 | Q98: =SUMIF(RIC!G:G,BS!G98,RIC!I:I) -> 0 | R98: =O98+Q98-P98 -> 2759666294 | S98: =SUMIF(RIT!H:H,BS!G98,RIT!J:J) -> 0 | T98: =SUMIF(RIT!K:K,BS!G98,RIT!M:M) -> 0 | U98: =R98+T98-S98 -> 2759666294 | V98: =SUMIF(지분법및기타!$D:$D,BS!G98,지분법및기타!$F:$F) -> 0 | W98: =SUMIF(지분법및기타!$G:$G,BS!G98,지분법및기타!$I:$I) -> 0 | X98: =U98+W98-V98 -> 2759666294 | Y98: 미지급비용 | AA98: =X98-O98 -> 0
A99: 4 | E99: 미지급법인세 | G99: 27500 | H99: =SUMIF(별도정산표!$G:$G,BS!G99,별도정산표!$E:$E) -> 0 | I99: =SUMIF(울트라팜_FS!$A:$A,BS!G99,울트라팜_FS!$D:$D) -> 0 | J99: =SUMIF(HK_BS!$A:$A,BS!G99,HK_BS!$K:$K) -> 0 | K99: =SUMIF(DHK_BS!$A:$A,BS!G99,DHK_BS!$K:$K) -> 0 | L99: =SUMIF(상해_BS!$A:$A,BS!G99,상해_BS!$K:$K) -> 0 | M99: =SUMIF(SG_BS!$A:$A,BS!G99,SG_BS!$K:$K) -> 0 | N99: =SUMIF(ATGC_BS!$H:$H,BS!G99,ATGC_BS!$I:$I) -> 0 | O99: =SUM(H99:N99) -> 0 | P99: =SUMIF(RIC!D:D,BS!G99,RIC!F:F) -> 0 | Q99: =SUMIF(RIC!G:G,BS!G99,RIC!I:I) -> 0 | R99: =O99+Q99-P99 -> 0 | S99: =SUMIF(RIT!H:H,BS!G99,RIT!J:J) -> 0 | T99: =SUMIF(RIT!K:K,BS!G99,RIT!M:M) -> 0 | U99: =R99+T99-S99 -> 0 | V99: =SUMIF(지분법및기타!$D:$D,BS!G99,지분법및기타!$F:$F) -> 0 | W99: =SUMIF(지분법및기타!$G:$G,BS!G99,지분법및기타!$I:$I) -> 0 | X99: =U99+W99-V99 -> 0 | Y99: 당기법인세부채
A100: 4 | E100: 반품충당부채 | G100: 28100 | H100: =SUMIF(별도정산표!$G:$G,BS!G100,별도정산표!$E:$E) -> 0 | I100: =SUMIF(울트라팜_FS!$A:$A,BS!G100,울트라팜_FS!$D:$D) -> 0 | J100: =SUMIF(HK_BS!$A:$A,BS!G100,HK_BS!$K:$K) -> 0 | K100: =SUMIF(DHK_BS!$A:$A,BS!G100,DHK_BS!$K:$K) -> 0 | L100: =SUMIF(상해_BS!$A:$A,BS!G100,상해_BS!$K:$K) -> 0 | M100: =SUMIF(SG_BS!$A:$A,BS!G100,SG_BS!$K:$K) -> 0 | N100: =SUMIF(ATGC_BS!$H:$H,BS!G100,ATGC_BS!$I:$I) -> 0 | O100: =SUM(H100:N100) -> 0 | P100: =SUMIF(RIC!D:D,BS!G100,RIC!F:F) -> 0 | Q100: =SUMIF(RIC!G:G,BS!G100,RIC!I:I) -> 0 | R100: =O100+Q100-P100 -> 0 | S100: =SUMIF(RIT!H:H,BS!G100,RIT!J:J) -> 0 | T100: =SUMIF(RIT!K:K,BS!G100,RIT!M:M) -> 0 | U100: =R100+T100-S100 -> 0 | V100: =SUMIF(지분법및기타!$D:$D,BS!G100,지분법및기타!$F:$F) -> 0 | W100: =SUMIF(지분법및기타!$G:$G,BS!G100,지분법및기타!$I:$I) -> 0 | X100: =U100+W100-V100 -> 0 | Y100: 반품충당부채
A101: 4 | E101: 유동성장기차입금 | G101: 28200 | H101: =SUMIF(별도정산표!$G:$G,BS!G101,별도정산표!$E:$E) -> 0 | I101: =SUMIF(울트라팜_FS!$A:$A,BS!G101,울트라팜_FS!$D:$D) -> 0 | J101: =SUMIF(HK_BS!$A:$A,BS!G101,HK_BS!$K:$K) -> 0 | K101: =SUMIF(DHK_BS!$A:$A,BS!G101,DHK_BS!$K:$K) -> 0 | L101: =SUMIF(상해_BS!$A:$A,BS!G101,상해_BS!$K:$K) -> 0 | M101: =SUMIF(SG_BS!$A:$A,BS!G101,SG_BS!$K:$K) -> 0 | N101: =SUMIF(ATGC_BS!$H:$H,BS!G101,ATGC_BS!$I:$I) -> 0 | O101: =SUM(H101:N101) -> 0 | P101: =SUMIF(RIC!D:D,BS!G101,RIC!F:F) -> 0 | Q101: =SUMIF(RIC!G:G,BS!G101,RIC!I:I) -> 0 | R101: =O101+Q101-P101 -> 0 | S101: =SUMIF(RIT!H:H,BS!G101,RIT!J:J) -> 0 | T101: =SUMIF(RIT!K:K,BS!G101,RIT!M:M) -> 0 | U101: =R101+T101-S101 -> 0 | V101: =SUMIF(지분법및기타!$D:$D,BS!G101,지분법및기타!$F:$F) -> 0 | W101: =SUMIF(지분법및기타!$G:$G,BS!G101,지분법및기타!$I:$I) -> 0 | X101: =U101+W101-V101 -> 0 | Y101: 유동성장기차입금 | AA101: =X101-O101 -> 0
...

Sheet PL
L1: 62335406
B2: Level | C2: 계정과목명(Account) | H2: Code | I2: 울트라브이 | J2: 울트라브이팜 | K2: ULTRA V HONG KONG LIMITED | L2: DERMASTER HONG KONG LIMITED | M2: ULTRA V SHANGHAI LIMITED | N2: ULTRA V (SG) PTE.LTD (24년 설립) | O2: ATGC | P2: 단순합산 | Q2: 투자자본상계 | T2: 내부거래제거 | W2: 지분법, 법인세, 기타조정 | Z2: 2019년 반기 | AA2: 2019년 3개월 | AB2: 공시용mapping | AC2: 공시용 Mapping 소분류
Q3: Dr | R3: Cr | S3: K-IFRS | T3: Dr | U3: Cr | V3: K-IFRS | W3: Dr | X3: Cr | Y3: K-IFRS
AD4: 성격별분류 구분
B5: 1 | C5: 손익
B6: 2 | D6: 매출액 | I6: =I7 -> 8288170687 | J6: =J7 -> 0 | K6: =K7 -> 807627666 | L6: =L7 -> 110521930 | M6: =M7 -> 0 | N6: =N7 -> 0 | O6: =O7 -> 0 | P6: =P7 -> 9206320283 | S6: =S7 -> 9206320283 | V6: =V7 -> 8812244469 | Y6: =Y7 -> 8812244469 | Z6: =Z7 -> 0 | AA6: =AA7 -> 0 | AD6: =P6-Y6 -> 394075814 | AF6: =Y6-P6 -> -394075814
B7: 3 | E7: 매출액 | I7: =SUM(I8:I12) -> 8288170687 | J7: =SUM(J8:J12) -> 0 | K7: =SUM(K8:K12) -> 807627666 | L7: =SUM(L8:L12) -> 110521930 | M7: =SUM(M8:M12) -> 0 | N7: =SUM(N8:N12) -> 0 | O7: =SUM(O8:O12) -> 0 | P7: =P8+P9+P11+P12+P10 -> 9206320283 | S7: =S8+S9+S11+S12+S10 -> 9206320283 | V7: =V8+V9+V11+V12+V10 -> 8812244469 | Y7: =Y8+Y9+Y11+Y12+Y10 -> 8812244469 | Z7: =Z8+Z9+Z11+Z12 -> 0 | AA7: =AA8+AA9+AA11+AA12 -> 0 | AF7: =Y7-P7 -> -394075814
B8: 4 | F8: 상품매출 | H8: 40100 | I8: =SUMIF(별도정산표!$G:$G,PL!H8,별도정산표!$E:$E) -> 278070981 | J8: =SUMIF(울트라팜_FS!$H:$H,PL!H8,울트라팜_FS!$J:$J) -> 0 | K8: =SUMIF(HK_PL!$A:$A,PL!H8,HK_PL!$K:$K) -> 807627666 | L8: =SUMIF(DHK_PL!$A:$A,PL!H8,DHK_PL!$K:$K) -> 110521930 | M8: =SUMIF(상해_PL!$A:$A,PL!H8,상해_PL!$K:$K) -> 0 | N8: =SUMIF(SG_PL!$A:$A,PL!H8,SG_PL!$K:$K) -> 0 | P8: =SUM(I8:O8) -> 1196220577 | Q8: =SUMIF(RIC!$D:$D,PL!H8,RIC!F:F) -> 0 | R8: =SUMIF(RIC!G:G,PL!H8,RIC!I:I) -> 0 | S8: =P8+R8-Q8 -> 1196220577 | T8: =SUMIF(RIT!H:H,PL!H8,RIT!J:J) -> 15093677 | U8: =SUMIF(RIT!K:K,PL!H8,RIT!M:M) -> 0 | V8: =S8+U8-T8 -> 1181126900 | W8: =SUMIF(지분법및기타!$D:$D,PL!H8,지분법및기타!$F:$F) -> 0 | X8: =SUMIF(지분법및기타!$G:$G,PL!H8,지분법및기타!$I:$I) -> 0 | Y8: =V8+X8-W8 -> 1181126900 | AB8: 매출 | AC8: 상품매출 | AF8: =Y8-P8 -> -15093677
B9: 4 | F9: 제품매출 | H9: 40400 | I9: =SUMIF(별도정산표!$G:$G,PL!H9,별도정산표!$E:$E) -> 7974892686 | J9: =SUMIF(울트라팜_FS!$H:$H,PL!H9,울트라팜_FS!$J:$J) -> 0 | K9: =SUMIF(HK_PL!$A:$A,PL!H9,HK_PL!$K:$K) -> 0 | L9: =SUMIF(DHK_PL!$A:$A,PL!H9,DHK_PL!$K:$K) -> 0 | M9: =SUMIF(상해_PL!$A:$A,PL!H9,상해_PL!$K:$K) -> 0 | N9: =SUMIF(SG_PL!$A:$A,PL!H9,SG_PL!$K:$K) -> 0 | P9: =SUM(I9:O9) -> 7974892686 | Q9: =SUMIF(RIC!$D:$D,PL!H9,RIC!F:F) -> 0 | R9: =SUMIF(RIC!G:G,PL!H9,RIC!I:I) -> 0 | S9: =P9+R9-Q9 -> 7974892686 | T9: =SUMIF(RIT!H:H,PL!H9,RIT!J:J) -> 378982137 | U9: =SUMIF(RIT!K:K,PL!H9,RIT!M:M) -> 0 | V9: =S9+U9-T9 -> 7595910549 | W9: =SUMIF(지분법및기타!$D:$D,PL!H9,지분법및기타!$F:$F) -> 0 | X9: =SUMIF(지분법및기타!$G:$G,PL!H9,지분법및기타!$I:$I) -> 0 | Y9: =V9+X9-W9 -> 7595910549 | AB9: 매출 | AC9: 제품매출 | AF9: =Y9-P9 -> -378982137
F10: 서비스매출 | H10: 40500 | I10: =SUMIF(별도정산표!$G:$G,PL!H10,별도정산표!$E:$E) -> 0 | J10: =SUMIF(울트라팜_FS!$H:$H,PL!H10,울트라팜_FS!$J:$J) -> 0 | K10: =SUMIF(HK_PL!$A:$A,PL!H10,HK_PL!$K:$K) -> 0 | L10: =SUMIF(DHK_PL!$A:$A,PL!H10,DHK_PL!$K:$K) -> 0 | M10: =SUMIF(상해_PL!$A:$A,PL!H10,상해_PL!$K:$K) -> 0 | N10: =SUMIF(SG_PL!$A:$A,PL!H10,SG_PL!$K:$K) -> 0 | P10: =SUM(I10:O10) -> 0 | Q10: =SUMIF(RIC!$D:$D,PL!H10,RIC!F:F) -> 0 | R10: =SUMIF(RIC!G:G,PL!H10,RIC!I:I) -> 0 | S10: =P10+R10-Q10 -> 0 | T10: =SUMIF(RIT!H:H,PL!H10,RIT!J:J) -> 0 | U10: =SUMIF(RIT!K:K,PL!H10,RIT!M:M) -> 0 | V10: =S10+U10-T10 -> 0 | W10: =SUMIF(지분법및기타!$D:$D,PL!H10,지분법및기타!$F:$F) -> 0 | X10: =SUMIF(지분법및기타!$G:$G,PL!H10,지분법및기타!$I:$I) -> 0 | Y10: =V10+X10-W10 -> 0 | AB10: 매출 | AC10: 서비스매출
B11: 4 | F11: 식음료매출 | H11: 40600 | I11: =SUMIF(별도정산표!$G:$G,PL!H11,별도정산표!$E:$E) -> 35207020 | J11: =SUMIF(울트라팜_FS!$H:$H,PL!H11,울트라팜_FS!$J:$J) -> 0 | K11: =SUMIF(HK_PL!$A:$A,PL!H11,HK_PL!$K:$K) -> 0 | L11: =SUMIF(DHK_PL!$A:$A,PL!H11,DHK_PL!$K:$K) -> 0 | M11: =SUMIF(상해_PL!$A:$A,PL!H11,상해_PL!$K:$K) -> 0 | N11: =SUMIF(SG_PL!$A:$A,PL!H11,SG_PL!$K:$K) -> 0 | P11: =SUM(I11:O11) -> 35207020 | Q11: =SUMIF(RIC!$D:$D,PL!H11,RIC!F:F) -> 0 | R11: =SUMIF(RIC!G:G,PL!H11,RIC!I:I) -> 0 | S11: =P11+R11-Q11 -> 35207020 | T11: =SUMIF(RIT!H:H,PL!H11,RIT!J:J) -> 0 | U11: =SUMIF(RIT!K:K,PL!H11,RIT!M:M) -> 0 | V11: =S11+U11-T11 -> 35207020 | W11: =SUMIF(지분법및기타!$D:$D,PL!H11,지분법및기타!$F:$F) -> 0 | X11: =SUMIF(지분법및기타!$G:$G,PL!H11,지분법및기타!$I:$I) -> 0 | Y11: =V11+X11-W11 -> 35207020 | AB11: 매출 | AC11: 식음료매출 | AF11: =Y11-P11 -> 0
B12: 4 | F12: 미사용 | I12: =SUMIF(별도정산표!$G:$G,PL!H12,별도정산표!$E:$E) -> 0 | J12: =SUMIF(울트라팜_FS!$H:$H,PL!H12,울트라팜_FS!$J:$J) -> 0 | K12: =SUMIF(HK_PL!$A:$A,PL!H12,HK_PL!$K:$K) -> 0 | L12: =SUMIF(DHK_PL!$A:$A,PL!H12,DHK_PL!$K:$K) -> 0 | M12: =SUMIF(상해_PL!$A:$A,PL!H12,상해_PL!$K:$K) -> 0 | N12: =SUMIF(SG_PL!$A:$A,PL!H12,SG_PL!$K:$K) -> 0 | P12: =SUM(I12:O12) -> 0 | Q12: =SUMIF(RIC!$D:$D,PL!H12,RIC!F:F) -> 0 | R12: =SUMIF(RIC!G:G,PL!H12,RIC!I:I) -> 0 | S12: =P12+R12-Q12 -> 0 | T12: =SUMIF(RIT!H:H,PL!H12,RIT!J:J) -> 0 | U12: =SUMIF(RIT!K:K,PL!H12,RIT!M:M) -> 0 | V12: =S12+U12-T12 -> 0 | W12: =SUMIF(지분법및기타!$D:$D,PL!H12,지분법및기타!$F:$F) -> 0 | X12: =SUMIF(지분법및기타!$G:$G,PL!H12,지분법및기타!$I:$I) -> 0 | Y12: =V12+X12-W12 -> 0 | AB12: 매출
B13: 2 | D13: 매출원가 | I13: =I14 -> 3596633522 | J13: =J14 -> 0 | K13: =K14 -> 378103308 | L13: =L14 -> 24568846 | M13: =M14 -> 0 | N13: =N14 -> 0 | O13: =O14 -> 0 | P13: =P14 -> 3999305676 | S13: =S14 -> 3999305676 | V13: =V14 -> 3634217621 | Y13: =Y14 -> 3634217621 | Z13: =Z14 -> 0 | AA13: =AA14 -> 0 | AD13: =P13-Y13 -> 365088055 | AF13: =Y13-P13 -> -365088055
B14: 3 | E14: 매출원가 | I14: =SUM(I15,I22,I29,I35) -> 3596633522 | J14: =SUM(J15,J22,J29,J35) -> 0 | K14: =SUM(K15,K22,K29,K35) -> 378103308 | L14: =SUM(L15,L22,L29,L35) -> 24568846 | M14: =SUM(M15,M22,M29,M35) -> 0 | N14: =SUM(N15,N22,N29,N35) -> 0 | O14: =SUM(O15:O41) -> 0 | P14: =SUM(P15,P22,P29,P35) -> 3999305676 | S14: =SUM(S15,S22,S29,S35) -> 3999305676 | V14: =SUM(V15,V22,V29,V35) -> 3634217621 | Y14: =SUM(Y15,Y22,Y29,Y35) -> 3634217621 | AD14: =AD6-AD13 -> 28987759 | AF14: =Y14-P14 -> -365088055
B15: 4 | F15: 제품매출원가 | I15: =SUM(I18:I20)-I21 -> 3389356072 | J15: =SUM(J18:J20)-J21 -> 0 | K15: =SUM(K18:K20)-K21 -> 0 | L15: =SUM(L18:L20)-L21 -> 0 | M15: =SUM(M18:M20)-M21 -> 0 | N15: =SUM(N18:N20)-N21 -> 0 | P15: =SUM(I15:O15) -> 3389356072 | Q15: =SUMIF(RIC!$D:$D,PL!H15,RIC!F:F) -> 0 | R15: =SUMIF(RIC!G:G,PL!H15,RIC!I:I) -> 0 | S15: =S18+S19+S20-S21 -> 3389356072 | T15: =SUMIF(RIT!H:H,PL!H15,RIT!J:J) -> 0 | U15: =SUMIF(RIT!K:K,PL!H15,RIT!M:M) -> 0 | V15: =V18+V19+V20-V21 -> 3389356072 | W15: =SUMIF(지분법및기타!$D:$D,PL!H15,지분법및기타!$F:$F) -> 0 | X15: =SUMIF(지분법및기타!$G:$G,PL!H15,지분법및기타!$I:$I) -> 0 | Y15: =Y18+Y19+Y20-Y21 -> 3389356072 | AB15: 매출원가 | AC15: 제품매출원가 | AD15: =RIT!J99-RIT!M85+RIT!M29 -> 30205388 | AF15: =Y15-P15 -> 0
F16: 기초제품재고액 | H16: 45100 | I16: =SUMIF(별도정산표!$G:$G,PL!H16,별도정산표!$E:$E) -> 2349819825 | J16: =SUMIF(울트라팜_FS!$H:$H,PL!H16,울트라팜_FS!$J:$J) -> 0 | K16: =SUMIF(HK_PL!$A:$A,PL!H16,HK_PL!$K:$K) -> 0 | L16: =SUMIF(DHK_PL!$A:$A,PL!H16,DHK_PL!$K:$K) -> 0 | M16: =SUMIF(상해_PL!$A:$A,PL!H16,상해_PL!$K:$K) -> 0 | N16: =SUMIF(SG_PL!$A:$A,PL!H16,SG_PL!$K:$K) -> 0 | P16: =SUM(I16:O16) -> 2349819825 | Q16: =SUMIF(RIC!$D:$D,PL!H16,RIC!F:F) -> 0 | R16: =SUMIF(RIC!G:G,PL!H16,RIC!I:I) -> 0 | S16: =P16+Q16-R16 -> 2349819825 | T16: =SUMIF(RIT!H:H,PL!H16,RIT!J:J) -> 0 | U16: =SUMIF(RIT!K:K,PL!H16,RIT!M:M) -> 0 | V16: =S16+T16-U16 -> 2349819825 | W16: =SUMIF(지분법및기타!$D:$D,PL!H16,지분법및기타!$F:$F) -> 0 | X16: =SUMIF(지분법및기타!$G:$G,PL!H16,지분법및기타!$I:$I) -> 0 | Y16: =V16+W16-X16 -> 2349819825 | AB16: 매출원가 | AC16: 기초제품재고액 | AD16: =AD14-AD15 -> -1217629 | AF16: =Y16-P16 -> 0
F17: 당기제품제조원가 | H17: 45200 | I17: =SUMIF(별도정산표!$G:$G,PL!H17,별도정산표!$E:$E) -> 3476800819 | J17: =SUMIF(울트라팜_FS!$H:$H,PL!H17,울트라팜_FS!$J:$J) -> 0 | K17: =SUMIF(HK_PL!$A:$A,PL!H17,HK_PL!$K:$K) -> 0 | L17: =SUMIF(DHK_PL!$A:$A,PL!H17,DHK_PL!$K:$K) -> 0 | M17: =SUMIF(상해_PL!$A:$A,PL!H17,상해_PL!$K:$K) -> 0 | N17: =SUMIF(SG_PL!$A:$A,PL!H17,SG_PL!$K:$K) -> 0 | P17: =SUM(I17:O17) -> 3476800819 | Q17: =SUMIF(RIC!$D:$D,PL!H17,RIC!F:F) -> 0 | R17: =SUMIF(RIC!G:G,PL!H17,RIC!I:I) -> 0 | S17: =P17+Q17-R17 -> 3476800819 | T17: =SUMIF(RIT!H:H,PL!H17,RIT!J:J) -> 0 | U17: =SUMIF(RIT!K:K,PL!H17,RIT!M:M) -> 0 | V17: =S17+T17-U17 -> 3476800819 | W17: =SUMIF(지분법및기타!$D:$D,PL!H17,지분법및기타!$F:$F) -> 0 | X17: =SUMIF(지분법및기타!$G:$G,PL!H17,지분법및기타!$I:$I) -> 0 | Y17: =V17+W17-X17 -> 3476800819 | AB17: 매출원가 | AC17: 당기제품제조원가 | AF17: =Y17-P17 -> 0
F18: 계(제품) | I18: =SUM(I16:I17) -> 5826620644 | J18: =SUM(J16:J17) -> 0 | K18: =SUM(K16:K17) -> 0 | L18: =SUM(L16:L17) -> 0 | M18: =SUM(M16:M17) -> 0 | N18: =SUM(N16:N17) -> 0 | P18: =SUM(I18:O18) -> 5826620644 | Q18: =SUMIF(RIC!$D:$D,PL!H18,RIC!F:F) -> 0 | R18: =SUMIF(RIC!G:G,PL!H18,RIC!I:I) -> 0 | S18: =SUM(S16:S17) -> 5826620644 | T18: =SUMIF(RIT!H:H,PL!H18,RIT!J:J) -> 0 | U18: =SUMIF(RIT!K:K,PL!H18,RIT!M:M) -> 0 | V18: =SUM(V16:V17) -> 5826620644 | W18: =SUMIF(지분법및기타!$D:$D,PL!H18,지분법및기타!$F:$F) -> 0 | X18: =SUMIF(지분법및기타!$G:$G,PL!H18,지분법및기타!$I:$I) -> 0 | Y18: =SUM(Y16:Y17) -> 5826620644 | AB18: 매출원가 | AC18: 계(제품) | AF18: =Y18-P18 -> 0
F19: 타계정대체(제품) | H19: 45300 | I19: =SUMIF(별도정산표!$G:$G,PL!H19,별도정산표!$E:$E) -> -5296679 | J19: =SUMIF(울트라팜_FS!$H:$H,PL!H19,울트라팜_FS!$J:$J) -> 0 | K19: =SUMIF(HK_PL!$A:$A,PL!H19,HK_PL!$K:$K) -> 0 | L19: =SUMIF(DHK_PL!$A:$A,PL!H19,DHK_PL!$K:$K) -> 0 | M19: =SUMIF(상해_PL!$A:$A,PL!H19,상해_PL!$K:$K) -> 0 | N19: =SUMIF(SG_PL!$A:$A,PL!H19,SG_PL!$K:$K) -> 0 | P19: =SUM(I19:O19) -> -5296679 | Q19: =SUMIF(RIC!$D:$D,PL!H19,RIC!F:F) -> 0 | R19: =SUMIF(RIC!G:G,PL!H19,RIC!I:I) -> 0 | S19: =P19+Q19-R19 -> -5296679 | T19: =SUMIF(RIT!H:H,PL!H19,RIT!J:J) -> 0 | U19: =SUMIF(RIT!K:K,PL!H19,RIT!M:M) -> 0 | V19: =S19+T19-U19 -> -5296679 | W19: =SUMIF(지분법및기타!$D:$D,PL!H19,지분법및기타!$F:$F) -> 0 | X19: =SUMIF(지분법및기타!$G:$G,PL!H19,지분법및기타!$I:$I) -> 0 | Y19: =V19+W19-X19 -> -5296679 | AB19: 매출원가 | AC19: 타계정대체(제품) | AF19: =Y19-P19 -> 0
F20: 재고자산평가 | H20: 45600 | I20: =SUMIF(별도정산표!$G:$G,PL!H20,별도정산표!$E:$E) -> 102749779 | J20: =SUMIF(울트라팜_FS!$H:$H,PL!H20,울트라팜_FS!$J:$J) -> 0 | K20: =SUMIF(HK_PL!$A:$A,PL!H20,HK_PL!$K:$K) -> 0 | L20: =SUMIF(DHK_PL!$A:$A,PL!H20,DHK_PL!$K:$K) -> 0 | M20: =SUMIF(상해_PL!$A:$A,PL!H20,상해_PL!$K:$K) -> 0 | N20: =SUMIF(SG_PL!$A:$A,PL!H20,SG_PL!$K:$K) -> 0 | P20: =SUM(I20:O20) -> 102749779 | Q20: =SUMIF(RIC!$D:$D,PL!H20,RIC!F:F) -> 0 | R20: =SUMIF(RIC!G:G,PL!H20,RIC!I:I) -> 0 | S20: =P20+Q20-R20 -> 102749779 | T20: =SUMIF(RIT!H:H,PL!H20,RIT!J:J) -> 0 | U20: =SUMIF(RIT!K:K,PL!H20,RIT!M:M) -> 0 | V20: =S20+T20-U20 -> 102749779 | W20: =SUMIF(지분법및기타!$D:$D,PL!H20,지분법및기타!$F:$F) -> 0 | X20: =SUMIF(지분법및기타!$G:$G,PL!H20,지분법및기타!$I:$I) -> 0 | Y20: =V20+W20-X20 -> 102749779 | AB20: 매출원가 | AC20: 재고자산평가(제품) | AF20: =Y20-P20 -> 0
F21: 기말제품재고액 | H21: 45400 | I21: =SUMIF(별도정산표!$G:$G,PL!H21,별도정산표!$E:$E) -> 2534717672 | J21: =SUMIF(울트라팜_FS!$H:$H,PL!H21,울트라팜_FS!$J:$J) -> 0 | K21: =SUMIF(HK_PL!$A:$A,PL!H21,HK_PL!$K:$K) -> 0 | L21: =SUMIF(DHK_PL!$A:$A,PL!H21,DHK_PL!$K:$K) -> 0 | M21: =SUMIF(상해_PL!$A:$A,PL!H21,상해_PL!$K:$K) -> 0 | N21: =SUMIF(SG_PL!$A:$A,PL!H21,SG_PL!$K:$K) -> 0 | P21: =SUM(I21:O21) -> 2534717672 | Q21: =SUMIF(RIC!$D:$D,PL!H21,RIC!F:F) -> 0 | R21: =SUMIF(RIC!G:G,PL!H21,RIC!I:I) -> 0 | S21: =P21+Q21-R21 -> 2534717672 | T21: =SUMIF(RIT!H:H,PL!H21,RIT!J:J) -> 0 | U21: =SUMIF(RIT!K:K,PL!H21,RIT!M:M) -> 0 | V21: =S21+T21-U21 -> 2534717672 | W21: =SUMIF(지분법및기타!$D:$D,PL!H21,지분법및기타!$F:$F) -> 0 | X21: =SUMIF(지분법및기타!$G:$G,PL!H21,지분법및기타!$I:$I) -> 0 | Y21: =V21+W21-X21 -> 2534717672 | AB21: 매출원가 | AC21: 기말제품재고액 | AF21: =Y21-P21 -> 0
